Workbook

Sheet Expenses
A1: Year | B1: Month | C1: ID | D1: Date | E1: Category | F1: Description | G1: Amount | H1: Paid? | I1: Mode | J1: Payment Date | K1: Rating | L1: Vendor Category | M1: Remarks
C2: 47 | D2: 45722 | E2: LOCAL PURCHASE | F2: Temprature controller | G2: 2710 | H2: TRUE | I2: Cash | K2: 5
C3: 228 | D3: 45736 | E3: MARKETING | F3: FOOD HUNTER SABU | G3: 25000 | H3: TRUE | I3: Cash | K3: 5
C4: 143 | D4: 45738 | E4: GREENZ VEGGIES | F4: veggies | G4: 2253 | H4: TRUE | I4: UPI | K4: 5
C5: 50 | D5: 45739 | E5: T3 SPECIALITY | F5: prawns | G5: 1160 | H5: TRUE | I5: Bank | K5: 5
C6: 51 | D6: 45741 | E6: TRIO MEATS KTM | F6: Oregano | G6: 1826 | H6: TRUE | I6: Bank | K6: 5
C7: 64 | D7: 45741 | E7: MATHA MEATS | F7: pork ribs | G7: 1805 | H7: TRUE | I7: Bank | K7: 5
C8: 144 | D8: 45741 | E8: Greenz Veggies | F8: veggies | G8: 558 | H8: TRUE | I8: UPI | K8: 5
C9: 53 | D9: 45742 | E9: MATHA MEATS | F9: Beef | G9: 720 | H9: TRUE | I9: Bank | K9: 5
C10: 145 | D10: 45742 | E10: Greenz Veggies | F10: veggies | G10: 1529 | H10: TRUE | I10: UPI | K10: 5
C11: 146 | D11: 45742 | E11: Greenz Veggies | F11: veggies | G11: 85 | H11: TRUE | I11: UPI | K11: 5
C12: 334 | D12: 45742 | E12: PULI WOOD CHINGAVANAM | F12: PULI WOOD CHINGAVANAM | G12: 19740 | H12: TRUE | I12: UPI | K12: 0
C13: 708 | D13: 45742 | E13: TEL PHONE | F13: AIRTEL PHILOS KAKKANAD | G13: 250 | H13: TRUE | I13: UPI | K13: 0
... C31: 148 | D31: 45748 | E31: Greenz Veggies | F31: veggies | G31: 2135 | H31: TRUE | I31: UPI | K31: 5
C32: 254 | D32: 45748 | E32: LULU KOCHI | F32: salmon /avocado | G32: 2807 | H32: TRUE | I32: UPI
C33: 63 | D33: 45749 | E33: MATHA MEATS | F33: BEEF | G33: 2180 | H33: TRUE | I33: Bank | K33: 5
C34: 65 | D34: 45750 | E34: UNITED TRADERS KTM | F34: wheet flour | G34: 2943 | H34: TRUE | I34: UPI | K34: 5
C35: 66 | D35: 45750 | E35: LOCAL PURCHASE | F35: floor brush | G35: 1307 | H35: TRUE | I35: Cash | K35: 5
C36: 8 | D36: 45751 | E36: ARACKAL BHARATH GAS | F36: GAS | G36: 1720 | H36: TRUE | I36: Bank | K36: 5
C37: 67 | D37: 45751 | E37: T3 SPECIALITY | F37: strawbery fruity | G37: 3409 | H37: TRUE | I37: Bank | K37: 5
C38: 68 | D38: 45752 | E38: POLAR ICE CUBES | F38: ice cube | G38: 350 | H38: TRUE | I38: UPI | K38: 5
C39: 69 | D39: 45752 | E39: MATHA MEATS | F39: Chicken | G39: 2238 | H39: TRUE | I39: Bank | K39: 5
C40: 70 | D40: 45752 | E40: T3 SPECIALITY | F40: CHEESE | G40: 5880 | H40: TRUE | I40: Bank | K40: 5
C41: 71 | D41: 45752 | E41: T3 SPECIALITY | F41: CHEESE | G41: 3506 | H41: TRUE | I41: Bank | K41: 5
C42: 72 | D42: 45752 | E42: LOCAL PURCHASE | F42: soda | G42: 600 | H42: TRUE | I42: Bank | K42: 5
C43: 225 | D43: 45752 | E43: STAFF SALARY | F43: SALARY MARCH (10 DAYS) | G43: 48000 | H43: TRUE | I43: Bank | K43: 5
C44: 255 | D44: 45752 | E44: LULU KOCHI | F44: salmon /avocado | G44: 2345 | H44: TRUE | I44: UPI
C45: 73 | D45: 45754 | E45: GROW GREENS | F45: Sunflower | G45: 300 | H45: TRUE | I45: UPI | K45: 5
C46: 74 | D46: 45754 | E46: T3 SPECIALITY | F46: peperoni | G46: 8439 | H46: TRUE | I46: Bank | K46: 5
C47: 147 | D47: 45754 | E47: Greenz Veggies | F47: veggies | G47: 1718.5 | H47: TRUE | I47: UPI | K47: 5
C48: 75 | D48: 45755 | E48: T3 SPECIALITY | F48: bufflo cut | G48: 2828 | H48: TRUE | I48: Bank | K48: 5
C49: 76 | D49: 45755 | E49: MATHA MEATS | F49: pork ribs | G49: 4734 | H49: TRUE | I49: Bank | K49: 5
C50: 77 | D50: 45755 | E50: POLAR ICE CUBES | F50: ice cube | G50: 140 | H50: TRUE | I50: UPI | K50: 5
C51: 78 | D51: 45756 | E51: KSEB | F51: kseb | G51: 7802 | H51: TRUE | I51: UPI | K51: 5
C52: 79 | D52: 45756 | E52: WATER SUPPLY | F52: 2000L | G52: 800 | H52: TRUE | I52: UPI | K52: 5
C53: 80 | D53: 45756 | E53: LERA COCA COLA | F53: sprite | G53: 3290 | H53: TRUE | I53: Bank | K53: 5
C54: 81 | D54: 45756 | E54: T3 SPECIALITY | F54: fruty mango | G54: 3156 | H54: TRUE | I54: Bank | K54: 5
C55: 152 | D55: 45756 | E55: Greenz Veggies | F55: veggies | G55: 676 | H55: TRUE | I55: Bank | K55: 5
C56: 12 | D56: 45757 | E56: ARACKAL BHARATH GAS | F56: GAS | G56: 1720 | H56: TRUE | I56: UPI | K56: 5
... C68: 153 | D68: 45759 | E68: Greenz Veggies | F68: veggies | G68: 1112.25 | H68: TRUE | I68: Bank | K68: 5
C69: 258 | D69: 45759 | E69: LULU KOCHI | F69: salmon /avocado | G69: 2051 | H69: TRUE | I69: UPI
C70: 11 | D70: 45760 | E70: ARACKAL BHARATH GAS | F70: GAS | G70: 5280 | H70: TRUE | I70: UPI | K70: 5
C71: 168 | D71: 45760 | E71: Amazon | F71: gloves | G71: 1596 | H71: TRUE | I71: UPI | K71: 5
C72: 91 | D72: 45761 | E72: POLAR ICE CUBES | F72: ice cube | G72: 140 | H72: TRUE | I72: UPI | K72: 5
C73: 92 | D73: 45761 | E73: MATHA MEATS | F73: chicken full | G73: 1896 | H73: TRUE | I73: Bank | K73: 5
C74: 93 | D74: 45761 | E74: MATHA MEATS | F74: pork ribs | G74: 1800 | H74: TRUE | I74: Bank | K74: 5
C75: 10 | D75: 45762 | E75: ARACKAL BHARATH GAS | F75: GAS | G75: 1720 | H75: TRUE | I75: Bank | K75: 5
C76: 94 | D76: 45762 | E76: T3 SPECIALITY | F76: tomato ketup | G76: 16514 | H76: TRUE | I76: Bank | K76: 5
C77: 155 | D77: 45762 | E77: Greenz Veggies | F77: veggies | G77: 1450 | H77: TRUE | I77: Bank | K77: 5
C78: 202 | D78: 45762 | E78: CAREVELLO (PIZZA BOX) | F78: pizza boxes | G78: 40948 | H78: TRUE | I78: UPI | K78: 5
C79: 335 | D79: 45762 | E79: PULI WOOD CHINGAVANAM | F79: PULI WOOD CHINGAVANAM | G79: 18510 | H79: TRUE | I79: UPI | K79: 0
C80: 27 | D80: 45763 | E80: POLAR ICE CUBES | F80: ice cube | G80: 140 | H80: TRUE | I80: Cash | K80: 5
C81: 15 | D81: 45764 | E81: AMAZON | F81: FLY CATCHER ******* | G81: 1949 | H81: TRUE | I81: UPI | K81: 5
... C98: 98 | D98: 45768 | E98: Greenz Veggies | F98: brocoli | G98: 951 | H98: TRUE | I98: Bank | K98: 5
C99: 259 | D99: 45768 | E99: LULU KOCHI | F99: salmon /avocado | G99: 2117 | H99: TRUE | I99: UPI
C100: 320 | D100: 45768 | E100: Diamond | F100: food wraping paper, | G100: 1370 | H100: TRUE | I100: Bank | K100: 0
C101: 35 | D101: 45769 | E101: POLAR ICE CUBES | F101: ice cube | G101: 140 | H101: TRUE | I101: UPI | K101: 5
C102: 39 | D102: 45769 | E102: T3 SPECIALITY | F102: Mushroom | G102: 6180 | H102: TRUE | I102: Bank | K102: 5
C103: 223 | D103: 45769 | E103: STAFF ACCOMODATION | F103: ANITHA JAYACHANDRAN | G103: 22000 | H103: TRUE | I103: Bank | K103: 5
C104: 333 | D104: 45769 | E104: SELF TRANSFER | F104: CHITTY (POST OFFFICE) | G104: 3000 | H104: TRUE | I104: Bank | K104: 0
C105: 9 | D105: 45770 | E105: ARACKAL BHARATH GAS | F105: GAS | G105: 1760 | H105: TRUE | I105: Bank | K105: 5
C106: 40 | D106: 45770 | E106: T3 SPECIALITY | F106: Buffalo | G106: 2426 | H106: TRUE | I106: Bank | K106: 5
C107: 41 | D107: 45770 | E107: HYGIENE FRESH | F107: cap | G107: 2490 | H107: TRUE | I107: UPI | K107: 5
C108: 46 | D108: 45770 | E108: MATHA MEATS | F108: pork ribs | G108: 2880 | H108: TRUE | I108: Bank | K108: 5
C109: 111 | D109: 45770 | E109: T3 SPECIALITY | F109: BEEF CURRY CUT | G109: 3087 | H109: TRUE | I109: Bank | K109: 5
C110: 241 | D110: 45770 | E110: Greenz Veggies | F110: veggies | G110: 1246 | H110: TRUE | I110: Bank | K110: 0
C111: 261 | D111: 45770 | E111: Local purchase | F111: Chilly powder, Oil | G111: 201 | H111: TRUE | I111: UPI | K111: 0
... C114: 44 | D114: 45771 | E114: Matha meats | F114: Chicken | G114: 2960 | H114: TRUE | I114: Bank | K114: 5
C115: 242 | D115: 45771 | E115: Greenz Veggies | F115: veggies | G115: 1475 | H115: TRUE | I115: Bank
C116: 262 | D116: 45771 | E116: Zepto | F116: Oil & milkymist zepto(Alby) | G116: 292 | H116: TRUE | I116: UPI | K116: 0
C117: 263 | D117: 45771 | E117: Local purchase | F117: Oil | G117: 179 | H117: TRUE | I117: UPI | K117: 0
C118: 95 | D118: 45772 | E118: POLAR ICE CUBES | F118: ice cube | G118: 140 | H118: TRUE | I118: UPI | K118: 5
C119: 96 | D119: 45772 | E119: T3 SPECIALITY | F119: CHEESE | G119: 10362 | H119: TRUE | I119: Bank | K119: 5
C120: 243 | D120: 45772 | E120: Greenz Veggies | F120: veggies | G120: 1135 | H120: TRUE | I120: Bank
C121: 332 | D121: 45772 | E121: SELF TRANSFER | F121: SELF | G121: 5000 | H121: TRUE | I121: Bank | K121: 0
A122: {=IF(D122:D3756="", "", TEXT(D122:D3756, "YYYY"))} -> 2025 | B122: {=IF(D122:D3756="", "", TEXT(D122:D3756, "MM-MMM"))} -> 04-Apr | C122: 1 | D122: 45773 | E122: MATHA MEATS | F122: Chicken | G122: 2997 | H122: TRUE | I122: Bank | K122: 5
A123: 2025 | B123: 04-Apr | C123: 13 | D123: 45773 | E123: ARACKAL BHARATH GAS | F123: GAS | G123: 1760 | H123: TRUE | I123: Bank | K123: 5
A124: 2025 | B124: 04-Apr | C124: 16 | D124: 45773 | E124: T3 SPECIALITY | F124: JUICE | G124: 1979 | H124: TRUE | I124: Bank | K124: 5
A125: 2025 | B125: 04-Apr | C125: 19 | D125: 45773 | E125: T3 SPECIALITY | F125: CHEESE | G125: 12527 | H125: TRUE | I125: Bank | K125: 5
A126: 2025 | B126: 04-Apr | C126: 97 | D126: 45773 | E126: T3 SPECIALITY | F126: spegatti | G126: 3016 | H126: TRUE | I126: Bank | K126: 5
A127: 2025 | B127: 04-Apr | C127: 244 | D127: 45773 | E127: Greenz Veggies | F127: veggies | G127: 680 | H127: TRUE | I127: Bank
A128: 2025 | B128: 04-Apr | C128: 260 | D128: 45773 | E128: LULU KOCHI | F128: salmon /avocado | G128: 3286 | H128: TRUE | I128: UPI
A129: 2025 | B129: 04-Apr | C129: 4 | D129: 45774 | E129: MATHA MEATS | F129: pork ribs | G129: 2880 | H129: TRUE | I129: Bank | K129: 5
A130: 2025 | B130: 04-Apr | C130: 5 | D130: 45774 | E130: POLAR ICE CUBES | F130: ice cube | G130: 300 | H130: TRUE | I130: UPI | K130: 5
A131: 2025 | B131: 04-Apr | C131: 20 | D131: 45774 | E131: LOCAL PURCHASE | F131: MENU PRINTING | G131: 800 | H131: TRUE | I131: Cash | K131: 5
A132: 2025 | B132: 04-Apr | C132: 43 | D132: 45774 | E132: LOCAL PURCHASE | F132: Jeans (MANJU FASHIONS) | G132: 4196 | H132: TRUE | I132: UPI | K132: 5
A133: 2025 | B133: 04-Apr | C133: 2 | D133: 45775 | E133: GROW GREENS | F133: micro greens | G133: 300 | H133: TRUE | I133: UPI | K133: 5
A134: 2025 | B134: 04-Apr | C134: 3 | D134: 45775 | E134: RIGHT SOLUTION PAPER TISSUE | F134: Tissue | G134: 1320 | H134: TRUE | I134: Bank | K134: 5
A135: 2025 | B135: 04-Apr | C135: 6 | D135: 45775 | E135: POLAR ICE CUBES | F135: ice cube | G135: 75 | H135: TRUE | I135: UPI | K135: 5
A136: 2025 | B136: 04-Apr | C136: 17 | D136: 45775 | E136: T3 SPECIALITY | F136: JUICE | G136: 2715 | H136: TRUE | I136: Bank | K136: 5
A137: 2025 | B137: 04-Apr | C137: 18 | D137: 45775 | E137: T3 SPECIALITY | F137: CHEESE | G137: 10379 | H137: TRUE | I137: Bank | K137: 5
A138: 2025 | B138: 04-Apr | C138: 245 | D138: 45775 | E138: Greenz Veggies | F138: veggies | G138: 1914 | H138: TRUE | I138: Bank
A139: 2025 | B139: 04-Apr | C139: 25 | D139: 45776 | E139: POLAR ICE CUBES | F139: ice cube | G139: 75 | H139: TRUE | I139: Cash | K139: 5
A140: 2025 | B140: 04-Apr | C140: 26 | D140: 45776 | E140: ARACKAL BHARATH GAS | F140: GAS | G140: 1760 | H140: TRUE | I140: Bank | K140: 5
A141: 2025 | B141: 04-Apr | C141: 120 | D141: 45776 | E141: T3 SPECIALITY | F141: PASTA | G141: 900 | H141: TRUE | I141: Bank | K141: 5
A142: 2025 | B142: 04-Apr | C142: 24 | D142: 45777 | E142: POLAR ICE CUBES | F142: ice cube | G142: 150 | H142: TRUE | I142: Cash | K142: 5
A143: 2025 | B143: 04-Apr | C143: 31 | D143: 45777 | E143: MATHA MEATS | F143: pork cuts | G143: 5100 | H143: TRUE | I143: Bank | K143: 5
A144: 2025 | B144: 04-Apr | C144: 49 | D144: 45777 | E144: LERA COCA COLA | F144: soda,sprite | G144: 2049 | H144: TRUE | I144: Bank | K144: 5
A145: 2025 | B145: 04-Apr | C145: 239 | D145: 45777 | E145: EMMES AGENCIES (GREEN VALLEY WATER) | F145: BOTTLE WATER & 20LTR CAN | G145: 3780 | H145: TRUE | I145: UPI | K145: 5
A146: 2025 | B146: 05-May | C146: 116 | D146: 45778 | E146: T3 SPECIALITY | F146: CHEESE | G146: 4348 | H146: TRUE | I146: Bank | K146: 5
...

Sheet Pivot Table 7

Sheet Daybook
A1: Month | B1: Date | C1: Week | D1: Description | E1: Income | F1: Expense
A2: 04-Apr | B2: 45773 | C2: 17 | D2: Matha meats | F2: 2997
A3: 04-Apr | B3: 45775 | C3: 18 | D3: Grow greens | F3: 300
A4: 04-Apr | B4: 45775 | C4: 18 | D4: Right solution Tissue paper | F4: 1320
A5: 04-Apr | B5: 45774 | C5: 18 | D5: Matha meats | F5: 2880
A6: 04-Apr | B6: 45774 | C6: 18 | D6: Polar Ice Cubes | F6: 300
A7: 04-Apr | B7: 45775 | C7: 18 | D7: Polar Ice Cubes | F7: 75
A8: 04-Apr | B8: 45748 | C8: 14 | D8: Local purchase | F8: 156
A9: 04-Apr | B9: 45751 | C9: 14 | D9: Arackal bharath gas | F9: 1720
A10: 04-Apr | B10: 45770 | C10: 17 | D10: Arackal bharath gas | F10: 1760
A11: 04-Apr | B11: 45762 | C11: 16 | D11: Arackal bharath gas | F11: 1720
A12: 04-Apr | B12: 45760 | C12: 16 | D12: Arackal bharath gas | F12: 5280
A13: 04-Apr | B13: 45757 | C13: 15 | D13: Arackal bharath gas | F13: 1720
... A319: 06-Jun | B319: 45829 | C319: 25 | D319: T3 Speciality | F319: 5880
A320: 06-Jun | B320: 45831 | C320: 26 | D320: Trio meats Kottayam
A321: 06-Jun | B321: 45833 | C321: 26 | D321: Arackal bharath gas | F321: 1740
A322: 06-Jun | B322: 45833 | C322: 26 | D322: EURO INDIA KOCHI | F322: 4435
A323: 05-May | B323: 45787 | C323: 19 | D323: EURO INDIA KOCHI | F323: 2262
A324: 06-Jun | B324: 45829 | C324: 25 | D324: EURO INDIA KOCHI | F324: 4435
A325: 05-May | B325: 45799 | C325: 21 | D325: EURO INDIA KOCHI | F325: 4435
A326: 04-Apr | B326: 45768 | C326: 17 | D326: Diamond | F326: 1370
A327: 06-Jun | B327: 45833 | C327: 26 | D327: Diamond | F327: 1217
A328: 06-Jun | B328: 45826 | C328: 25 | D328: Greenz Veggies | F328: 731
A329: 06-Jun | B329: 45832 | C329: 26 | D329: Greenz Veggies | F329: 95
A330: 06-Jun | B330: 45832 | C330: 26 | D330: Greenz Veggies | F330: 813
A331: 06-Jun | B331: 45826 | C331: 25 | D331: Greenz Veggies | F331: 836
A332: 06-Jun | B332: 45824 | C332: 25 | D332: Greenz Veggies | F332: 1160
... A420: 07-Jul | B420: 45854 | C420: 29 | D420: T3 Speciality | F420: 6986
A421: 04-Apr | B421: 45749 | C421: 14 | D421: Kakkanad Income | E421: 10655
A422: 04-Apr | B422: 45750 | C422: 14 | D422: Kakkanad Income | E422: 15640
A423: 04-Apr | B423: 45751 | C423: 14 | D423: Kakkanad Income | E423: 18210
A424: 04-Apr | B424: 45752 | C424: 14 | D424: Kakkanad Income | E424: 10385
A425: 04-Apr | B425: 45753 | C425: 15 | D425: Kakkanad Income | E425: 16845
A426: 04-Apr | B426: 45754 | C426: 15 | D426: Kakkanad Income | E426: 20030
A427: 04-Apr | B427: 45755 | C427: 15 | D427: Kakkanad Income | E427: 16870
A428: 04-Apr | B428: 45756 | C428: 15 | D428: Kakkanad Income | E428: 2635
A429: 04-Apr | B429: 45757 | C429: 15 | D429: Kakkanad Income | E429: 24368
A430: 04-Apr | B430: 45758 | C430: 15 | D430: Kakkanad Income | E430: 27640
A431: 04-Apr | B431: 45759 | C431: 15 | D431: Kakkanad Income | E431: 23040
A432: 04-Apr | B432: 45760 | C432: 16 | D432: Kakkanad Income | E432: 19155
... A529: 07-Jul | B529: 45857 | C529: 29 | D529: Kakkanad Income | E529: 38358
A530: =TEXT(B530,"MM")&"-"&text(B530,"MMM") -> 07-Jul | B530: 45858 | C530: =WEEKNUM(B530,1) -> 30 | D530: Kakkanad Income | E530: 0
A531: =TEXT(B531,"MM")&"-"&text(B531,"MMM") -> 07-Jul | B531: 45859 | C531: =WEEKNUM(B531,1) -> 30 | D531: Kakkanad Income | E531: 22788
A532: =TEXT(B532,"MM")&"-"&text(B532,"MMM") -> 07-Jul | B532: =B531+1 -> 45860 | C532: =WEEKNUM(B532,1) -> 30 | D532: Kakkanad Income | E532: 27286
A533: =TEXT(B533,"MM")&"-"&text(B533,"MMM") -> 07-Jul | B533: 45861 | C533: =WEEKNUM(B533,1) -> 30 | D533: Kakkanad Income | E533: 33241.5
A534: =TEXT(B534,"MM")&"-"&text(B534,"MMM") -> 07-Jul | B534: 45862 | C534: =WEEKNUM(B534,1) -> 30 | D534: Kakkanad Income | E534: 31635.5
A535: =TEXT(B535,"MM")&"-"&text(B535,"MMM") -> 07-Jul | B535: 45863 | C535: =WEEKNUM(B535,1) -> 30 | D535: Kakkanad Income | E535: 44015
A536: 07-Jul | B536: 45860 | C536: =WEEKNUM(B536,1) -> 30 | D536: Trio meats Kottayam | F536: 1680
A537: 07-Jul | B537: 45861 | C537: =WEEKNUM(B537,1) -> 30 | D537: T3 Speciality | F537: 5157
A538: 07-Jul | B538: 45859 | C538: =WEEKNUM(B538,1) -> 30 | D538: Matha meats | F538: 2520
A539: 07-Jul | B539: 45860 | C539: =WEEKNUM(B539,1) -> 30 | D539: Arackal bharath gas | F539: 1670
A540: 07-Jul | B540: 45860 | C540: =WEEKNUM(B540,1) -> 30 | D540: Polar Ice Cubes | F540: 75
A541: 07-Jul | B541: 45859 | C541: =WEEKNUM(B541,1) -> 30 | D541: Polar Ice Cubes | F541: 75
A542: 07-Jul | B542: 45861 | C542: =WEEKNUM(B542,1) -> 30 | D542: THE FOOD CART | F542: 6048
A543: 07-Jul | B543: 45859 | C543: =WEEKNUM(B543,1) -> 30 | D543: Lera coca-cola | F543: 1654
A544: 07-Jul | B544: 45863 | C544: =WEEKNUM(B544,1) -> 30 | D544: Polar Ice Cubes | F544: 75
A545: 07-Jul | B545: 45861 | C545: =WEEKNUM(B545,1) -> 30 | D545: Greenz Veggies | F545: 1377
A546: 07-Jul | B546: 45862 | C546: =WEEKNUM(B546,1) -> 30 | D546: Greenz Veggies | F546: 875
A547: 07-Jul | B547: 45859 | C547: =WEEKNUM(B547,1) -> 30 | D547: Trio meats Kottayam | F547: 7151
... A549: 07-Jul | B549: 45863 | C549: =WEEKNUM(B549,1) -> 30 | D549: T3 Speciality | F549: 11011
A550: 07-Jul | B550: 45864 | C550: =WEEKNUM(B550,1) -> 30 | D550: PetPooja | E550: 29060
A551: 07-Jul | B551: 45864 | C551: =WEEKNUM(B551,1) -> 30 | D551: Swiggy | E551: 22550
A552: 07-Jul | B552: 45864 | C552: =WEEKNUM(B552,1) -> 30 | D552: Zomato | E552: =729+699+260+2027+549 -> 4264

Sheet SwiggyInvoiceSummary
A1: Philos Kakkanad Swiggy Trasaction Tracker
Y2: Actual Payment (from Swiggy Stmnt) | Z2: Difference | AA2: Swiggy % | AB2: Philos % | AD2: =A2 -> PaymentID | AE2: =B2 -> No. of Ord. | AF2: =F2 -> [A] Net Bill Value | AG2: [B] Swiggy Fee | AH2: [C] Cancellation | AI2: [D] Taxes | AJ2: =X2 -> Net Payout [A-B-C-D] | AK2: Actual Pay | AL2: Difference | AM2: Swiggy % | AN2: Philos %
Y3: 4386.32 | Z3: =X3-Y3 -> 1179 | AA3: =(R3+S3+T3+Z3)/F3 -> 0.32882506 | AB3: =Y3/F3 -> 0.67017876 | AD3: =A3 -> 45763 | AE3: =B3 -> 7 | AF3: =F3 -> 6545 | AG3: =R3 -> 973.16 | AH3: =S3+T3 -> 0 | AI3: =U3+V3+W3 -> 333.8 | AJ3: =X3 -> 5565.32 | AK3: =Y3 -> 4386.32 | AL3: =Z3 -> 1179 | AM3: =AA3 -> 0.32882506 | AN3: =AB3 -> 0.67017876
Y4: 11190.28 | Z4: =X4-Y4 -> 0.01 | AA4: =(R4+S4+T4+Z4)/F4 -> 0.1486815 | AB4: =Y4/F4 -> 0.85032458 | AD4: =A4 -> 45770 | AE4: =B4 -> 16 | AF4: =F4 -> 13160.01 | AG4: =R4 -> 1956.64 | AH4: =S4+T4 -> 0 | AI4: =U4+V4+W4 -> 671.16 | AJ4: =X4 -> 11190.29 | AK4: =Y4 -> 11190.28 | AL4: =Z4 -> 0.01 | AM4: =AA4 -> 0.1486815 | AN4: =AB4 -> 0.85032458
Y5: 39721.55 | Z5: =X5-Y5 -> 0 | AA5: =(R5+S5+T5+Z5)/F5 -> 0.15439719 | AB5: =Y5/F5 -> 0.84460026 | AD5: =A5 -> 45777 | AE5: =B5 -> 53 | AF5: =F5 -> 47030 | AG5: =R5 -> 6992.3 | AH5: =S5+T5 -> 269 | AI5: =U5+V5+W5 -> 2398.52 | AJ5: =X5 -> 39721.55 | AK5: =Y5 -> 39721.55 | AL5: =Z5 -> 0 | AM5: =AA5 -> 0.15439719 | AN5: =AB5 -> 0.84460026
Y6: 15152.76 | Z6: =X6-Y6 -> 0 | AA6: =(R6+S6+T6+Z6)/F6 -> 0.14867677 | AB6: =Y6/F6 -> 0.85032323 | AD6: =A6 -> 45782 | AE6: =B6 -> 18 | AF6: =F6 -> 17820 | AG6: =R6 -> 2649.42 | AH6: =S6+T6 -> 0 | AI6: =U6+V6+W6 -> 908.82 | AJ6: =X6 -> 15152.76 | AK6: =Y6 -> 15152.76 | AL6: =Z6 -> 0 | AM6: =AA6 -> 0.14867677 | AN6: =AB6 -> 0.85032323
Y7: 10486.25 | Z7: =X7-Y7 -> 0 | AA7: =(R7+S7+T7+Z7)/F7 -> 0.2017447 | AB7: =Y7/F7 -> 0.79725097 | AD7: =A7 -> 45784 | AE7: =B7 -> 15 | AF7: =F7 -> 13153.01 | AG7: =R7 -> 1955.55 | AH7: =S7+T7 -> 698 | AI7: =U7+V7+W7 -> 670.81 | AJ7: =X7 -> 10486.25 | AK7: =Y7 -> 10486.25 | AL7: =Z7 -> 0 | AM7: =AA7 -> 0.2017447 | AN7: =AB7 -> 0.79725097
Y8: 14375.22 | Z8: =X8-Y8 -> 3.01 | AA8: =(R8+S8+T8+Z8)/F8 -> 0.1492814 | AB8: =Y8/F8 -> 0.84972082 | AD8: =A8 -> 45791 | AE8: =B8 -> 24 | AF8: =F8 -> 16917.58 | AG8: =R8 -> 2522.47 | AH8: =S8+T8 -> 0 | AI8: =U8+V8+W8 -> 862.81 | AJ8: =X8 -> 14378.23 | AK8: =Y8 -> 14375.22 | AL8: =Z8 -> 3.01 | AM8: =AA8 -> 0.1492814 | AN8: =AB8 -> 0.84972082
Y9: 15528.99 | Z9: =X9-Y9 -> -0.03 | AA9: =(R9+S9+T9+Z9)/F9 -> 0.17850084 | AB9: =Y9/F9 -> 0.8224212 | AD9: =A9 -> 45798 | AE9: =B9 -> 24 | AF9: =F9 -> 18882.04 | AG9: =R9 -> 2633.39 | AH9: =S9+T9 -> 737.1 | AI9: =U9+V9+W9 -> 926.71 | AJ9: =X9 -> 15528.96 | AK9: =Y9 -> 15528.99 | AL9: =Z9 -> -0.03 | AM9: =AA9 -> 0.17850084 | AN9: =AB9 -> 0.8224212
Y10: 16561.62 | Z10: =X10-Y10 -> 0.01 | AA10: =(R10+S10+T10+Z10)/F10 -> 0.15479356 | AB10: =Y10/F10 -> 0.84420532 | AD10: =A10 -> 45805 | AE10: =B10 -> 29 | AF10: =F10 -> 19618 | AG10: =R10 -> 2916.73 | AH10: =S10+T10 -> 120 | AI10: =U10+V10+W10 -> 1000.47 | AJ10: =X10 -> 16561.63 | AK10: =Y10 -> 16561.62 | AL10: =Z10 -> 0.01 | AM10: =AA10 -> 0.15479356 | AN10: =AB10 -> 0.84420532
Y11: 24755.42 | Z11: =X11-Y11 -> -0.01 | AA11: =(R11+S11+T11+Z11)/F11 -> 0.14868056 | AB11: =Y11/F11 -> 0.85032127 | AD11: =A11 -> 45812 | AE11: =B11 -> 34 | AF11: =F11 -> 29113.02 | AG11: =R11 -> 4328.55 | AH11: =S11+T11 -> 0 | AI11: =U11+V11+W11 -> 1484.76 | AJ11: =X11 -> 24755.41 | AK11: =Y11 -> 24755.42 | AL11: =Z11 -> -0.01 | AM11: =AA11 -> 0.14868056 | AN11: =AB11 -> 0.85032127
Y12: 25440.8 | Z12: =X12-Y12 -> 3539.98 | AA12: =(R12+S12+T12+Z12)/F12 -> 0.25254546 | AB12: =Y12/F12 -> 0.74645197 | AD12: =A12 -> 45819 | AE12: =B12 -> 42 | AF12: =F12 -> 34082.3 | AG12: =R12 -> 5067.35 | AH12: =S12+T12 -> 0 | AI12: =U12+V12+W12 -> 1738.28 | AJ12: =X12 -> 28980.78 | AK12: =Y12 -> 25440.8 | AL12: =Z12 -> 3539.98 | AM12: =AA12 -> 0.25254546 | AN12: =AB12 -> 0.74645197
Y13: 24872.2 | Z13: =X13-Y13 -> 3539.99 | AA13: =(R13+S13+T13+Z13)/F13 -> 0.25462574 | AB13: =Y13/F13 -> 0.74437466 | AD13: =A13 -> 45826 | AE13: =B13 -> 42 | AF13: =F13 -> 33413.55 | AG13: =R13 -> 4967.96 | AH13: =S13+T13 -> 0 | AI13: =U13+V13+W13 -> 1704.14 | AJ13: =X13 -> 28412.19 | AK13: =Y13 -> 24872.2 | AL13: =Z13 -> 3539.99 | AM13: =AA13 -> 0.25462574 | AN13: =AB13 -> 0.74437466
Y14: 24947.72 | Z14: =X14-Y14 -> 3540.03 | AA14: =(R14+S14+T14+Z14)/F14 -> 0.2543452 | AB14: =Y14/F14 -> 0.74465338 | AD14: =A14 -> 45833 | AE14: =B14 -> 34 | AF14: =F14 -> 33502.46 | AG14: =R14 -> 4981.16 | AH14: =S14+T14 -> 0 | AI14: =U14+V14+W14 -> 1708.65 | AJ14: =X14 -> 28487.75 | AK14: =Y14 -> 24947.72 | AL14: =Z14 -> 3540.03 | AM14: =AA14 -> 0.2543452 | AN14: =AB14 -> 0.74465338
... Y17: 41700 | Z17: =X17-Y17 -> 0.02 | AA17: =(R17+S17+T17+Z17)/F17 -> 0.15923133 | AB17: =Y17/F17 -> 0.83977141 | AD17: =A17 -> 45854 | AE17: =B17 -> 50 | AF17: =F17 -> 49656.37 | AG17: =R17 -> 7382.83 | AH17: =S17+T17 -> 524 | AI17: =U17+V17+W17 -> 2532.36 | AJ17: =X17 -> 41700.02 | AK17: =Y17 -> 41700 | AL17: =Z17 -> 0.02 | AM17: =AA17 -> 0.15923133 | AN17: =AB17 -> 0.83977141
Y18: =SUM(Y5:Y17) -> 330132.41 | Z18: =SUM(Z5:Z17) -> 15376.92 | AA18: =AVERAGE(AA6:AA17) -> 0.19107856 | AB18: =AVERAGE(AB6:AB17) -> 0.80808067 | AE18: =B18 -> 483 | AF18: =SUM(AF5:AF17) -> 408851.2 | AG18: =SUM(AG5:AG17) -> 60620.69 | AH18: =SUM(AH5:AH17) -> 2348.1 | AI18: =SUM(AI5:AI17) -> 20815.15 | AJ18: =SUM(AJ5:AJ17) -> 345509.33 | AK18: =SUM(AK5:AK17) -> 330132.41 | AL18: =SUM(AL5:AL17) -> 15376.92 | AM18: =AVERAGE(AM5:AM17) -> 0.18825692 | AN18: =AVERAGE(AN5:AN17) -> 0.81088987
D19: AOV
C20: =A3 -> 45763 | D20: =F3/B3 -> 935
C21: =A4 -> 45770 | D21: =F4/B4 -> 822.50063
C22: =A5 -> 45777 | D22: =F5/B5 -> 887.35849
C23: =A6 -> 45782 | D23: =F6/B6 -> 990
C24: =A7 -> 45784 | D24: =F7/B7 -> 876.86733
C25: =A8 -> 45791 | D25: =F8/B8 -> 704.89917
C26: =A9 -> 45798 | D26: =F9/B9 -> 786.75167
C27: =A10 -> 45805 | D27: =F10/B10 -> 676.48276
C28: =A11 -> 45812 | D28: =F11/B11 -> 856.26529
C29: =A12 -> 45819 | D29: =F12/B12 -> 811.48333
C30: =A13 -> 45826 | D30: =F13/B13 -> 795.56071
C31: =A14 -> 45833 | D31: =F14/B14 -> 985.36647
... C33: =A16 -> 45847 | D33: =F16/B16 -> 975.00026

Sheet Menu
A1: Name | B1: Online_Name | C1: Description | D1: Short_Code | E1: Short_Code_2 | F1: Sap_Code | G1: HSN_Code | H1: Parent_Category | I1: Category | J1: Category_online_display | K1: Price | L1: Attributes | M1: Goods_Services | N1: Unit | O1: is_Self_Item_Recipe | P1: minimum_stock_level | Q1: at_par_stock_level | R1: Rank | S1: Packing_Charges | T1: Allow_Decimal_Qty | U1: Addon_Group_Name | V1: Addon_Group_Selection | W1: Addon_Group_Min | X1: Addon_Group_Max | Y1: Variation_group_name | Z1: Variation | AA1: Variation_Price | AB1: Variation_Sap_Code | AC1: Variation_Packing_Charges | AD1: Variation 2 | AE1: Variation_Price 2 | AF1: Variation_Sap_Code 2 | AG1: Variation_Packing_Charges 2 | AH1: Variation 3 | AI1: Variation_Price 3 | AJ1: Variation_Sap_Code 3 | AK1: Variation_Packing_Charges 3
A2: Cajun Fried Prawns | B2: Cajun Fried Prawns | D2: 1 | I2: Western | K2: 380 | L2: non-veg | O2: 0 | R2: 1 | S2: 0 | T2: Yes
A3: Moroccan Meat Balls | B3: Moroccan Meat Balls | D3: 2 | I3: Western | K3: 360 | L3: non-veg | O3: 0 | R3: 1 | S3: 0 | T3: Yes
A4: Jamaican Chicken Skewer | B4: Jamaican Chicken Skewer | D4: 3 | I4: Western | K4: 310 | L4: non-veg | O4: 0 | R4: 1 | S4: 0 | T4: Yes
A5: Spicy Corn & Cheese Balls | B5: Spicy Corn & Cheese Balls | D5: 4 | I5: Western | K5: 310 | L5: veg | O5: 0 | R5: 1 | S5: 0 | T5: Yes
A6: Nachos With Confit Tomato Salsa | B6: Nachos With Confit Tomato Salsa | D6: 5 | I6: Western | K6: 260 | L6: veg | O6: 0 | R6: 1 | S6: 0 | T6: Yes
A7: Pasta Arabiata | B7: Pasta Arabiata | D7: 6 | I7: Pastas | K7: 340 | L7: veg | O7: 0 | R7: 1 | S7: 0 | T7: Yes
A8: Classic Pasta | B8: Classic Pasta | D8: 8 | I8: Pastas | K8: 470 | L8: non-veg | O8: 0 | R8: 1 | S8: 0 | T8: Yes
A9: Mexican Tostadas | B9: Mexican Tostadas | D9: 9 | I9: Wraps/Burger | K9: 380 | L9: veg | O9: 0 | R9: 1 | S9: 0 | T9: Yes
A10: Chicken Quesadilla | B10: Chicken Quesadilla | D10: 10 | I10: Wraps/Burger | K10: 420 | L10: non-veg | O10: 0 | R10: 1 | S10: 0 | T10: Yes
A11: Stuffed Chicken Roulade | B11: Stuffed Chicken Roulade | D11: stuffed chicken roul | I11: Mains | K11: 490 | L11: non-veg | O11: 0 | R11: 1 | S11: 0 | T11: Yes
A12: Grilled Beef Tenderloin | B12: Grilled Beef Tenderloin | D12: grilled beef tenderl | I12: Mains | K12: 520 | L12: non-veg | O12: 0 | R12: 1 | S12: 0 | T12: Yes
A13: Asian Bbq Pork Ribs | B13: Asian Bbq Pork Ribs | D13: 14 | I13: Asian | K13: 380 | L13: non-veg | O13: 0 | R13: 1 | S13: 0 | T13: Yes
A14: Shepherds Pie | B14: Shepherds Pie | D14: shepherds pie | I14: Mains | K14: 520 | L14: non-veg | O14: 0 | R14: 1 | S14: 0 | T14: Yes
A15: Korean Pork Rice | B15: Korean Pork Rice | D15: korean pork rice | I15: Mains | K15: 490 | L15: non-veg | O15: 0 | R15: 1 | S15: 0 | T15: Yes
A16: Loaded Fries | B16: Loaded Fries | D16: 17 | I16: Sides | K16: 220 | L16: veg | O16: 0 | R16: 1 | S16: 0 | T16: Yes
A17: Chilly Cheese Toast | B17: Chilly Cheese Toast | D17: 18 | I17: Sides | K17: 210 | L17: veg | O17: 0 | R17: 1 | S17: 0 | T17: Yes
A18: Potato Wedges | B18: Potato Wedges | D18: 19 | I18: Sides | K18: 180 | L18: veg | O18: 0 | R18: 1 | S18: 0 | T18: Yes
A19: French Fries | B19: French Fries | D19: 20 | I19: Sides | K19: 160 | L19: veg | O19: 0 | R19: 1 | S19: 0 | T19: Yes
A20: Garlic Bread | B20: Garlic Bread | D20: 21 | I20: Sides | K20: 120 | L20: veg | O20: 0 | R20: 1 | S20: 0 | T20: Yes
A21: Prawn Tempura | B21: Prawn Tempura | D21: 22 | I21: Asian | K21: 380 | L21: non-veg | O21: 0 | R21: 1 | S21: 0 | T21: Yes
A22: Thai Chicken Satay | B22: Thai Chicken Satay | D22: thai chicken satay | I22: Asian | K22: 360 | L22: non-veg | O22: 0 | R22: 1 | S22: 0 | T22: Yes
A23: Chicken Karaage | B23: Chicken Karaage | D23: 24 | I23: Asian | K23: 360 | L23: non-veg | O23: 0 | R23: 1 | S23: 0 | T23: Yes
A24: Teriyaki Sliced Beef Tenderloin | B24: Teriyaki Sliced Beef Tenderloin | D24: 25 | I24: Asian | K24: 360 | L24: non-veg | O24: 0 | R24: 1 | S24: 0 | T24: Yes
A25: Thai Paneer Satay | B25: Thai Paneer Satay | D25: 26 | I25: Asian | K25: 310 | L25: veg | O25: 0 | R25: 1 | S25: 0 | T25: Yes
A26: Pork Tonkotsu Ramen | B26: Pork Tonkotsu Ramen | D26: 27 | I26: Ramen Bowls | K26: 450 | L26: non-veg | O26: 0 | R26: 1 | S26: 0 | T26: Yes
A27: Korean Pulled Chicken Ramen | B27: Korean Pulled Chicken Ramen | D27: 28 | I27: Ramen Bowls | K27: 420 | L27: non-veg | O27: 0 | R27: 1 | S27: 0 | T27: Yes
A28: Classic Maki | B28: Classic Maki | D28: 29 | I28: Authentic Japanese Sushi | K28: 490 | L28: veg | O28: 0 | R28: 1 | S28: 0 | T28: Yes
A29: Salmon Tartar Maki | B29: Salmon Tartar Maki | D29: 30 | I29: Authentic Japanese Sushi | K29: 650 | L29: non-veg | O29: 0 | R29: 1 | S29: 0 | T29: Yes
A30: Spicy Crunchy Tuna Roll | B30: Spicy Crunchy Tuna Roll | D30: 31 | I30: Authentic Japanese Sushi | K30: 650 | L30: non-veg | O30: 0 | R30: 1 | S30: 0 | T30: Yes
A31: Crispy Salmon Tempura Roll | B31: Crispy Salmon Tempura Roll | D31: 32 | I31: Authentic Japanese Sushi | K31: 650 | L31: non-veg | O31: 0 | R31: 1 | S31: 0 | T31: Yes
A32: Classic California Roll | B32: Classic California Roll | D32: 33 | I32: Authentic Japanese Sushi | K32: 700 | L32: non-veg | O32: 0 | R32: 1 | S32: 0 | T32: Yes
A33: Tuna Akami Roll | B33: Tuna Akami Roll | D33: 34 | I33: Authentic Japanese Sushi | K33: 650 | L33: non-veg | O33: 0 | R33: 1 | S33: 0 | T33: Yes
A34: Futo Maki | B34: Futo Maki | D34: 35 | I34: Authentic Japanese Sushi | K34: 700 | L34: veg | O34: 0 | R34: 1 | S34: 0 | T34: Yes
A35: Crunchy Caprese Roll | B35: Crunchy Caprese Roll | D35: 36 | I35: Authentic Japanese Sushi | K35: 450 | L35: veg | O35: 0 | R35: 1 | S35: 0 | T35: Yes
A36: Wild Mushroom | B36: Wild Mushroom | D36: 37 | I36: Veg Pizzas | K36: 0 | L36: veg | O36: 0 | R36: 1 | S36: 0 | T36: Yes | Y36: Quantity | Z36: 8 Inch | AA36: 375 | AC36: 0 | AD36: 10 Inch | AE36: 525 | AG36: 0 | AH36: 12 Inch | AI36: 650 | AK36: 0
A37: Melanzane | B37: Melanzane | D37: 38 | I37: Veg Pizzas | K37: 0 | L37: veg | O37: 0 | R37: 1 | S37: 0 | T37: Yes | Y37: Quantity | Z37: 8 Inch | AA37: 350 | AC37: 0 | AD37: 10 Inch | AE37: 450 | AG37: 0 | AH37: 12 Inch | AI37: 550 | AK37: 0
A38: Premavera | B38: Premavera | D38: 39 | I38: Veg Pizzas | K38: 0 | L38: veg | O38: 0 | R38: 1 | S38: 0 | T38: Yes | Y38: Quantity | Z38: 8 Inch | AA38: 375 | AC38: 0 | AD38: 10 Inch | AE38: 525 | AG38: 0 | AH38: 12 Inch | AI38: 650 | AK38: 0
A39: Grilled Paneer | B39: Grilled Paneer | D39: 40 | I39: Veg Pizzas | K39: 0 | L39: veg | O39: 0 | R39: 1 | S39: 0 | T39: Yes | Y39: Quantity | Z39: 8 Inch | AA39: 375 | AC39: 0 | AD39: 10 Inch | AE39: 525 | AG39: 0 | AH39: 12 Inch | AI39: 650 | AK39: 0
A40: Margherita | B40: Margherita | D40: 41 | I40: Veg Pizzas | K40: 0 | L40: veg | O40: 0 | R40: 1 | S40: 0 | T40: Yes | Y40: Quantity | Z40: 8 Inch | AA40: 325 | AC40: 0 | AD40: 10 Inch | AE40: 450 | AG40: 0 | AH40: 12 Inch | AI40: 600 | AK40: 0
A41: Quattro Formaggi | B41: Quattro Formaggi | D41: 42 | I41: Veg Pizzas | K41: 0 | L41: veg | O41: 0 | R41: 1 | S41: 0 | T41: Yes | Y41: Quantity | Z41: 8 Inch | AA41: 425 | AC41: 0 | AD41: 10 Inch | AE41: 575 | AG41: 0 | AH41: 12 Inch | AI41: 725 | AK41: 0
A42: Italian Salsiccia | B42: Italian Salsiccia | D42: 43 | I42: Non Veg Pizzas | K42: 0 | L42: non-veg | O42: 0 | R42: 1 | S42: 0 | T42: Yes | Y42: Quantity | Z42: 8 Inch | AA42: 425 | AC42: 0 | AD42: 10 Inch | AE42: 575 | AG42: 0 | AH42: 12 Inch | AI42: 700 | AK42: 0
A43: Capricciosa | B43: Capricciosa | D43: 44 | I43: Non Veg Pizzas | K43: 0 | L43: non-veg | O43: 0 | R43: 1 | S43: 0 | T43: Yes | Y43: Quantity | Z43: 8 Inch | AA43: 425 | AC43: 0 | AD43: 10 Inch | AE43: 575 | AG43: 0 | AH43: 12 Inch | AI43: 700 | AK43: 0
A44: Pepperoni | B44: Pepperoni | D44: 45 | I44: Non Veg Pizzas | K44: 0 | L44: non-veg | O44: 0 | R44: 1 | S44: 0 | T44: Yes | Y44: Quantity | Z44: 8 Inch | AA44: 425 | AC44: 0 | AD44: 10 Inch | AE44: 575 | AG44: 0 | AH44: 12 Inch | AI44: 750 | AK44: 0
A45: Bbq Chicken Pizza | B45: Bbq Chicken Pizza | D45: 46 | I45: Non Veg Pizzas | K45: 0 | L45: non-veg | O45: 0 | R45: 1 | S45: 0 | T45: Yes | Y45: Quantity | Z45: 8 Inch | AA45: 425 | AC45: 0 | AD45: 10 Inch | AE45: 575 | AG45: 0 | AH45: 12 Inch | AI45: 725 | AK45: 0
A46: Jamaican Jerk Pizza | B46: Jamaican Jerk Pizza | D46: 47 | I46: Non Veg Pizzas | K46: 0 | L46: non-veg | O46: 0 | R46: 1 | S46: 0 | T46: Yes | Y46: Quantity | Z46: 8 Inch | AA46: 425 | AC46: 0 | AD46: 10 Inch | AE46: 550 | AG46: 0 | AH46: 12 Inch | AI46: 750 | AK46: 0
A47: Lebanese Chicken Pizza | B47: Lebanese Chicken Pizza | D47: 48 | I47: Non Veg Pizzas | K47: 0 | L47: non-veg | O47: 0 | R47: 1 | S47: 0 | T47: Yes | Y47: Quantity | Z47: 8 Inch | AA47: 450 | AC47: 0 | AD47: 10 Inch | AE47: 575 | AG47: 0 | AH47: 12 Inch | AI47: 750 | AK47: 0
... A56: Meat Lovers Pizza | B56: Meat Lovers Pizza | D56: 57 | I56: Non Veg Pizzas | K56: 0 | L56: non-veg | O56: 0 | R56: 1 | S56: 0 | T56: Yes | Y56: Quantity | Z56: 8 Inch | AA56: 700 | AC56: 0 | AD56: 10 Inch | AE56: 900 | AG56: 0 | AH56: 12 Inch | AI56: 1250 | AK56: 0
A57: Make Your Own Pizza | B57: Make Your Own Pizza | D57: 58 | I57: Non Veg Pizzas | K57: 1200 | L57: veg | O57: 0 | R57: 1 | S57: 0 | T57: Yes
A58: Chefs Signature Spaghetti Bolognese | B58: Chefs Signature Spaghetti Bolognese | D58: 7 | I58: Pastas | K58: 450 | L58: non-veg | O58: 0 | R58: 1 | S58: 0 | T58: Yes
A59: Citys Best Melted Burger | B59: Citys Best Melted Burger | D59: 11 | I59: Wraps/Burger | K59: 350 | L59: veg | O59: 0 | R59: 1 | S59: 0 | T59: Yes
A60: King Alphonso | B60: King Alphonso | D60: KA | I60: BEVERAGES | K60: 180 | L60: veg | O60: 0 | R60: 1 | S60: 0 | T60: Yes
A61: Blue Lagoon | B61: Blue Lagoon | D61: BL | I61: BEVERAGES | K61: 160 | L61: veg | O61: 0 | R61: 1 | S61: 0 | T61: Yes
A62: Jack Rose | B62: Jack Rose | D62: JR | I62: BEVERAGES | K62: 160 | L62: veg | O62: 0 | R62: 1 | S62: 0 | T62: Yes
A63: Mango Basil Blossom | B63: Mango Basil Blossom | D63: MBB | I63: BEVERAGES | K63: 180 | L63: veg | O63: 0 | R63: 1 | S63: 0 | T63: Yes
A64: Pina Colada | B64: Pina Colada | D64: PC | I64: BEVERAGES | K64: 170 | L64: veg | O64: 0 | R64: 1 | S64: 0 | T64: Yes
A65: Passionfruit Spritzer | B65: Passionfruit Spritzer | D65: PS | I65: BEVERAGES | K65: 160 | L65: veg | O65: 0 | R65: 1 | S65: 0 | T65: Yes
A66: Strawberry Colada | B66: Strawberry Colada | D66: SC | I66: BEVERAGES | K66: 160 | L66: veg | O66: 0 | R66: 1 | S66: 0 | T66: Yes
A67: Virgin Mojito | B67: Virgin Mojito | D67: VM | I67: BEVERAGES | K67: 120 | L67: veg | O67: 0 | R67: 1 | S67: 0 | T67: Yes
A68: Iced Tea | B68: Iced Tea | D68: IT | I68: BEVERAGES | K68: 125 | L68: veg | O68: 0 | R68: 1 | S68: 0 | T68: Yes
A69: Fresh Lime | B69: Fresh Lime | D69: FL | I69: BEVERAGES | K69: 75 | L69: veg | O69: 0 | R69: 1 | S69: 0 | T69: Yes
A70: Bottle Water | B70: Bottle Water | D70: BW | I70: BEVERAGES | K70: 20 | L70: veg | O70: 0 | R70: 1 | S70: 0 | T70: Yes
A71: Double Cheese | B71: double cheese | D71: double cheese | I71: Add ons | K71: 120 | L71: veg | M71: services | O71: 0 | R71: 1 | S71: 0 | T71: Yes
A72: Truffle Fries | B72: Truffle Fries | D72: TF | I72: Sides | K72: 190 | L72: veg | O72: 0 | R72: 1 | S72: 0 | T72: Yes
A73: Pepperoni Pork/chicken | B73: pepperoni | D73: pepp | I73: Add ons | K73: 120 | L73: non-veg | M73: services | O73: 0 | R73: 1 | S73: 0 | T73: Yes
A74: Broccoli | B74: Broccoli | D74: BI | I74: Add ons | K74: 50 | L74: veg | O74: 0 | R74: 1 | S74: 0 | T74: Yes
A75: Mushroom | B75: Mushroom | D75: MM | I75: Add ons | K75: 50 | L75: veg | O75: 0 | R75: 1 | S75: 0 | T75: Yes
A76: Olives | B76: Olives | D76: OL | I76: Add ons | K76: 50 | L76: veg | O76: 0 | R76: 1 | S76: 0 | T76: Yes
A77: Chicken | B77: Chicken | D77: CK | I77: Add ons | K77: 120 | L77: non-veg | O77: 0 | R77: 1 | S77: 0 | T77: Yes
A78: Beef | B78: Beef | D78: BF | I78: Add ons | K78: 120 | L78: non-veg | O78: 0 | R78: 1 | S78: 0 | T78: Yes
A79: Sprite | B79: Sprite | D79: sp | I79: BEVERAGES | K79: 20 | L79: veg | O79: 0 | R79: 1 | S79: 0 | T79: Yes
A80: Irish Coffee Delight | B80: Irish Coffee Delight | D80: IC | I80: BEVERAGES | K80: 170 | L80: veg | O80: 0 | R80: 1 | S80: 0 | T80: Yes
A81: Sausage Chicken/pork | B81: sausage chicken/pork | D81: sausage chicken/pork | I81: Add ons | K81: 120 | L81: non-veg | M81: services | O81: 0 | R81: 1 | S81: 0 | T81: Yes
A82: Veg Soup | B82: Veg Soup | D82: VG | I82: Sides | K82: 220 | L82: veg | O82: 0 | R82: 1 | S82: 0 | T82: Yes
A83: Cajun Fried Prawns (1/2) | B83: cajun fried prawns 1/2 | D83: cajun fried | I83: Western | K83: 190 | L83: non-veg | M83: services | O83: 0 | R83: 1 | S83: 0 | T83: Yes
A84: Mexican Nachos (1/2) | B84: mexican nachos (1/2) | D84: mexican nachos (1/2) | I84: Western | K84: 130 | L84: veg | M84: services | O84: 0 | R84: 1 | S84: 0 | T84: Yes
A85: Chilly Cheese Toast (1/2) | B85: chilly cheese toast (1/2) | D85: chilly cheese toast | I85: Sides | K85: 95 | L85: veg | M85: services | O85: 0 | R85: 1 | S85: 0 | T85: Yes
A86: Quattro Formaggi/ Chefspecial | B86: Quattro Formaggi/ Chefspecial | D86: fc | I86: Non Veg Pizzas | K86: 500 | L86: veg | O86: 0 | R86: 1 | S86: 0 | T86: Yes
A87: Sweet Corn | B87: sweet corn | D87: sweet corn | I87: Add ons | K87: 50 | L87: veg | M87: services | O87: 0 | R87: 1 | S87: 0 | T87: Yes
A88: Dynamite Crispy Shrimp | B88: dynamite crispy shrimp | D88: dynamite crispy shri | I88: Asian | K88: 380 | L88: non-veg | M88: services | O88: 0 | R88: 1 | S88: 0 | T88: Yes
A89: Jalepino | B89: Jalepino | D89: jpl | I89: Add ons | K89: 50 | L89: veg | O89: 0 | R89: 1 | S89: 0 | T89: Yes
A90: Korean Prawns Rice | B90: Korean Prawns Rice | D90: KP | I90: Mains | K90: 650 | L90: non-veg | O90: 0 | R90: 1 | S90: 0 | T90: Yes
A91: Chefs/jamican | B91: Chefs/jamican | D91: cj | I91: Non Veg Pizzas | K91: 812 | L91: non-veg | O91: 0 | R91: 1 | S91: 0 | T91: Yes
A92: Garlic Bread (half) | B92: Garlic Bread (half) | D92: gb1/2 | I92: Sides | K92: 60 | L92: veg | O92: 0 | R92: 1 | S92: 0 | T92: Yes
A93: Chicken (small) | B93: Chicken (small) | D93: Cs | I93: Add ons | K93: 75 | L93: veg | O93: 0 | R93: 1 | S93: 0 | T93: Yes
A94: Masala Omelet | B94: Masala Omelet | D94: MO | I94: Sides | K94: 120 | L94: egg | O94: 0 | R94: 1 | S94: 0 | T94: Yes

Sheet Income
A1: Sl | B1: Month | C1: Date | D1: Day | E1: Week Number | F1: Petpooja Actual | G1: GST 5% | H1: Petpooja | I1: Swiggy | J1: Swiggy Payout | K1: Paper Bill | L1: Zomato | M1: Zomato Payout | N1: Total | P1: FED BANK | Q1: YES BANK | R1: SWIGGY | S1: SWIGGY1 | T1: Cash | U1: Alerts
A2: 1 | B2: =TEXT(C2,"MM")&"-"&text(C2,"MMM") -> 04-Apr | C2: 45749 | D2: =text(C2,"ddd") -> Wed | E2: =WEEKNUM(C2,1) -> 14 | F2: 0 | G2: =if(F2<>"",F2*0.05,"") -> 0 | H2: =F2-G2 -> 0 | I2: 0 | K2: 10655 | N2: =if(or(H2<>"",I2<>"",K2<>""),sum(H2:K2),"") -> 10655
A3: 2 | B3: =TEXT(C3,"MM")&"-"&text(C3,"MMM") -> 04-Apr | C3: 45750 | D3: =text(C3,"ddd") -> Thu | E3: =WEEKNUM(C3,1) -> 14 | F3: 0 | G3: =if(F3<>"",F3*0.05,"") -> 0 | H3: =F3-G3 -> 0 | I3: 0 | K3: 15640 | N3: =if(or(H3<>"",I3<>"",K3<>""),sum(H3:K3),"") -> 15640
A4: 3 | B4: =TEXT(C4,"MM")&"-"&text(C4,"MMM") -> 04-Apr | C4: 45751 | D4: =text(C4,"ddd") -> Fri | E4: =WEEKNUM(C4,1) -> 14 | F4: 0 | G4: =if(F4<>"",F4*0.05,"") -> 0 | H4: =F4-G4 -> 0 | I4: 0 | K4: 18210 | N4: =if(or(H4<>"",I4<>"",K4<>""),sum(H4:K4),"") -> 18210
A5: 4 | B5: =TEXT(C5,"MM")&"-"&text(C5,"MMM") -> 04-Apr | C5: 45752 | D5: =text(C5,"ddd") -> Sat | E5: =WEEKNUM(C5,1) -> 14 | F5: 0 | G5: =if(F5<>"",F5*0.05,"") -> 0 | H5: =F5-G5 -> 0 | I5: 0 | K5: 10385 | N5: =if(or(H5<>"",I5<>"",K5<>""),sum(H5:K5),"") -> 10385
A6: 5 | B6: =TEXT(C6,"MM")&"-"&text(C6,"MMM") -> 04-Apr | C6: 45753 | D6: =text(C6,"ddd") -> Sun | E6: =WEEKNUM(C6,1) -> 15 | F6: 0 | G6: =if(F6<>"",F6*0.05,"") -> 0 | H6: =F6-G6 -> 0 | I6: 0 | K6: 16845 | N6: =if(or(H6<>"",I6<>"",K6<>""),sum(H6:K6),"") -> 16845
A7: 6 | B7: =TEXT(C7,"MM")&"-"&text(C7,"MMM") -> 04-Apr | C7: 45754 | D7: =text(C7,"ddd") -> Mon | E7: =WEEKNUM(C7,1) -> 15 | F7: 20030 | G7: =if(F7<>"",F7*0.05,"") -> 1001.5 | H7: =F7-G7 -> 19028.5 | I7: 0 | K7: 0 | N7: =if(or(H7<>"",I7<>"",K7<>""),sum(H7:K7),"") -> 19028.5
A8: 7 | B8: =TEXT(C8,"MM")&"-"&text(C8,"MMM") -> 04-Apr | C8: 45755 | D8: =text(C8,"ddd") -> Tue | E8: =WEEKNUM(C8,1) -> 15 | F8: 16870 | G8: =if(F8<>"",F8*0.05,"") -> 843.5 | H8: =F8-G8 -> 16026.5 | I8: 0 | K8: 0 | N8: =if(or(H8<>"",I8<>"",K8<>""),sum(H8:K8),"") -> 16026.5
A9: 8 | B9: =TEXT(C9,"MM")&"-"&text(C9,"MMM") -> 04-Apr | C9: 45756 | D9: =text(C9,"ddd") -> Wed | E9: =WEEKNUM(C9,1) -> 15 | F9: 2635 | G9: =if(F9<>"",F9*0.05,"") -> 131.75 | H9: =F9-G9 -> 2503.25 | I9: 0 | K9: 0 | N9: =if(or(H9<>"",I9<>"",K9<>""),sum(H9:K9),"") -> 2503.25
A10: 9 | B10: =TEXT(C10,"MM")&"-"&text(C10,"MMM") -> 04-Apr | C10: 45757 | D10: =text(C10,"ddd") -> Thu | E10: =WEEKNUM(C10,1) -> 15 | F10: 24368 | G10: =if(F10<>"",F10*0.05,"") -> 1218.4 | H10: =F10-G10 -> 23149.6 | I10: 0 | K10: 0 | N10: =if(or(H10<>"",I10<>"",K10<>""),sum(H10:K10),"") -> 23149.6
A11: 10 | B11: =TEXT(C11,"MM")&"-"&text(C11,"MMM") -> 04-Apr | C11: 45758 | D11: =text(C11,"ddd") -> Fri | E11: =WEEKNUM(C11,1) -> 15 | F11: 27640 | G11: =if(F11<>"",F11*0.05,"") -> 1382 | H11: =F11-G11 -> 26258 | I11: 0 | K11: 0 | N11: =if(or(H11<>"",I11<>"",K11<>""),sum(H11:K11),"") -> 26258
A12: 11 | B12: =TEXT(C12,"MM")&"-"&text(C12,"MMM") -> 04-Apr | C12: 45759 | D12: =text(C12,"ddd") -> Sat | E12: =WEEKNUM(C12,1) -> 15 | F12: 23040 | G12: =if(F12<>"",F12*0.05,"") -> 1152 | H12: =F12-G12 -> 21888 | I12: 0 | K12: 0 | N12: =if(or(H12<>"",I12<>"",K12<>""),sum(H12:K12),"") -> 21888
A13: 12 | B13: =TEXT(C13,"MM")&"-"&text(C13,"MMM") -> 04-Apr | C13: 45760 | D13: =text(C13,"ddd") -> Sun | E13: =WEEKNUM(C13,1) -> 16 | F13: 19155 | G13: =if(F13<>"",F13*0.05,"") -> 957.75 | H13: =F13-G13 -> 18197.25 | I13: 0 | K13: 0 | N13: =if(or(H13<>"",I13<>"",K13<>""),sum(H13:K13),"") -> 18197.25
... A29: 28 | B29: =TEXT(C29,"MM")&"-"&text(C29,"MMM") -> 04-Apr | C29: 45776 | D29: =text(C29,"ddd") -> Tue | E29: =WEEKNUM(C29,1) -> 18 | F29: 20695 | G29: =if(F29<>"",F29*0.05,"") -> 1034.75 | H29: =F29-G29 -> 19660.25 | I29: 0 | K29: 0 | N29: =if(or(H29<>"",I29<>"",K29<>""),sum(H29:K29),"") -> 19660.25
A30: 29 | B30: =TEXT(C30,"MM")&"-"&text(C30,"MMM") -> 04-Apr | C30: 45777 | D30: =text(C30,"ddd") -> Wed | E30: =WEEKNUM(C30,1) -> 18 | F30: 37420 | G30: =if(F30<>"",F30*0.05,"") -> 1871 | H30: =F30-G30 -> 35549 | I30: 0 | K30: 0 | N30: =if(or(H30<>"",I30<>"",K30<>""),sum(H30:K30),"") -> 35549 | P30: 635558
A31: 30 | B31: =TEXT(C31,"MM")&"-"&text(C31,"MMM") -> 05-May | C31: 45778 | D31: =text(C31,"ddd") -> Thu | E31: =WEEKNUM(C31,1) -> 18 | F31: 27400 | G31: =if(F31<>"",F31*0.05,"") -> 1370 | H31: =F31-G31 -> 26030 | I31: 0 | K31: 0 | N31: =if(or(H31<>"",I31<>"",K31<>""),sum(H31:K31),"") -> 26030
A32: 31 | B32: =TEXT(C32,"MM")&"-"&text(C32,"MMM") -> 05-May | C32: 45779 | D32: =text(C32,"ddd") -> Fri | E32: =WEEKNUM(C32,1) -> 18 | F32: 28540 | G32: =if(F32<>"",F32*0.05,"") -> 1427 | H32: =F32-G32 -> 27113 | I32: 0 | K32: 0 | N32: =if(or(H32<>"",I32<>"",K32<>""),sum(H32:K32),"") -> 27113
A33: 32 | B33: =TEXT(C33,"MM")&"-"&text(C33,"MMM") -> 05-May | C33: 45780 | D33: =text(C33,"ddd") -> Sat | E33: =WEEKNUM(C33,1) -> 18 | F33: 34760 | G33: =if(F33<>"",F33*0.05,"") -> 1738 | H33: =F33-G33 -> 33022 | I33: 0 | K33: 0 | N33: =if(or(H33<>"",I33<>"",K33<>""),sum(H33:K33),"") -> 33022
A34: 33 | B34: =TEXT(C34,"MM")&"-"&text(C34,"MMM") -> 05-May | C34: 45781 | D34: =text(C34,"ddd") -> Sun | E34: =WEEKNUM(C34,1) -> 19 | F34: 0 | G34: =if(F34<>"",F34*0.05,"") -> 0 | H34: =F34-G34 -> 0 | I34: 0 | K34: 0 | N34: =if(or(H34<>"",I34<>"",K34<>""),sum(H34:K34),"") -> 0
A35: 34 | B35: =TEXT(C35,"MM")&"-"&text(C35,"MMM") -> 05-May | C35: 45782 | D35: =text(C35,"ddd") -> Mon | E35: =WEEKNUM(C35,1) -> 19 | F35: 28428 | G35: =if(F35<>"",F35*0.05,"") -> 1421.4 | H35: =F35-G35 -> 27006.6 | I35: 0 | K35: 0 | N35: =if(or(H35<>"",I35<>"",K35<>""),sum(H35:K35),"") -> 27006.6
A36: 35 | B36: =TEXT(C36,"MM")&"-"&text(C36,"MMM") -> 05-May | C36: 45783 | D36: =text(C36,"ddd") -> Tue | E36: =WEEKNUM(C36,1) -> 19 | F36: 26020 | G36: =if(F36<>"",F36*0.05,"") -> 1301 | H36: =F36-G36 -> 24719 | I36: 0 | K36: 0 | N36: =if(or(H36<>"",I36<>"",K36<>""),sum(H36:K36),"") -> 24719
A37: 36 | B37: =TEXT(C37,"MM")&"-"&text(C37,"MMM") -> 05-May | C37: 45784 | D37: =text(C37,"ddd") -> Wed | E37: =WEEKNUM(C37,1) -> 19 | F37: 22465 | G37: =if(F37<>"",F37*0.05,"") -> 1123.25 | H37: =F37-G37 -> 21341.75 | I37: 0 | K37: 0 | N37: =if(or(H37<>"",I37<>"",K37<>""),sum(H37:K37),"") -> 21341.75
A38: 37 | B38: =TEXT(C38,"MM")&"-"&text(C38,"MMM") -> 05-May | C38: 45785 | D38: =text(C38,"ddd") -> Thu | E38: =WEEKNUM(C38,1) -> 19 | F38: 14110 | G38: =if(F38<>"",F38*0.05,"") -> 705.5 | H38: =F38-G38 -> 13404.5 | I38: 0 | K38: 0 | N38: =if(or(H38<>"",I38<>"",K38<>""),sum(H38:K38),"") -> 13404.5
A39: 38 | B39: =TEXT(C39,"MM")&"-"&text(C39,"MMM") -> 05-May | C39: 45786 | D39: =text(C39,"ddd") -> Fri | E39: =WEEKNUM(C39,1) -> 19 | F39: 39260 | G39: =if(F39<>"",F39*0.05,"") -> 1963 | H39: =F39-G39 -> 37297 | I39: 0 | K39: 0 | N39: =if(or(H39<>"",I39<>"",K39<>""),sum(H39:K39),"") -> 37297
A40: 39 | B40: =TEXT(C40,"MM")&"-"&text(C40,"MMM") -> 05-May | C40: 45787 | D40: =text(C40,"ddd") -> Sat | E40: =WEEKNUM(C40,1) -> 19 | F40: 23155 | G40: =if(F40<>"",F40*0.05,"") -> 1157.75 | H40: =F40-G40 -> 21997.25 | I40: 0 | K40: 0 | N40: =if(or(H40<>"",I40<>"",K40<>""),sum(H40:K40),"") -> 21997.25
A41: 40 | B41: =TEXT(C41,"MM")&"-"&text(C41,"MMM") -> 05-May | C41: 45788 | D41: =text(C41,"ddd") -> Sun | E41: =WEEKNUM(C41,1) -> 20 | F41: 0 | G41: =if(F41<>"",F41*0.05,"") -> 0 | H41: =F41-G41 -> 0 | I41: 0 | K41: 0 | N41: =if(or(H41<>"",I41<>"",K41<>""),sum(H41:K41),"") -> 0
A42: 41 | B42: =TEXT(C42,"MM")&"-"&text(C42,"MMM") -> 05-May | C42: 45789 | D42: =text(C42,"ddd") -> Mon | E42: =WEEKNUM(C42,1) -> 20 | F42: 19740 | G42: =if(F42<>"",F42*0.05,"") -> 987 | H42: =F42-G42 -> 18753 | I42: 0 | K42: 0 | N42: =if(or(H42<>"",I42<>"",K42<>""),sum(H42:K42),"") -> 18753
... A60: 59 | B60: =TEXT(C60,"MM")&"-"&text(C60,"MMM") -> 05-May | C60: 45807 | D60: =text(C60,"ddd") -> Fri | E60: =WEEKNUM(C60,1) -> 22 | F60: 33580 | G60: =if(F60<>"",F60*0.05,"") -> 1679 | H60: =F60-G60 -> 31901 | I60: 2812 | K60: 0 | N60: =if(or(H60<>"",I60<>"",K60<>""),sum(H60:K60),"") -> 34713
A61: 60 | B61: =TEXT(C61,"MM")&"-"&text(C61,"MMM") -> 05-May | C61: 45808 | D61: =text(C61,"ddd") -> Sat | E61: =WEEKNUM(C61,1) -> 22 | F61: 38090 | G61: =if(F61<>"",F61*0.05,"") -> 1904.5 | H61: =F61-G61 -> 36185.5 | I61: 5279 | K61: 0 | N61: =if(or(H61<>"",I61<>"",K61<>""),sum(H61:K61),"") -> 41464.5 | P61: 696194
A62: 61 | B62: =TEXT(C62,"MM")&"-"&text(C62,"MMM") -> 06-Jun | C62: 45809 | D62: =text(C62,"ddd") -> Sun | E62: =WEEKNUM(C62,1) -> 23 | F62: 0 | G62: =if(F62<>"",F62*0.05,"") -> 0 | H62: =F62-G62 -> 0 | I62: 0 | K62: 0 | N62: =if(or(H62<>"",I62<>"",K62<>""),sum(H62:K62),"") -> 0
A63: 62 | B63: =TEXT(C63,"MM")&"-"&text(C63,"MMM") -> 06-Jun | C63: 45810 | D63: =text(C63,"ddd") -> Mon | E63: =WEEKNUM(C63,1) -> 23 | F63: 7010 | G63: =if(F63<>"",F63*0.05,"") -> 350.5 | H63: =F63-G63 -> 6659.5 | I63: 2390 | K63: 0 | N63: =if(or(H63<>"",I63<>"",K63<>""),sum(H63:K63),"") -> 9049.5
A64: 63 | B64: =TEXT(C64,"MM")&"-"&text(C64,"MMM") -> 06-Jun | C64: 45811 | D64: =text(C64,"ddd") -> Tue | E64: =WEEKNUM(C64,1) -> 23 | F64: 43200 | G64: =if(F64<>"",F64*0.05,"") -> 2160 | H64: =F64-G64 -> 41040 | I64: 4216 | K64: 0 | N64: =if(or(H64<>"",I64<>"",K64<>""),sum(H64:K64),"") -> 45256
A65: 64 | B65: =TEXT(C65,"MM")&"-"&text(C65,"MMM") -> 06-Jun | C65: 45812 | D65: =text(C65,"ddd") -> Wed | E65: =WEEKNUM(C65,1) -> 23 | F65: 17150 | G65: =if(F65<>"",F65*0.05,"") -> 857.5 | H65: =F65-G65 -> 16292.5 | I65: 5635 | K65: 0 | N65: =if(or(H65<>"",I65<>"",K65<>""),sum(H65:K65),"") -> 21927.5
A66: 65 | B66: =TEXT(C66,"MM")&"-"&text(C66,"MMM") -> 06-Jun | C66: 45813 | D66: =text(C66,"ddd") -> Thu | E66: =WEEKNUM(C66,1) -> 23 | F66: 24722 | G66: =if(F66<>"",F66*0.05,"") -> 1236.1 | H66: =F66-G66 -> 23485.9 | I66: 5683 | K66: 0 | N66: =if(or(H66<>"",I66<>"",K66<>""),sum(H66:K66),"") -> 29168.9
A67: 66 | B67: =TEXT(C67,"MM")&"-"&text(C67,"MMM") -> 06-Jun | C67: 45814 | D67: =text(C67,"ddd") -> Fri | E67: =WEEKNUM(C67,1) -> 23 | F67: 25380 | G67: =if(F67<>"",F67*0.05,"") -> 1269 | H67: =F67-G67 -> 24111 | I67: 3131 | K67: 0 | N67: =if(or(H67<>"",I67<>"",K67<>""),sum(H67:K67),"") -> 27242
A68: 67 | B68: =TEXT(C68,"MM")&"-"&text(C68,"MMM") -> 06-Jun | C68: 45815 | D68: =text(C68,"ddd") -> Sat | E68: =WEEKNUM(C68,1) -> 23 | F68: 37650 | G68: =if(F68<>"",F68*0.05,"") -> 1882.5 | H68: =F68-G68 -> 35767.5 | I68: 7465 | K68: 0 | N68: =if(or(H68<>"",I68<>"",K68<>""),sum(H68:K68),"") -> 43232.5
A69: 68 | B69: =TEXT(C69,"MM")&"-"&text(C69,"MMM") -> 06-Jun | C69: 45816 | D69: =text(C69,"ddd") -> Sun | E69: =WEEKNUM(C69,1) -> 24 | F69: 0 | G69: =if(F69<>"",F69*0.05,"") -> 0 | H69: =F69-G69 -> 0 | I69: 0 | K69: 0 | N69: =if(or(H69<>"",I69<>"",K69<>""),sum(H69:K69),"") -> 0
A70: 69 | B70: =TEXT(C70,"MM")&"-"&text(C70,"MMM") -> 06-Jun | C70: 45817 | D70: =text(C70,"ddd") -> Mon | E70: =WEEKNUM(C70,1) -> 24 | F70: 15615 | G70: =if(F70<>"",F70*0.05,"") -> 780.75 | H70: =F70-G70 -> 14834.25 | I70: 2458 | K70: 0 | N70: =if(or(H70<>"",I70<>"",K70<>""),sum(H70:K70),"") -> 17292.25
A71: 70 | B71: =TEXT(C71,"MM")&"-"&text(C71,"MMM") -> 06-Jun | C71: 45818 | D71: =text(C71,"ddd") -> Tue | E71: =WEEKNUM(C71,1) -> 24 | F71: 15000 | G71: =if(F71<>"",F71*0.05,"") -> 750 | H71: =F71-G71 -> 14250 | I71: 6227 | K71: 0 | N71: =if(or(H71<>"",I71<>"",K71<>""),sum(H71:K71),"") -> 20477
A72: 71 | B72: =TEXT(C72,"MM")&"-"&text(C72,"MMM") -> 06-Jun | C72: 45819 | D72: =text(C72,"ddd") -> Wed | E72: =WEEKNUM(C72,1) -> 24 | F72: 21170 | G72: =if(F72<>"",F72*0.05,"") -> 1058.5 | H72: =F72-G72 -> 20111.5 | I72: 3671 | K72: 0 | N72: =if(or(H72<>"",I72<>"",K72<>""),sum(H72:K72),"") -> 23782.5
A73: =A72+1 -> 72 | B73: =TEXT(C73,"MM")&"-"&text(C73,"MMM") -> 06-Jun | C73: =C72+1 -> 45820 | D73: =text(C73,"ddd") -> Thu | E73: =WEEKNUM(C73,1) -> 24 | F73: 23090 | G73: =if(F73<>"",F73*0.05,"") -> 1154.5 | H73: =F73-G73 -> 21935.5 | I73: 2916 | K73: 0 | N73: =if(or(H73<>"",I73<>"",K73<>""),sum(H73:K73),"") -> 24851.5 | U73: =if(N73=sum(P73:S73),"","Difference: " & N73-sum(P73:S73)) -> Difference: 24851.5
A74: =A73+1 -> 73 | B74: =TEXT(C74,"MM")&"-"&text(C74,"MMM") -> 06-Jun | C74: =C73+1 -> 45821 | D74: =text(C74,"ddd") -> Fri | E74: =WEEKNUM(C74,1) -> 24 | F74: 27305 | G74: =if(F74<>"",F74*0.05,"") -> 1365.25 | H74: =F74-G74 -> 25939.75 | I74: 8791 | K74: 0 | N74: =if(or(H74<>"",I74<>"",K74<>""),sum(H74:K74),"") -> 34730.75 | U74: =if(N74=sum(P74:S74),"","Difference: " & N74-sum(P74:S74)) -> Difference: 34730.75
A75: =A74+1 -> 74 | B75: =TEXT(C75,"MM")&"-"&text(C75,"MMM") -> 06-Jun | C75: =C74+1 -> 45822 | D75: =text(C75,"ddd") -> Sat | E75: =WEEKNUM(C75,1) -> 24 | F75: 35865 | G75: =if(F75<>"",F75*0.05,"") -> 1793.25 | H75: =F75-G75 -> 34071.75 | I75: 4649 | K75: 0 | N75: =if(or(H75<>"",I75<>"",K75<>""),sum(H75:K75),"") -> 38720.75 | U75: =if(N75=sum(P75:S75),"","Difference: " & N75-sum(P75:S75)) -> Difference: 38720.75
A76: =A75+1 -> 75 | B76: =TEXT(C76,"MM")&"-"&text(C76,"MMM") -> 06-Jun | C76: =C75+1 -> 45823 | D76: =text(C76,"ddd") -> Sun | E76: =WEEKNUM(C76,1) -> 25 | F76: 0 | G76: =if(F76<>"",F76*0.05,"") -> 0 | H76: =F76-G76 -> 0 | I76: 0 | K76: 0 | N76: =if(or(H76<>"",I76<>"",K76<>""),sum(H76:K76),"") -> 0 | U76: =if(N76=sum(P76:S76),"","Difference: " & N76-sum(P76:S76))
A77: =A76+1 -> 76 | B77: =TEXT(C77,"MM")&"-"&text(C77,"MMM") -> 06-Jun | C77: =C76+1 -> 45824 | D77: =text(C77,"ddd") -> Mon | E77: =WEEKNUM(C77,1) -> 25 | F77: 17405 | G77: =if(F77<>"",F77*0.05,"") -> 870.25 | H77: =F77-G77 -> 16534.75 | I77: 4401 | K77: 0 | N77: =if(or(H77<>"",I77<>"",K77<>""),sum(H77:K77),"") -> 20935.75 | U77: =if(N77=sum(P77:S77),"","Difference: " & N77-sum(P77:S77)) -> Difference: 20935.75
A78: =A77+1 -> 77 | B78: =TEXT(C78,"MM")&"-"&text(C78,"MMM") -> 06-Jun | C78: =C77+1 -> 45825 | D78: =text(C78,"ddd") -> Tue | E78: =WEEKNUM(C78,1) -> 25 | F78: 18356 | G78: =if(F78<>"",F78*0.05,"") -> 917.8 | H78: =F78-G78 -> 17438.2 | I78: 2202 | K78: 0 | N78: =if(or(H78<>"",I78<>"",K78<>""),sum(H78:K78),"") -> 19640.2 | U78: =if(N78=sum(P78:S78),"","Difference: " & N78-sum(P78:S78)) -> Difference: 19640.2
A79: =A78+1 -> 78 | B79: =TEXT(C79,"MM")&"-"&text(C79,"MMM") -> 06-Jun | C79: 45826 | D79: =text(C79,"ddd") -> Wed | E79: =WEEKNUM(C79,1) -> 25 | F79: 24425 | G79: =if(F79<>"",F79*0.05,"") -> 1221.25 | H79: =F79-G79 -> 23203.75 | I79: 4575 | K79: 0 | N79: =if(or(H79<>"",I79<>"",K79<>""),sum(H79:K79),"") -> 27778.75 | U79: =if(N79=sum(P79:S79),"","Difference: " & N79-sum(P79:S79)) -> Difference: 27778.75
A80: =A79+1 -> 79 | B80: =TEXT(C80,"MM")&"-"&text(C80,"MMM") -> 06-Jun | C80: 45827 | D80: =text(C80,"ddd") -> Thu | E80: =WEEKNUM(C80,1) -> 25 | F80: 18800 | G80: =if(F80<>"",F80*0.05,"") -> 940 | H80: =F80-G80 -> 17860 | I80: 1841 | K80: 0 | N80: =if(or(H80<>"",I80<>"",K80<>""),sum(H80:K80),"") -> 19701 | U80: =if(N80=sum(P80:S80),"","Difference: " & N80-sum(P80:S80)) -> Difference: 19701
A81: =A80+1 -> 80 | B81: =TEXT(C81,"MM")&"-"&text(C81,"MMM") -> 06-Jun | C81: 45828 | D81: =text(C81,"ddd") -> Fri | E81: =WEEKNUM(C81,1) -> 25 | F81: 23960 | G81: =if(F81<>"",F81*0.05,"") -> 1198 | H81: =F81-G81 -> 22762 | I81: 9970 | K81: 1170 | N81: =if(or(H81<>"",I81<>"",K81<>""),sum(H81:K81),"") -> 33902 | U81: =if(N81=sum(P81:S81),"","Difference: " & N81-sum(P81:S81)) -> Difference: 33902
A82: =A81+1 -> 81 | B82: =TEXT(C82,"MM")&"-"&text(C82,"MMM") -> 06-Jun | C82: 45829 | D82: =text(C82,"ddd") -> Sat | E82: =WEEKNUM(C82,1) -> 25 | F82: 38495 | G82: =if(F82<>"",F82*0.05,"") -> 1924.75 | H82: =F82-G82 -> 36570.25 | I82: 6108 | K82: 0 | N82: =if(or(H82<>"",I82<>"",K82<>""),sum(H82:K82),"") -> 42678.25 | U82: =if(N82=sum(P82:S82),"","Difference: " & N82-sum(P82:S82)) -> Difference: 42678.25 | V82: 1103 saray salary
A83: =A82+1 -> 82 | B83: =TEXT(C83,"MM")&"-"&text(C83,"MMM") -> 06-Jun | C83: 45830 | D83: =text(C83,"ddd") -> Sun | E83: =WEEKNUM(C83,1) -> 26 | F83: 0 | G83: =if(F83<>"",F83*0.05,"") -> 0 | H83: =F83-G83 -> 0 | I83: 0 | K83: 0 | N83: =if(or(H83<>"",I83<>"",K83<>""),sum(H83:K83),"") -> 0 | U83: =if(N83=sum(P83:S83),"","Difference: " & N83-sum(P83:S83))
A84: =A83+1 -> 83 | B84: =TEXT(C84,"MM")&"-"&text(C84,"MMM") -> 06-Jun | C84: 45831 | D84: =text(C84,"ddd") -> Mon | E84: =WEEKNUM(C84,1) -> 26 | F84: 7020 | G84: =if(F84<>"",F84*0.05,"") -> 351 | H84: =F84-G84 -> 6669 | I84: 3998 | K84: 0 | N84: =if(or(H84<>"",I84<>"",K84<>""),sum(H84:K84),"") -> 10667 | U84: =if(N84=sum(P84:S84),"","Difference: " & N84-sum(P84:S84)) -> Difference: 10667
A85: =A84+1 -> 84 | B85: =TEXT(C85,"MM")&"-"&text(C85,"MMM") -> 06-Jun | C85: 45832 | D85: =text(C85,"ddd") -> Tue | E85: =WEEKNUM(C85,1) -> 26 | F85: 19580 | G85: =if(F85<>"",F85*0.05,"") -> 979 | H85: =F85-G85 -> 18601 | I85: 5987 | K85: 0 | N85: =if(or(H85<>"",I85<>"",K85<>""),sum(H85:K85),"") -> 24588 | U85: =if(N85=sum(P85:S85),"","Difference: " & N85-sum(P85:S85)) -> Difference: 24588
A86: =A85+1 -> 85 | B86: =TEXT(C86,"MM")&"-"&text(C86,"MMM") -> 06-Jun | C86: 45833 | D86: =text(C86,"ddd") -> Wed | E86: =WEEKNUM(C86,1) -> 26 | F86: 10975 | G86: =if(F86<>"",F86*0.05,"") -> 548.75 | H86: =F86-G86 -> 10426.25 | I86: 3838 | K86: 0 | N86: =if(or(H86<>"",I86<>"",K86<>""),sum(H86:K86),"") -> 14264.25 | U86: =if(N86=sum(P86:S86),"","Difference: " & N86-sum(P86:S86)) -> Difference: 14264.25
A87: =A86+1 -> 86 | B87: =TEXT(C87,"MM")&"-"&text(C87,"MMM") -> 06-Jun | C87: 45834 | D87: =text(C87,"ddd") -> Thu | E87: =WEEKNUM(C87,1) -> 26 | F87: 20845 | G87: =if(F87<>"",F87*0.05,"") -> 1042.25 | H87: =F87-G87 -> 19802.75 | I87: 8902 | K87: 0 | N87: =if(or(H87<>"",I87<>"",K87<>""),sum(H87:K87),"") -> 28704.75 | U87: =if(N87=sum(P87:S87),"","Difference: " & N87-sum(P87:S87)) -> Difference: 28704.75
A88: =A87+1 -> 87 | B88: =TEXT(C88,"MM")&"-"&text(C88,"MMM") -> 06-Jun | C88: 45835 | D88: =text(C88,"ddd") -> Fri | E88: =WEEKNUM(C88,1) -> 26 | F88: 21025 | G88: =if(F88<>"",F88*0.05,"") -> 1051.25 | H88: =F88-G88 -> 19973.75 | I88: 10795 | K88: 0 | N88: =if(or(H88<>"",I88<>"",K88<>""),sum(H88:K88),"") -> 30768.75 | U88: =if(N88=sum(P88:S88),"","Difference: " & N88-sum(P88:S88)) -> Difference: 30768.75
A89: =A88+1 -> 88 | B89: =TEXT(C89,"MM")&"-"&text(C89,"MMM") -> 06-Jun | C89: 45836 | D89: =text(C89,"ddd") -> Sat | E89: =WEEKNUM(C89,1) -> 26 | F89: 36095 | G89: =if(F89<>"",F89*0.05,"") -> 1804.75 | H89: =F89-G89 -> 34290.25 | I89: 9289 | K89: 0 | N89: =if(or(H89<>"",I89<>"",K89<>""),sum(H89:K89),"") -> 43579.25 | U89: =if(N89=sum(P89:S89),"","Difference: " & N89-sum(P89:S89)) -> Difference: 43579.25
A90: =A89+1 -> 89 | B90: =TEXT(C90,"MM")&"-"&text(C90,"MMM") -> 06-Jun | C90: 45837 | D90: =text(C90,"ddd") -> Sun | E90: =WEEKNUM(C90,1) -> 27 | F90: 0 | G90: =if(F90<>"",F90*0.05,"") -> 0 | H90: =F90-G90 -> 0 | I90: 0 | K90: 0 | N90: =if(or(H90<>"",I90<>"",K90<>""),sum(H90:K90),"") -> 0 | U90: =if(N90=sum(P90:S90),"","Difference: " & N90-sum(P90:S90))
A91: =A90+1 -> 90 | B91: =TEXT(C91,"MM")&"-"&text(C91,"MMM") -> 06-Jun | C91: 45838 | D91: =text(C91,"ddd") -> Mon | E91: =WEEKNUM(C91,1) -> 27 | F91: 8565 | G91: =if(F91<>"",F91*0.05,"") -> 428.25 | H91: =F91-G91 -> 8136.75 | I91: 8227 | K91: 0 | N91: =if(or(H91<>"",I91<>"",K91<>""),sum(H91:K91),"") -> 16363.75 | U91: =if(N91=sum(P91:S91),"","Difference: " & N91-sum(P91:S91)) -> Difference: 16363.75
A92: =A91+1 -> 91 | B92: =TEXT(C92,"MM")&"-"&text(C92,"MMM") -> 07-Jul | C92: 45839 | D92: =text(C92,"ddd") -> Tue | E92: =WEEKNUM(C92,1) -> 27 | F92: 25340 | G92: =if(F92<>"",F92*0.05,"") -> 1267 | H92: =F92-G92 -> 24073 | I92: 4026 | K92: 0 | N92: =if(or(H92<>"",I92<>"",K92<>""),sum(H92:K92),"") -> 28099 | U92: =if(N92=sum(P92:S92),"","Difference: " & N92-sum(P92:S92)) -> Difference: 28099
A93: =A92+1 -> 92 | B93: =TEXT(C93,"MM")&"-"&text(C93,"MMM") -> 07-Jul | C93: =C92+1 -> 45840 | D93: =text(C93,"ddd") -> Wed | E93: =WEEKNUM(C93,1) -> 27 | F93: 24670 | G93: =if(F93<>"",F93*0.05,"") -> 1233.5 | H93: =F93-G93 -> 23436.5 | I93: 3381 | K93: 0 | N93: =if(or(H93<>"",I93<>"",K93<>""),sum(H93:K93),"") -> 26817.5 | U93: =if(N93=sum(P93:S93),"","Difference: " & N93-sum(P93:S93)) -> Difference: 26817.5 | W93: 171645
A94: =A93+1 -> 93 | B94: =TEXT(C94,"MM")&"-"&text(C94,"MMM") -> 07-Jul | C94: 45841 | D94: =text(C94,"ddd") -> Thu | E94: =WEEKNUM(C94,1) -> 27 | F94: 16160 | G94: =if(F94<>"",F94*0.05,"") -> 808 | H94: =F94-G94 -> 15352 | I94: 3318 | K94: 0 | N94: =if(or(H94<>"",I94<>"",K94<>""),sum(H94:K94),"") -> 18670 | U94: =if(N94=sum(P94:S94),"","Difference: " & N94-sum(P94:S94)) -> Difference: 18670 | V94: transasia
A95: =A94+1 -> 94 | B95: =TEXT(C95,"MM")&"-"&text(C95,"MMM") -> 07-Jul | C95: =C94+1 -> 45842 | D95: =text(C95,"ddd") -> Fri | E95: =WEEKNUM(C95,1) -> 27 | F95: 39040 | G95: =if(F95<>"",F95*0.05,"") -> 1952 | H95: =F95-G95 -> 37088 | I95: 7141 | K95: 0 | N95: =if(or(H95<>"",I95<>"",K95<>""),sum(H95:K95),"") -> 44229 | U95: =if(N95=sum(P95:S95),"","Difference: " & N95-sum(P95:S95)) -> Difference: 44229 | V95: Swiggy ad campaign started
A96: =A95+1 -> 95 | B96: =TEXT(C96,"MM")&"-"&text(C96,"MMM") -> 07-Jul | C96: =C95+1 -> 45843 | D96: =text(C96,"ddd") -> Sat | E96: =WEEKNUM(C96,1) -> 27 | F96: 48485 | G96: =if(F96<>"",F96*0.05,"") -> 2424.25 | H96: =F96-G96 -> 46060.75 | I96: 12773 | K96: 0 | N96: =if(or(H96<>"",I96<>"",K96<>""),sum(H96:K96),"") -> 58833.75 | U96: =if(N96=sum(P96:S96),"","Difference: " & N96-sum(P96:S96)) -> Difference: 58833.75 | V96: Swiggy deducts 25%
A97: =A96+1 -> 96 | B97: =TEXT(C97,"MM")&"-"&text(C97,"MMM") -> 07-Jul | C97: 45844 | D97: =text(C97,"ddd") -> Sun | E97: =WEEKNUM(C97,1) -> 28 | F97: 0 | G97: =if(F97<>"",F97*0.05,"") -> 0 | H97: =F97-G97 -> 0 | I97: 0 | K97: 0 | N97: =if(or(H97<>"",I97<>"",K97<>""),sum(H97:K97),"") -> 0 | U97: =if(N97=sum(P97:S97),"","Difference: " & N97-sum(P97:S97))
A98: =A97+1 -> 97 | B98: =TEXT(C98,"MM")&"-"&text(C98,"MMM") -> 07-Jul | C98: 45845 | D98: =text(C98,"ddd") -> Mon | E98: =WEEKNUM(C98,1) -> 28 | F98: 14375 | G98: =if(F98<>"",F98*0.05,"") -> 718.75 | H98: =F98-G98 -> 13656.25 | I98: =448*0.75 -> 336 | K98: 0 | N98: =if(or(H98<>"",I98<>"",K98<>""),sum(H98:K98),"") -> 13992.25 | U98: =if(N98=sum(P98:S98),"","Difference: " & N98-sum(P98:S98)) -> Difference: 13992.25 | V98: transasia
A99: =A98+1 -> 98 | B99: =TEXT(C99,"MM")&"-"&text(C99,"MMM") -> 07-Jul | C99: =C98+1 -> 45846 | D99: =text(C99,"ddd") -> Tue | E99: =WEEKNUM(C99,1) -> 28 | F99: =22485 -> 22485 | G99: =if(F99<>"",F99*0.05,"") -> 1124.25 | H99: =F99-G99 -> 21360.75 | I99: 3527 | K99: 0 | N99: =if(or(H99<>"",I99<>"",K99<>""),sum(H99:K99),"") -> 24887.75 | U99: =if(N99=sum(P99:S99),"","Difference: " & N99-sum(P99:S99)) -> Difference: 24887.75
A100: =A99+1 -> 99 | B100: =TEXT(C100,"MM")&"-"&text(C100,"MMM") -> 07-Jul | C100: =C99+1 -> 45847 | D100: =text(C100,"ddd") -> Wed | E100: =WEEKNUM(C100,1) -> 28 | F100: 13100 | G100: =if(F100<>"",F100*0.05,"") -> 655 | H100: =F100-G100 -> 12445 | I100: 8765 | K100: 0 | N100: =if(or(H100<>"",I100<>"",K100<>""),sum(H100:K100),"") -> 21210 | U100: =if(N100=sum(P100:S100),"","Difference: " & N100-sum(P100:S100)) -> Difference: 21210 | V100: Bharat Bandh: Minimal Restaruant operations
A101: =A100+1 -> 100 | B101: =TEXT(C101,"MM")&"-"&text(C101,"MMM") -> 07-Jul | C101: =C100+1 -> 45848 | D101: =text(C101,"ddd") -> Thu | E101: =WEEKNUM(C101,1) -> 28 | F101: 14350 | G101: =if(F101<>"",F101*0.05,"") -> 717.5 | H101: =F101-G101 -> 13632.5 | I101: 10473 | K101: 0 | N101: =if(or(H101<>"",I101<>"",K101<>""),sum(H101:K101),"") -> 24105.5 | U101: =if(N101=sum(P101:S101),"","Difference: " & N101-sum(P101:S101)) -> Difference: 24105.5
A102: =A101+1 -> 101 | B102: =TEXT(C102,"MM")&"-"&text(C102,"MMM") -> 07-Jul | C102: =C101+1 -> 45849 | D102: =text(C102,"ddd") -> Fri | E102: =WEEKNUM(C102,1) -> 28 | F102: 32040 | G102: =if(F102<>"",F102*0.05,"") -> 1602 | H102: =F102-G102 -> 30438 | I102: =17632*0.75 -> 13224 | K102: 0 | N102: =if(or(H102<>"",I102<>"",K102<>""),sum(H102:K102),"") -> 43662 | U102: =if(N102=sum(P102:S102),"","Difference: " & N102-sum(P102:S102)) -> Difference: 43662 | V102: Combo Offer | W102: Rs. 450 refund
A103: =A102+1 -> 102 | B103: =TEXT(C103,"MM")&"-"&text(C103,"MMM") -> 07-Jul | C103: 45850 | D103: =text(C103,"ddd") -> Sat | E103: =WEEKNUM(C103,1) -> 28 | F103: 15050 | G103: =if(F103<>"",F103*0.05,"") -> 752.5 | H103: =F103-G103 -> 14297.5 | I103: =7882*0.75 -> 5911.5 | K103: 0 | N103: =if(or(H103<>"",I103<>"",K103<>""),sum(H103:K103),"") -> 20209
A104: =A103+1 -> 103 | B104: =TEXT(C104,"MM")&"-"&text(C104,"MMM") -> 07-Jul | C104: 45851 | D104: =text(C104,"ddd") -> Sun | E104: =WEEKNUM(C104,1) -> 29 | F104: 0 | G104: =if(F104<>"",F104*0.05,"") -> 0 | H104: =F104-G104 -> 0 | I104: 0 | K104: 0 | N104: =if(or(H104<>"",I104<>"",K104<>""),sum(H104:K104),"") -> 0
A105: =A104+1 -> 104 | B105: =TEXT(C105,"MM")&"-"&text(C105,"MMM") -> 07-Jul | C105: 45852 | D105: =text(C105,"ddd") -> Mon | E105: =WEEKNUM(C105,1) -> 29 | F105: 12800 | G105: =if(F105<>"",F105*0.05,"") -> 640 | H105: =F105-G105 -> 12160 | I105: =7476*0.75 -> 5607 | K105: 0 | N105: =if(or(H105<>"",I105<>"",K105<>""),sum(H105:K105),"") -> 17767
A106: =A105+1 -> 105 | B106: =TEXT(C106,"MM")&"-"&text(C106,"MMM") -> 07-Jul | C106: 45853 | D106: =text(C106,"ddd") -> Tue | E106: =WEEKNUM(C106,1) -> 29 | F106: 29120 | G106: =if(F106<>"",F106*0.05,"") -> 1456 | H106: =F106-G106 -> 27664 | I106: =8858*0.75 -> 6643.5 | K106: 0 | N106: =if(or(H106<>"",I106<>"",K106<>""),sum(H106:K106),"") -> 34307.5
A107: =A106+1 -> 106 | B107: =TEXT(C107,"MM")&"-"&text(C107,"MMM") -> 07-Jul | C107: =C106+1 -> 45854 | D107: =text(C107,"ddd") -> Wed | E107: =WEEKNUM(C107,1) -> 29 | F107: 28555 | G107: =if(F107<>"",F107*0.05,"") -> 1427.75 | H107: =F107-G107 -> 27127.25 | I107: =2532*0.75 -> 1899 | K107: 0 | N107: =if(or(H107<>"",I107<>"",K107<>""),sum(H107:K107),"") -> 29026.25 | V107: Swiggy credit of 41,700.00 to YES Bank
A108: =A107+1 -> 107 | B108: =TEXT(C108,"MM")&"-"&text(C108,"MMM") -> 07-Jul | C108: =C107+1 -> 45855 | D108: =text(C108,"ddd") -> Thu | E108: =WEEKNUM(C108,1) -> 29 | F108: 35305 | G108: =if(F108<>"",F108*0.05,"") -> 1765.25 | H108: =F108-G108 -> 33539.75 | I108: 6618 | K108: 0 | N108: =if(or(H108<>"",I108<>"",K108<>""),sum(H108:K108),"") -> 40157.75
A109: =A108+1 -> 108 | B109: =TEXT(C109,"MM")&"-"&text(C109,"MMM") -> 07-Jul | C109: 45856 | D109: =text(C109,"ddd") -> Fri | E109: =WEEKNUM(C109,1) -> 29 | F109: 28095 | G109: =if(F109<>"",F109*0.05,"") -> 1404.75 | H109: =F109-G109 -> 26690.25 | I109: 8531 | K109: 0 | N109: =if(or(H109<>"",I109<>"",K109<>""),sum(H109:K109),"") -> 35221.25
A110: =A109+1 -> 109 | B110: =TEXT(C110,"MM")&"-"&text(C110,"MMM") -> 07-Jul | C110: 45857 | D110: =text(C110,"ddd") -> Sat | E110: =WEEKNUM(C110,1) -> 29 | F110: 26710 | G110: =if(F110<>"",F110*0.05,"") -> 1335.5 | H110: =F110-G110 -> 25374.5 | I110: =11760*0.75 -> 8820 | K110: 0 | L110: 2828 | N110: =if(or(H110<>"",I110<>"",K110<>""),sum(H110:L110),"") -> 37022.5 | T110: 3940
A111: =A110+1 -> 110 | B111: =TEXT(C111,"MM")&"-"&text(C111,"MMM") -> 07-Jul | C111: 45858 | D111: =text(C111,"ddd") -> Sun | E111: =WEEKNUM(C111,1) -> 30 | F111: 0 | G111: =if(F111<>"",F111*0.05,"") -> 0 | H111: =F111-G111 -> 0 | I111: 0 | K111: 0 | L111: 0 | N111: =if(or(H111<>"",I111<>"",K111<>""),sum(H111:L111),"") -> 0
A112: =A111+1 -> 111 | B112: =TEXT(C112,"MM")&"-"&text(C112,"MMM") -> 07-Jul | C112: 45859 | D112: =text(C112,"ddd") -> Mon | E112: =WEEKNUM(C112,1) -> 30 | F112: 13065 | G112: =if(F112<>"",F112*0.05,"") -> 653.25 | H112: =F112-G112 -> 12411.75 | I112: 8975 | K112: 0 | L112: 748 | N112: =if(or(H112<>"",I112<>"",K112<>""),sum(H112:L112),"") -> 22134.75 | V112: INR 2,50,000 paid to Sumit
A113: =A112+1 -> 112 | B113: =TEXT(C113,"MM")&"-"&text(C113,"MMM") -> 07-Jul | C113: =C112+1 -> 45860 | D113: =text(C113,"ddd") -> Tue | E113: =WEEKNUM(C113,1) -> 30 | F113: 22800 | G113: =if(F113<>"",F113*0.05,"") -> 1140 | H113: =F113-G113 -> 21660 | I113: =4984*0.75 -> 3738 | K113: 0 | L113: 748 | N113: =if(or(H113<>"",I113<>"",K113<>""),sum(H113:L113),"") -> 26146 | T113: 3535
A114: =A113+1 -> 113 | B114: =TEXT(C114,"MM")&"-"&text(C114,"MMM") -> 07-Jul | C114: 45861 | D114: =text(C114,"ddd") -> Wed | E114: =WEEKNUM(C114,1) -> 30 | F114: 27890 | G114: =if(F114<>"",F114*0.05,"") -> 1394.5 | H114: =F114-G114 -> 26495.5 | I114: =6482*0.75 -> 4861.5 | K114: 0 | L114: 490 | N114: =if(or(H114<>"",I114<>"",K114<>""),sum(H114:L114),"") -> 31847
A115: =A114+1 -> 114 | B115: =TEXT(C115,"MM")&"-"&text(C115,"MMM") -> 07-Jul | C115: 45862 | D115: =text(C115,"ddd") -> Thu | E115: =WEEKNUM(C115,1) -> 30 | F115: 24620 | G115: =if(F115<>"",F115*0.05,"") -> 1231 | H115: =F115-G115 -> 23389 | I115: =8714*0.75 -> 6535.5 | K115: 0 | L115: 480 | N115: =if(or(H115<>"",I115<>"",K115<>""),sum(H115:L115),"") -> 30404.5
A116: =A115+1 -> 115 | B116: =TEXT(C116,"MM")&"-"&text(C116,"MMM") -> 07-Jul | C116: 45863 | D116: =text(C116,"ddd") -> Fri | E116: =WEEKNUM(C116,1) -> 30 | F116: 25255 | G116: =if(F116<>"",F116*0.05,"") -> 1262.75 | H116: =F116-G116 -> 23992.25 | I116: 17293 | K116: 0 | L116: 1467 | N116: =if(or(H116<>"",I116<>"",K116<>""),sum(H116:L116),"") -> 42752.25
A117: =A116+1 -> 116 | B117: =TEXT(C117,"MM")&"-"&text(C117,"MMM") -> 07-Jul | C117: 45864 | D117: =text(C117,"ddd") -> Sat | E117: =WEEKNUM(C117,1) -> 30 | F117: 28960 | G117: =if(F117<>"",F117*0.05,"") -> 1448 | H117: =F117-G117 -> 27512 | I117: 23068 | K117: 0 | L117: 3497 | N117: =if(or(H117<>"",I117<>"",K117<>""),sum(H117:L117),"") -> 54077
A118: =A117+1 -> 117 | B118: =TEXT(C118,"MM")&"-"&text(C118,"MMM") -> 07-Jul | C118: 45865 | D118: =text(C118,"ddd") -> Sun | E118: =WEEKNUM(C118,1) -> 31 | F118: 0 | G118: =if(F118<>"",F118*0.05,"") -> 0 | H118: =F118-G118 -> 0 | I118: 0 | K118: 0 | L118: 0 | N118: =if(or(H118<>"",I118<>"",K118<>""),sum(H118:L118),"") -> 0
A119: =A118+1 -> 118 | B119: =TEXT(C119,"MM")&"-"&text(C119,"MMM") -> 07-Jul | C119: 45866 | D119: =text(C119,"ddd") -> Mon | E119: =WEEKNUM(C119,1) -> 31 | F119: 9970 | G119: =if(F119<>"",F119*0.05,"") -> 498.5 | H119: =F119-G119 -> 9471.5 | I119: 7386 | K119: 0 | L119: 1086 | N119: =if(or(H119<>"",I119<>"",K119<>""),sum(H119:L119),"") -> 17943.5
A120: =A119+1 -> 119 | B120: =TEXT(C120,"MM")&"-"&text(C120,"MMM") -> 07-Jul | C120: 45867 | D120: =text(C120,"ddd") -> Tue | E120: =WEEKNUM(C120,1) -> 31 | F120: 17255 | G120: =if(F120<>"",F120*0.05,"") -> 862.75 | H120: =F120-G120 -> 16392.25 | I120: 4554 | K120: 0 | L120: 1220 | N120: =if(or(H120<>"",I120<>"",K120<>""),sum(H120:L120),"") -> 22166.25
A121: =A120+1 -> 120 | B121: =TEXT(C121,"MM")&"-"&text(C121,"MMM") -> 07-Jul | C121: 45868 | D121: =text(C121,"ddd") -> Wed | E121: =WEEKNUM(C121,1) -> 31 | F121: 33565 | G121: =if(F121<>"",F121*0.05,"") -> 1678.25 | H121: =F121-G121 -> 31886.75 | I121: =6468*0.75 -> 4851 | K121: 0 | L121: 1441 | N121: =if(or(H121<>"",I121<>"",K121<>""),sum(H121:L121),"") -> 38178.75
A122: =A121+1 -> 121 | B122: =TEXT(C122,"MM")&"-"&text(C122,"MMM") -> 07-Jul | C122: 45869 | D122: =text(C122,"ddd") -> Thu | E122: =WEEKNUM(C122,1) -> 31 | F122: 23715 | G122: =if(F122<>"",F122*0.05,"") -> 1185.75 | H122: =F122-G122 -> 22529.25 | I122: 5928 | K122: 0 | L122: 1564 | N122: =if(or(H122<>"",I122<>"",K122<>""),sum(H122:L122),"") -> 30021.25
A123: =A122+1 -> 122 | B123: =TEXT(C123,"MM")&"-"&text(C123,"MMM") -> 08-Aug | C123: 45870 | D123: =text(C123,"ddd") -> Fri | E123: =WEEKNUM(C123,1) -> 31 | F123: 22585 | G123: =if(F123<>"",F123*0.05,"") -> 1129.25 | H123: =F123-G123 -> 21455.75 | I123: 7021.5 | K123: 0 | L123: 0 | N123: =if(or(H123<>"",I123<>"",K123<>""),sum(H123:L123),"") -> 28477.25
A124: =A123+1 -> 123 | B124: =TEXT(C124,"MM")&"-"&text(C124,"MMM") -> 08-Aug | C124: 45871 | D124: =text(C124,"ddd") -> Sat | E124: =WEEKNUM(C124,1) -> 31 | F124: 31900 | G124: =if(F124<>"",F124*0.05,"") -> 1595 | H124: =F124-G124 -> 30305 | I124: =22496*0.75 -> 16872 | K124: 0 | L124: =3868*0.75 -> 2901 | N124: =if(or(H124<>"",I124<>"",K124<>""),sum(H124:L124),"") -> 50078 | P124: 193814
A125: =A124+1 -> 124 | B125: =TEXT(C125,"MM")&"-"&text(C125,"MMM") -> 08-Aug | C125: 45872 | D125: =text(C125,"ddd") -> Sun | E125: =WEEKNUM(C125,1) -> 32 | F125: 0 | G125: =if(F125<>"",F125*0.05,"") -> 0 | H125: =F125-G125 -> 0 | I125: 0 | K125: 0 | L125: 0 | N125: 0
A126: =A125+1 -> 125 | B126: =TEXT(C126,"MM")&"-"&text(C126,"MMM") -> 08-Aug | C126: 45873 | D126: =text(C126,"ddd") -> Mon | E126: =WEEKNUM(C126,1) -> 32 | F126: 11875 | G126: =if(F126<>"",F126*0.05,"") -> 593.75 | H126: =F126-G126 -> 11281.25 | I126: =8506*0.75 -> 6379.5 | K126: 0 | L126: =(2347-749)*0.75 -> 1198.5 | N126: =if(or(H126<>"",I126<>"",K126<>""),sum(H126:L126),"") -> 18859.25
A127: =A126+1 -> 126 | B127: =TEXT(C127,"MM")&"-"&text(C127,"MMM") -> 08-Aug | C127: 45874 | D127: =text(C127,"ddd") -> Tue | E127: =WEEKNUM(C127,1) -> 32 | F127: 18454 | G127: =if(F127<>"",F127*0.05,"") -> 922.7 | H127: =F127-G127 -> 17531.3 | I127: =9536*0.75 -> 7152 | K127: 0 | L127: =749*0.75 -> 561.75 | N127: =if(or(H127<>"",I127<>"",K127<>""),sum(H127:L127),"") -> 25245.05
A128: =A127+1 -> 127 | B128: =TEXT(C128,"MM")&"-"&text(C128,"MMM") -> 08-Aug | C128: 45875 | D128: =text(C128,"ddd") -> Wed | E128: =WEEKNUM(C128,1) -> 32 | F128: 14580 | G128: =if(F128<>"",F128*0.05,"") -> 729 | H128: =F128-G128 -> 13851 | I128: 9375 | K128: 0 | L128: 0 | N128: =if(or(H128<>"",I128<>"",K128<>""),sum(H128:L128),"") -> 23226
A129: =A128+1 -> 128 | B129: =TEXT(C129,"MM")&"-"&text(C129,"MMM") -> 08-Aug | C129: 45876 | D129: =text(C129,"ddd") -> Thu | E129: =WEEKNUM(C129,1) -> 32 | F129: 22615 | G129: =if(F129<>"",F129*0.05,"") -> 1130.75 | H129: =F129-G129 -> 21484.25 | I129: 7185 | K129: 0 | L129: 409 | N129: =if(or(H129<>"",I129<>"",K129<>""),sum(H129:L129),"") -> 29078.25
A130: =A129+1 -> 129 | B130: =TEXT(C130,"MM")&"-"&text(C130,"MMM") -> 08-Aug | C130: 45877 | D130: =text(C130,"ddd") -> Fri | E130: =WEEKNUM(C130,1) -> 32 | F130: 40455 | G130: =if(F130<>"",F130*0.05,"") -> 2022.75 | H130: =F130-G130 -> 38432.25 | I130: 9441 | K130: 0 | L130: 213 | N130: =if(or(H130<>"",I130<>"",K130<>""),sum(H130:L130),"") -> 48086.25
A131: =A130+1 -> 130 | B131: =TEXT(C131,"MM")&"-"&text(C131,"MMM") -> 08-Aug | C131: 45878 | D131: =text(C131,"ddd") -> Sat | E131: =WEEKNUM(C131,1) -> 32 | F131: 28866 | G131: =if(F131<>"",F131*0.05,"") -> 1443.3 | H131: =F131-G131 -> 27422.7 | I131: 9785 | K131: 0 | L131: 614 | N131: =if(or(H131<>"",I131<>"",K131<>""),sum(H131:L131),"") -> 37821.7 | P131: 189158
A132: =A131+1 -> 131 | B132: =TEXT(C132,"MM")&"-"&text(C132,"MMM") -> 08-Aug | C132: 45879 | D132: sun | E132: =WEEKNUM(C132,1) -> 33 | F132: 0 | G132: =if(F132<>"",F132*0.05,"") -> 0 | H132: =F132-G132 -> 0 | I132: 0 | K132: 0 | L132: 0 | N132: =if(or(H132<>"",I132<>"",K132<>""),sum(H132:L132),"") -> 0
...

Sheet MenuUpdater
A1: Sl. | B1: Item ID | C1: Category | D1: Item Name | E1: Variation | F1: Online Display Name | G1: Item Type | H1: Price | I1: Description | J1: SwiggyPrice | K1: SwiggyIncome | L1: Dietary | M1: Short Code | N1: Sap Code | O1: HSN Code | P1: Weight | Q1: Weight Unit | R1: Rank | S1: Packing Charges | T1: Expose in Captain | U1: Goods/Services | V1: Short Code Two | W1: Allow Decimal Qty | X1: Manufacturing Date (DD-MM-YYYY) | Y1: Expiry Date (DD-MM-YYYY)
A2: 1 | B2: 154634344 | C2: Western | D2: Cajun Fried Prawns | G2: item | H2: 380 | I2: =H2+H2*(1/(0.78)-1) -> 487.17949 | L2: non-veg | M2: ~1 | R2: 1 | S2: 0 | T2: Yes | W2: Yes
A3: 2 | B3: 154634345 | C3: Western | D3: Moroccan Meat Balls | G3: item | H3: 360 | I3: =H3+H3*(1/(1-0.22)-1) -> 461.53846 | L3: non-veg | M3: ~2 | R3: 1 | S3: 0 | T3: Yes | W3: Yes
A4: 3 | B4: 154634346 | C4: Western | D4: Jamaican Chicken Skewer | G4: item | H4: 310 | I4: =H4+H4*(1/(1-0.22)-1) -> 397.4359 | L4: non-veg | M4: ~3 | R4: 1 | S4: 0 | T4: Yes | W4: Yes
A5: 4 | B5: 154634347 | C5: Western | D5: Spicy Corn & Cheese Balls | G5: item | H5: 310 | I5: =H5+H5*(1/(1-0.22)-1) -> 397.4359 | L5: veg | M5: ~4 | R5: 1 | S5: 0 | T5: Yes | W5: Yes
A6: 5 | B6: 154634348 | C6: Western | D6: Nachos With Confit Tomato Salsa | G6: item | H6: 260 | I6: =H6+H6*(1/(1-0.22)-1) -> 333.33333 | L6: veg | M6: ~5 | R6: 1 | S6: 0 | T6: Yes | W6: Yes
A7: 6 | B7: 154634349 | C7: Pastas | D7: Pasta Arabiata | G7: item | H7: 340 | I7: =H7+H7*(1/(1-0.22)-1) -> 435.89744 | L7: veg | M7: ~6 | R7: 1 | S7: 0 | T7: Yes | W7: Yes
A8: 7 | B8: 154634350 | C8: Pastas | D8: Classic Pasta | G8: item | H8: 470 | I8: =H8+H8*(1/(1-0.22)-1) -> 602.5641 | L8: non-veg | M8: ~8 | R8: 1 | S8: 0 | T8: Yes | W8: Yes
A9: 8 | B9: 154634351 | C9: Wraps/Burger | D9: Mexican Tostadas | G9: item | H9: 380 | I9: =H9+H9*(1/(1-0.22)-1) -> 487.17949 | L9: veg | M9: ~9 | R9: 1 | S9: 0 | T9: Yes | W9: Yes
A10: 9 | B10: 154634352 | C10: Wraps/Burger | D10: Chicken Quesadilla | G10: item | H10: 420 | I10: =H10+H10*(1/(1-0.22)-1) -> 538.46154 | L10: non-veg | M10: ~10 | R10: 1 | S10: 0 | T10: Yes | W10: Yes
A11: 10 | B11: 154634353 | C11: Mains | D11: Stuffed Chicken Roulade | G11: item | H11: 490 | I11: =H11+H11*(1/(1-0.22)-1) -> 628.20513 | L11: non-veg | M11: stuffed chicken roul | R11: 1 | S11: 0 | T11: Yes | W11: Yes
A12: 11 | B12: 154634354 | C12: Mains | D12: Grilled Beef Tenderloin | G12: item | H12: 520 | I12: =H12+H12*(1/(1-0.22)-1) -> 666.66667 | L12: non-veg | M12: grilled beef tenderl | R12: 1 | S12: 0 | T12: Yes | W12: Yes
A13: 12 | B13: 154634355 | C13: Asian | D13: Asian Bbq Pork Ribs | G13: item | H13: 380 | I13: =H13+H13*(1/(1-0.22)-1) -> 487.17949 | L13: non-veg | M13: ~14 | R13: 1 | S13: 0 | T13: Yes | W13: Yes
A14: 13 | B14: 154634356 | C14: Mains | D14: Shepherds Pie | G14: item | H14: 520 | I14: =H14+H14*(1/(1-0.22)-1) -> 666.66667 | L14: non-veg | M14: shepherds pie | R14: 1 | S14: 0 | T14: Yes | W14: Yes
... A35: 34 | B35: 154634377 | C35: Authentic Japanese Sushi | D35: Crunchy Caprese Roll | G35: item | H35: 450 | I35: =H35+H35*(1/(1-0.22)-1) -> 576.92308 | L35: veg | M35: ~36 | R35: 1 | S35: 0 | T35: Yes | W35: Yes
A36: 35 | B36: 154634378 | C36: Veg Pizzas | D36: Wild Mushroom | G36: item | H36: 0 | I36: =H36+H36*(1/(1-0.22)-1) -> 0 | K36: =if(J36<>"",J36-J36*20%,"") | L36: veg | M36: ~37 | R36: 1 | S36: 0 | T36: Yes | W36: Yes
A37: 36 | B37: 154634412 | C37: Veg Pizzas | D37: Wild Mushroom (8 Inch) | E37: 8 Inch | G37: variation | H37: 375 | I37: =H37+H37*(1/(1-0.22)-1) -> 480.76923 | K37: =if(J37<>"",J37-J37*20%,"") | L37: veg | R37: 1 | S37: 0 | T37: Yes | W37: Yes
A38: 37 | B38: 154634413 | C38: Veg Pizzas | D38: Wild Mushroom (10 Inch) | E38: 10 Inch | G38: variation | H38: 525 | I38: =H38+H38*(1/(1-0.22)-1) -> 673.07692 | K38: =if(J38<>"",J38-J38*20%,"") | L38: veg | R38: 1 | S38: 0 | T38: Yes | W38: Yes
A39: 38 | B39: 154634414 | C39: Veg Pizzas | D39: Wild Mushroom (12 Inch) | E39: 12 Inch | G39: variation | H39: 650 | I39: =H39+H39*(1/(1-0.22)-1) -> 833.33333 | K39: =if(J39<>"",J39-J39*20%,"") | L39: veg | R39: 1 | S39: 0 | T39: Yes | W39: Yes
A40: 39 | B40: 154634379 | C40: Veg Pizzas | D40: Melanzane | G40: item | H40: 0 | I40: =H40+H40*(1/(1-0.22)-1) -> 0 | L40: veg | M40: ~38 | R40: 1 | S40: 0 | T40: Yes | W40: Yes
A41: 40 | B41: 154634415 | C41: Veg Pizzas | D41: Melanzane (8 Inch) | E41: 8 Inch | G41: variation | H41: 350 | I41: =H41+H41*(1/(1-0.22)-1) -> 448.71795 | K41: =if(J41<>"",J41-J41*20%,"") | L41: veg | R41: 1 | S41: 0 | T41: Yes | W41: Yes
A42: 41 | B42: 154634416 | C42: Veg Pizzas | D42: Melanzane (10 Inch) | E42: 10 Inch | G42: variation | H42: 450 | I42: =H42+H42*(1/(1-0.22)-1) -> 576.92308 | K42: =if(J42<>"",J42-J42*20%,"") | L42: veg | R42: 1 | S42: 0 | T42: Yes | W42: Yes
A43: 42 | B43: 154634417 | C43: Veg Pizzas | D43: Melanzane (12 Inch) | E43: 12 Inch | G43: variation | H43: 550 | I43: =H43+H43*(1/(1-0.22)-1) -> 705.12821 | K43: =if(J43<>"",J43-J43*20%,"") | L43: veg | R43: 1 | S43: 0 | T43: Yes | W43: Yes
A44: 43 | B44: 154634380 | C44: Veg Pizzas | D44: Premavera | G44: item | H44: 0 | I44: =H44+H44*(1/(1-0.22)-1) -> 0 | L44: veg | M44: ~39 | R44: 1 | S44: 0 | T44: Yes | W44: Yes
A45: 44 | B45: 154634418 | C45: Veg Pizzas | D45: Premavera (8 Inch) | E45: 8 Inch | G45: variation | H45: 375 | I45: =H45+H45*(1/(1-0.22)-1) -> 480.76923 | K45: =if(J45<>"",J45-J45*20%,"") | L45: veg | R45: 1 | S45: 0 | T45: Yes | W45: Yes
A46: 45 | B46: 154634419 | C46: Veg Pizzas | D46: Premavera (10 Inch) | E46: 10 Inch | G46: variation | H46: 525 | I46: =H46+H46*(1/(1-0.22)-1) -> 673.07692 | K46: =if(J46<>"",J46-J46*20%,"") | L46: veg | R46: 1 | S46: 0 | T46: Yes | W46: Yes
A47: 46 | B47: 154634420 | C47: Veg Pizzas | D47: Premavera (12 Inch) | E47: 12 Inch | G47: variation | H47: 650 | I47: =H47+H47*(1/(1-0.22)-1) -> 833.33333 | K47: =if(J47<>"",J47-J47*20%,"") | L47: veg | R47: 1 | S47: 0 | T47: Yes | W47: Yes
A48: 47 | B48: 154634381 | C48: Veg Pizzas | D48: Grilled Paneer | G48: item | H48: 0 | I48: =H48+H48*(1/(1-0.22)-1) -> 0 | L48: veg | M48: ~40 | R48: 1 | S48: 0 | T48: Yes | W48: Yes
A49: 48 | B49: 154634421 | C49: Veg Pizzas | D49: Grilled Paneer (8 Inch) | E49: 8 Inch | G49: variation | H49: 375 | I49: =H49+H49*(1/(1-0.22)-1) -> 480.76923 | K49: =if(J49<>"",J49-J49*20%,"") | L49: veg | R49: 1 | S49: 0 | T49: Yes | W49: Yes
A50: 49 | B50: 154634422 | C50: Veg Pizzas | D50: Grilled Paneer (10 Inch) | E50: 10 Inch | G50: variation | H50: 525 | I50: =H50+H50*(1/(1-0.22)-1) -> 673.07692 | K50: =if(J50<>"",J50-J50*20%,"") | L50: veg | R50: 1 | S50: 0 | T50: Yes | W50: Yes
A51: 50 | B51: 154634423 | C51: Veg Pizzas | D51: Grilled Paneer (12 Inch) | E51: 12 Inch | G51: variation | H51: 650 | I51: =H51+H51*(1/(1-0.22)-1) -> 833.33333 | K51: =if(J51<>"",J51-J51*20%,"") | L51: veg | R51: 1 | S51: 0 | T51: Yes | W51: Yes
A52: 51 | B52: 154634382 | C52: Veg Pizzas | D52: Margherita | G52: item | H52: 0 | I52: =H52+H52*(1/(1-0.22)-1) -> 0 | L52: veg | M52: ~41 | R52: 1 | S52: 0 | T52: Yes | W52: Yes
A53: 52 | B53: 154634424 | C53: Veg Pizzas | D53: Margherita (8 Inch) | E53: 8 Inch | G53: variation | H53: 325 | I53: =H53+H53*(1/(1-0.22)-1) -> 416.66667 | K53: =if(J53<>"",J53-J53*20%,"") | L53: veg | R53: 1 | S53: 0 | T53: Yes | W53: Yes
A54: 53 | B54: 154634425 | C54: Veg Pizzas | D54: Margherita (10 Inch) | E54: 10 Inch | G54: variation | H54: 450 | I54: =H54+H54*(1/(1-0.22)-1) -> 576.92308 | K54: =if(J54<>"",J54-J54*20%,"") | L54: veg | R54: 1 | S54: 0 | T54: Yes | W54: Yes
A55: 54 | B55: 154634426 | C55: Veg Pizzas | D55: Margherita (12 Inch) | E55: 12 Inch | G55: variation | H55: 600 | I55: =H55+H55*(1/(1-0.22)-1) -> 769.23077 | K55: =if(J55<>"",J55-J55*20%,"") | L55: veg | R55: 1 | S55: 0 | T55: Yes | W55: Yes
A56: 55 | B56: 154634383 | C56: Veg Pizzas | D56: Quattro Formaggi | G56: item | H56: 0 | I56: =H56+H56*(1/(1-0.22)-1) -> 0 | L56: veg | M56: ~42 | R56: 1 | S56: 0 | T56: Yes | W56: Yes
A57: 56 | B57: 154634427 | C57: Veg Pizzas | D57: Quattro Formaggi (8 Inch) | E57: 8 Inch | G57: variation | H57: 425 | I57: =H57+H57*(1/(1-0.22)-1) -> 544.87179 | K57: =if(J57<>"",J57-J57*20%,"") | L57: veg | R57: 1 | S57: 0 | T57: Yes | W57: Yes
A58: 57 | B58: 154634428 | C58: Veg Pizzas | D58: Quattro Formaggi (10 Inch) | E58: 10 Inch | G58: variation | H58: 575 | I58: =H58+H58*(1/(1-0.22)-1) -> 737.17949 | K58: =if(J58<>"",J58-J58*20%,"") | L58: veg | R58: 1 | S58: 0 | T58: Yes | W58: Yes
A59: 58 | B59: 154634429 | C59: Veg Pizzas | D59: Quattro Formaggi (12 Inch) | E59: 12 Inch | G59: variation | H59: 725 | I59: =H59+H59*(1/(1-0.22)-1) -> 929.48718 | K59: =if(J59<>"",J59-J59*20%,"") | L59: veg | R59: 1 | S59: 0 | T59: Yes | W59: Yes
A60: 59 | B60: 154634384 | C60: Non Veg Pizzas | D60: Italian Salsiccia | G60: item | H60: 0 | I60: =H60+H60*(1/(1-0.22)-1) -> 0 | L60: non-veg | M60: ~43 | R60: 1 | S60: 0 | T60: Yes | W60: Yes
A61: 60 | B61: 154634430 | C61: Non Veg Pizzas | D61: Italian Salsiccia (8 Inch) | E61: 8 Inch | G61: variation | H61: 425 | I61: =H61+H61*(1/(1-0.22)-1) -> 544.87179 | K61: =if(J61<>"",J61-J61*20%,"") | L61: non-veg | R61: 1 | S61: 0 | T61: Yes | W61: Yes
A62: 61 | B62: 154634431 | C62: Non Veg Pizzas | D62: Italian Salsiccia (10 Inch) | E62: 10 Inch | G62: variation | H62: 575 | I62: =H62+H62*(1/(1-0.22)-1) -> 737.17949 | K62: =if(J62<>"",J62-J62*20%,"") | L62: non-veg | R62: 1 | S62: 0 | T62: Yes | W62: Yes
A63: 62 | B63: 154634432 | C63: Non Veg Pizzas | D63: Italian Salsiccia (12 Inch) | E63: 12 Inch | G63: variation | H63: 700 | I63: =H63+H63*(1/(1-0.22)-1) -> 897.4359 | K63: =if(J63<>"",J63-J63*20%,"") | L63: non-veg | R63: 1 | S63: 0 | T63: Yes | W63: Yes
A64: 63 | B64: 154634385 | C64: Non Veg Pizzas | D64: Capricciosa | G64: item | H64: 0 | I64: =H64+H64*(1/(1-0.22)-1) -> 0 | L64: non-veg | M64: ~44 | R64: 1 | S64: 0 | T64: Yes | W64: Yes
A65: 64 | B65: 154634433 | C65: Non Veg Pizzas | D65: Capricciosa (8 Inch) | E65: 8 Inch | G65: variation | H65: 425 | I65: =H65+H65*(1/(1-0.22)-1) -> 544.87179 | K65: =if(J65<>"",J65-J65*20%,"") | L65: non-veg | R65: 1 | S65: 0 | T65: Yes | W65: Yes
A66: 65 | B66: 154634434 | C66: Non Veg Pizzas | D66: Capricciosa (10 Inch) | E66: 10 Inch | G66: variation | H66: 575 | I66: =H66+H66*(1/(1-0.22)-1) -> 737.17949 | K66: =if(J66<>"",J66-J66*20%,"") | L66: non-veg | R66: 1 | S66: 0 | T66: Yes | W66: Yes
A67: 66 | B67: 154634435 | C67: Non Veg Pizzas | D67: Capricciosa (12 Inch) | E67: 12 Inch | G67: variation | H67: 700 | I67: =H67+H67*(1/(1-0.22)-1) -> 897.4359 | K67: =if(J67<>"",J67-J67*20%,"") | L67: non-veg | R67: 1 | S67: 0 | T67: Yes | W67: Yes
A68: 67 | B68: 154634386 | C68: Non Veg Pizzas | D68: Pepperoni | G68: item | H68: 0 | I68: =H68+H68*(1/(1-0.22)-1) -> 0 | L68: non-veg | M68: ~45 | R68: 1 | S68: 0 | T68: Yes | W68: Yes
A69: 68 | B69: 154634436 | C69: Non Veg Pizzas | D69: Pepperoni (8 Inch) | E69: 8 Inch | G69: variation | H69: 425 | I69: =H69+H69*(1/(1-0.22)-1) -> 544.87179 | K69: =if(J69<>"",J69-J69*20%,"") | L69: non-veg | R69: 1 | S69: 0 | T69: Yes | W69: Yes
A70: 69 | B70: 154634437 | C70: Non Veg Pizzas | D70: Pepperoni (10 Inch) | E70: 10 Inch | G70: variation | H70: 575 | I70: =H70+H70*(1/(1-0.22)-1) -> 737.17949 | K70: =if(J70<>"",J70-J70*20%,"") | L70: non-veg | R70: 1 | S70: 0 | T70: Yes | W70: Yes
A71: 70 | B71: 154634438 | C71: Non Veg Pizzas | D71: Pepperoni (12 Inch) | E71: 12 Inch | G71: variation | H71: 750 | I71: =H71+H71*(1/(1-0.22)-1) -> 961.53846 | K71: =if(J71<>"",J71-J71*20%,"") | L71: non-veg | R71: 1 | S71: 0 | T71: Yes | W71: Yes
A72: 71 | B72: 154634387 | C72: Non Veg Pizzas | D72: Bbq Chicken Pizza | G72: item | H72: 0 | I72: =H72+H72*(1/(1-0.22)-1) -> 0 | L72: non-veg | M72: ~46 | R72: 1 | S72: 0 | T72: Yes | W72: Yes
A73: 72 | B73: 154634439 | C73: Non Veg Pizzas | D73: Bbq Chicken Pizza (8 Inch) | E73: 8 Inch | G73: variation | H73: 425 | I73: =H73+H73*(1/(1-0.22)-1) -> 544.87179 | K73: =if(J73<>"",J73-J73*20%,"") | L73: non-veg | R73: 1 | S73: 0 | T73: Yes | W73: Yes
A74: 73 | B74: 154634440 | C74: Non Veg Pizzas | D74: Bbq Chicken Pizza (10 Inch) | E74: 10 Inch | G74: variation | H74: 575 | I74: =H74+H74*(1/(1-0.22)-1) -> 737.17949 | K74: =if(J74<>"",J74-J74*20%,"") | L74: non-veg | R74: 1 | S74: 0 | T74: Yes | W74: Yes
A75: 74 | B75: 154634441 | C75: Non Veg Pizzas | D75: Bbq Chicken Pizza (12 Inch) | E75: 12 Inch | G75: variation | H75: 725 | I75: =H75+H75*(1/(1-0.22)-1) -> 929.48718 | K75: =if(J75<>"",J75-J75*20%,"") | L75: non-veg | R75: 1 | S75: 0 | T75: Yes | W75: Yes
A76: 75 | B76: 154634388 | C76: Non Veg Pizzas | D76: Jamaican Jerk Pizza | G76: item | H76: 0 | I76: =H76+H76*(1/(1-0.22)-1) -> 0 | L76: non-veg | M76: ~47 | R76: 1 | S76: 0 | T76: Yes | W76: Yes
A77: 76 | B77: 154634442 | C77: Non Veg Pizzas | D77: Jamaican Jerk Pizza (8 Inch) | E77: 8 Inch | G77: variation | H77: 425 | I77: =H77+H77*(1/(1-0.22)-1) -> 544.87179 | K77: =if(J77<>"",J77-J77*20%,"") | L77: non-veg | R77: 1 | S77: 0 | T77: Yes | W77: Yes
A78: 77 | B78: 154634443 | C78: Non Veg Pizzas | D78: Jamaican Jerk Pizza (10 Inch) | E78: 10 Inch | G78: variation | H78: 550 | I78: =H78+H78*(1/(1-0.22)-1) -> 705.12821 | K78: =if(J78<>"",J78-J78*20%,"") | L78: non-veg | R78: 1 | S78: 0 | T78: Yes | W78: Yes
A79: 78 | B79: 154634444 | C79: Non Veg Pizzas | D79: Jamaican Jerk Pizza (12 Inch) | E79: 12 Inch | G79: variation | H79: 750 | I79: =H79+H79*(1/(1-0.22)-1) -> 961.53846 | K79: =if(J79<>"",J79-J79*20%,"") | L79: non-veg | R79: 1 | S79: 0 | T79: Yes | W79: Yes
A80: 79 | B80: 154634389 | C80: Non Veg Pizzas | D80: Lebanese Chicken Pizza | G80: item | H80: 0 | I80: =H80+H80*(1/(1-0.22)-1) -> 0 | L80: non-veg | M80: ~48 | R80: 1 | S80: 0 | T80: Yes | W80: Yes
A81: 80 | B81: 154634445 | C81: Non Veg Pizzas | D81: Lebanese Chicken Pizza (8 Inch) | E81: 8 Inch | G81: variation | H81: 450 | I81: =H81+H81*(1/(1-0.22)-1) -> 576.92308 | K81: =if(J81<>"",J81-J81*20%,"") | L81: non-veg | R81: 1 | S81: 0 | T81: Yes | W81: Yes
A82: 81 | B82: 154634446 | C82: Non Veg Pizzas | D82: Lebanese Chicken Pizza (10 Inch) | E82: 10 Inch | G82: variation | H82: 575 | I82: =H82+H82*(1/(1-0.22)-1) -> 737.17949 | K82: =if(J82<>"",J82-J82*20%,"") | L82: non-veg | R82: 1 | S82: 0 | T82: Yes | W82: Yes
A83: 82 | B83: 154634447 | C83: Non Veg Pizzas | D83: Lebanese Chicken Pizza (12 Inch) | E83: 12 Inch | G83: variation | H83: 750 | I83: =H83+H83*(1/(1-0.22)-1) -> 961.53846 | K83: =if(J83<>"",J83-J83*20%,"") | L83: non-veg | R83: 1 | S83: 0 | T83: Yes | W83: Yes
A84: 83 | B84: 154634390 | C84: Non Veg Pizzas | D84: Diavola | G84: item | H84: 0 | I84: =H84+H84*(1/(1-0.22)-1) -> 0 | L84: non-veg | M84: ~49 | R84: 1 | S84: 0 | T84: Yes | W84: Yes
A85: 84 | B85: 154634448 | C85: Non Veg Pizzas | D85: Diavola (8 Inch) | E85: 8 Inch | G85: variation | H85: 475 | I85: =H85+H85*(1/(1-0.22)-1) -> 608.97436 | K85: =if(J85<>"",J85-J85*20%,"") | L85: non-veg | R85: 1 | S85: 0 | T85: Yes | W85: Yes
A86: 85 | B86: 154634449 | C86: Non Veg Pizzas | D86: Diavola (10 Inch) | E86: 10 Inch | G86: variation | H86: 600 | I86: =H86+H86*(1/(1-0.22)-1) -> 769.23077 | K86: =if(J86<>"",J86-J86*20%,"") | L86: non-veg | R86: 1 | S86: 0 | T86: Yes | W86: Yes
A87: 86 | B87: 154634450 | C87: Non Veg Pizzas | D87: Diavola (12 Inch) | E87: 12 Inch | G87: variation | H87: 750 | I87: =H87+H87*(1/(1-0.22)-1) -> 961.53846 | K87: =if(J87<>"",J87-J87*20%,"") | L87: non-veg | R87: 1 | S87: 0 | T87: Yes | W87: Yes
A88: 87 | B88: 154634391 | C88: Non Veg Pizzas | D88: Chicken Tikka Pizza | G88: item | H88: 0 | I88: =H88+H88*(1/(1-0.22)-1) -> 0 | L88: non-veg | M88: ~50 | R88: 1 | S88: 0 | T88: Yes | W88: Yes
A89: 88 | B89: 154634451 | C89: Non Veg Pizzas | D89: Chicken Tikka Pizza (8 Inch) | E89: 8 Inch | G89: variation | H89: 450 | I89: =H89+H89*(1/(1-0.22)-1) -> 576.92308 | K89: =if(J89<>"",J89-J89*20%,"") | L89: non-veg | R89: 1 | S89: 0 | T89: Yes | W89: Yes
A90: 89 | B90: 154634452 | C90: Non Veg Pizzas | D90: Chicken Tikka Pizza (10 Inch) | E90: 10 Inch | G90: variation | H90: 600 | I90: =H90+H90*(1/(1-0.22)-1) -> 769.23077 | K90: =if(J90<>"",J90-J90*20%,"") | L90: non-veg | R90: 1 | S90: 0 | T90: Yes | W90: Yes
A91: 90 | B91: 154634453 | C91: Non Veg Pizzas | D91: Chicken Tikka Pizza (12 Inch) | E91: 12 Inch | G91: variation | H91: 750 | I91: =H91+H91*(1/(1-0.22)-1) -> 961.53846 | K91: =if(J91<>"",J91-J91*20%,"") | L91: non-veg | R91: 1 | S91: 0 | T91: Yes | W91: Yes
A92: 91 | B92: 154634392 | C92: Non Veg Pizzas | D92: Signature Bolognese Pizza | G92: item | H92: 0 | I92: =H92+H92*(1/(1-0.22)-1) -> 0 | L92: non-veg | M92: ~51 | R92: 1 | S92: 0 | T92: Yes | W92: Yes
A93: 92 | B93: 154634454 | C93: Non Veg Pizzas | D93: Signature Bolognese Pizza (8 Inch) | E93: 8 Inch | G93: variation | H93: 490 | I93: =H93+H93*(1/(1-0.22)-1) -> 628.20513 | K93: =if(J93<>"",J93-J93*20%,"") | L93: non-veg | R93: 1 | S93: 0 | T93: Yes | W93: Yes
A94: 93 | B94: 154634455 | C94: Non Veg Pizzas | D94: Signature Bolognese Pizza (10 Inch) | E94: 10 Inch | G94: variation | H94: 650 | I94: =H94+H94*(1/(1-0.22)-1) -> 833.33333 | K94: =if(J94<>"",J94-J94*20%,"") | L94: non-veg | R94: 1 | S94: 0 | T94: Yes | W94: Yes
A95: 94 | B95: 154634456 | C95: Non Veg Pizzas | D95: Signature Bolognese Pizza (12 Inch) | E95: 12 Inch | G95: variation | H95: 825 | I95: =H95+H95*(1/(1-0.22)-1) -> 1057.6923 | K95: =if(J95<>"",J95-J95*20%,"") | L95: non-veg | R95: 1 | S95: 0 | T95: Yes | W95: Yes
A96: 95 | B96: 154634393 | C96: Non Veg Pizzas | D96: Turkish Meat Pizza | G96: item | H96: 0 | I96: =H96+H96*(1/(1-0.22)-1) -> 0 | L96: non-veg | M96: ~52 | R96: 1 | S96: 0 | T96: Yes | W96: Yes
A97: 96 | B97: 154634457 | C97: Non Veg Pizzas | D97: Turkish Meat Pizza (8 Inch) | E97: 8 Inch | G97: variation | H97: 490 | I97: =H97+H97*(1/(1-0.22)-1) -> 628.20513 | K97: =if(J97<>"",J97-J97*20%,"") | L97: non-veg | R97: 1 | S97: 0 | T97: Yes | W97: Yes
A98: 97 | B98: 154634458 | C98: Non Veg Pizzas | D98: Turkish Meat Pizza (10 Inch) | E98: 10 Inch | G98: variation | H98: 650 | I98: =H98+H98*(1/(1-0.22)-1) -> 833.33333 | K98: =if(J98<>"",J98-J98*20%,"") | L98: non-veg | R98: 1 | S98: 0 | T98: Yes | W98: Yes
A99: 98 | B99: 154634459 | C99: Non Veg Pizzas | D99: Turkish Meat Pizza (12 Inch) | E99: 12 Inch | G99: variation | H99: 825 | I99: =H99+H99*(1/(1-0.22)-1) -> 1057.6923 | K99: =if(J99<>"",J99-J99*20%,"") | L99: non-veg | R99: 1 | S99: 0 | T99: Yes | W99: Yes
A100: 99 | B100: 154634394 | C100: Non Veg Pizzas | D100: Porchetta | G100: item | H100: 0 | I100: =H100+H100*(1/(1-0.22)-1) -> 0 | L100: non-veg | M100: ~53 | R100: 1 | S100: 0 | T100: Yes | W100: Yes
A101: 100 | B101: 154634460 | C101: Non Veg Pizzas | D101: Porchetta (8 Inch) | E101: 8 Inch | G101: variation | H101: 550 | I101: =H101+H101*(1/(1-0.22)-1) -> 705.12821 | K101: =if(J101<>"",J101-J101*20%,"") | L101: non-veg | R101: 1 | S101: 0 | T101: Yes | W101: Yes
A102: 101 | B102: 154634461 | C102: Non Veg Pizzas | D102: Porchetta (10 Inch) | E102: 10 Inch | G102: variation | H102: 675 | I102: =H102+H102*(1/(1-0.22)-1) -> 865.38462 | K102: =if(J102<>"",J102-J102*20%,"") | L102: non-veg | R102: 1 | S102: 0 | T102: Yes | W102: Yes
A103: 102 | B103: 154634462 | C103: Non Veg Pizzas | D103: Porchetta (12 Inch) | E103: 12 Inch | G103: variation | H103: 875 | I103: =H103+H103*(1/(1-0.22)-1) -> 1121.7949 | K103: =if(J103<>"",J103-J103*20%,"") | L103: non-veg | R103: 1 | S103: 0 | T103: Yes | W103: Yes
A104: 103 | B104: 154634395 | C104: Non Veg Pizzas | D104: Classic Pork | G104: item | H104: 0 | I104: =H104+H104*(1/(1-0.22)-1) -> 0 | L104: non-veg | M104: ~54 | R104: 1 | S104: 0 | T104: Yes | W104: Yes
A105: 104 | B105: 154634463 | C105: Non Veg Pizzas | D105: Classic Pork (8 Inch) | E105: 8 Inch | G105: variation | H105: 550 | I105: =H105+H105*(1/(1-0.22)-1) -> 705.12821 | K105: =if(J105<>"",J105-J105*20%,"") | L105: non-veg | R105: 1 | S105: 0 | T105: Yes | W105: Yes
A106: 105 | B106: 154634464 | C106: Non Veg Pizzas | D106: Classic Pork (10 Inch) | E106: 10 Inch | G106: variation | H106: 675 | I106: =H106+H106*(1/(1-0.22)-1) -> 865.38462 | K106: =if(J106<>"",J106-J106*20%,"") | L106: non-veg | R106: 1 | S106: 0 | T106: Yes | W106: Yes
A107: 106 | B107: 154634465 | C107: Non Veg Pizzas | D107: Classic Pork (12 Inch) | E107: 12 Inch | G107: variation | H107: 875 | I107: =H107+H107*(1/(1-0.22)-1) -> 1121.7949 | K107: =if(J107<>"",J107-J107*20%,"") | L107: non-veg | R107: 1 | S107: 0 | T107: Yes | W107: Yes
A108: 107 | B108: 154634396 | C108: Non Veg Pizzas | D108: Chef Special Pizza | G108: item | H108: 0 | I108: =H108+H108*(1/(1-0.22)-1) -> 0 | L108: non-veg | M108: ~55 | R108: 1 | S108: 0 | T108: Yes | W108: Yes
A109: 108 | B109: 154634466 | C109: Non Veg Pizzas | D109: Chef Special Pizza (8 Inch) | E109: 8 Inch | G109: variation | H109: 575 | I109: =H109+H109*(1/(1-0.22)-1) -> 737.17949 | J109: 600 | K109: =if(J109<>"",J109-J109*20%,"") -> 480 | L109: non-veg | R109: 1 | S109: 0 | T109: Yes | W109: Yes
A110: 109 | B110: 154634467 | C110: Non Veg Pizzas | D110: Chef Special Pizza (10 Inch) | E110: 10 Inch | G110: variation | H110: 675 | I110: =H110+H110*(1/(1-0.22)-1) -> 865.38462 | J110: 800 | K110: =if(J110<>"",J110-J110*20%,"") -> 640 | L110: non-veg | R110: 1 | S110: 0 | T110: Yes | W110: Yes
A111: 110 | B111: 154634468 | C111: Non Veg Pizzas | D111: Chef Special Pizza (12 Inch) | E111: 12 Inch | G111: variation | H111: 875 | I111: =H111+H111*(1/(1-0.22)-1) -> 1121.7949 | J111: 950 | K111: =if(J111<>"",J111-J111*20%,"") -> 760 | L111: non-veg | R111: 1 | S111: 0 | T111: Yes | W111: Yes
A112: 111 | B112: 154634397 | C112: Non Veg Pizzas | D112: Gamberetti | G112: item | H112: 0 | I112: =H112+H112*(1/(1-0.22)-1) -> 0 | L112: veg | M112: ~56 | R112: 1 | S112: 0 | T112: Yes | W112: Yes
A113: 112 | B113: 154634469 | C113: Non Veg Pizzas | D113: Gamberetti (8 Inch) | E113: 8 Inch | G113: variation | H113: 575 | I113: =H113+H113*(1/(1-0.22)-1) -> 737.17949 | K113: =if(J113<>"",J113-J113*20%,"") | L113: veg | R113: 1 | S113: 0 | T113: Yes | W113: Yes
A114: 113 | B114: 154634470 | C114: Non Veg Pizzas | D114: Gamberetti (10 Inch) | E114: 10 Inch | G114: variation | H114: 675 | I114: =H114+H114*(1/(1-0.22)-1) -> 865.38462 | K114: =if(J114<>"",J114-J114*20%,"") | L114: veg | R114: 1 | S114: 0 | T114: Yes | W114: Yes
A115: 114 | B115: 154634471 | C115: Non Veg Pizzas | D115: Gamberetti (12 Inch) | E115: 12 Inch | G115: variation | H115: 875 | I115: =H115+H115*(1/(1-0.22)-1) -> 1121.7949 | K115: =if(J115<>"",J115-J115*20%,"") | L115: veg | R115: 1 | S115: 0 | T115: Yes | W115: Yes
A116: 115 | B116: 154634398 | C116: Non Veg Pizzas | D116: Meat Lovers Pizza | G116: item | H116: 0 | I116: =H116+H116*(1/(1-0.22)-1) -> 0 | L116: non-veg | M116: ~57 | R116: 1 | S116: 0 | T116: Yes | W116: Yes
A117: 116 | B117: 154634472 | C117: Non Veg Pizzas | D117: Meat Lovers Pizza (8 Inch) | E117: 8 Inch | G117: variation | H117: 700 | I117: =H117+H117*(1/(1-0.22)-1) -> 897.4359 | K117: =if(J117<>"",J117-J117*20%,"") | L117: non-veg | R117: 1 | S117: 0 | T117: Yes | W117: Yes
A118: 117 | B118: 154634473 | C118: Non Veg Pizzas | D118: Meat Lovers Pizza (10 Inch) | E118: 10 Inch | G118: variation | H118: 900 | I118: =H118+H118*(1/(1-0.22)-1) -> 1153.8462 | K118: =if(J118<>"",J118-J118*20%,"") | L118: non-veg | R118: 1 | S118: 0 | T118: Yes | W118: Yes
A119: 118 | B119: 154634474 | C119: Non Veg Pizzas | D119: Meat Lovers Pizza (12 Inch) | E119: 12 Inch | G119: variation | H119: 1250 | I119: =H119+H119*(1/(1-0.22)-1) -> 1602.5641 | K119: =if(J119<>"",J119-J119*20%,"") | L119: non-veg | R119: 1 | S119: 0 | T119: Yes | W119: Yes
A120: 119 | B120: 154634399 | C120: Non Veg Pizzas | D120: Make Your Own Pizza | G120: item | H120: 1200 | I120: =H120+H120*(1/(1-0.22)-1) -> 1538.4615 | K120: =if(J120<>"",J120-J120*20%,"") | L120: veg | M120: ~58 | R120: 1 | S120: 0 | T120: Yes | W120: Yes
...

Sheet Swiggy Order Summary
A4: PaymentID | B4: Start Date | C4: End Date | D4: No. of Orders | E4: Total Sales | F4: Sw_Order | G4: Sw_Total | H4: Sw_ServiceFee | I4: Sw_Other | J4: Sw_TCS | K4: SW_Payable | L4: SW_Differnce | M4: ActualDifference | N4: Swiggy%
A5: APR16 | B5: 45753 | C5: 45760 | D5: =COUNTIFS(SwiggyOrders[Order Delivery Time],">="&DATEVALUE(B5),SwiggyOrders[Order Delivery Time],"<="&DATEVALUE(C5)) -> 7 | E5: =SUMIFS(SwiggyOrders[Total Bill Amount],SwiggyOrders[Order Delivery Time],">="&DATEVALUE(B5),SwiggyOrders[Order Delivery Time],"<="&DATEVALUE(C5)) -> 6872 | F5: 7 | G5: 6872.28 | H5: 973.15 | I5: 1506.25 | J5: 6.55 | K5: 4386.32 | L5: =G5-K5 -> 2485.96 | M5: =E5-K5 -> 2485.68 | N5: =L5/G5 -> 0.3617373
A6: APR23 | B6: 45760 | C6: 45767 | D6: =COUNTIFS(SwiggyOrders[Order Delivery Time],">="&DATEVALUE(B6),SwiggyOrders[Order Delivery Time],"<="&DATEVALUE(C6)) -> 15 | E6: =SUMIFS(SwiggyOrders[Total Bill Amount],SwiggyOrders[Order Delivery Time],">="&DATEVALUE(B6),SwiggyOrders[Order Delivery Time],"<="&DATEVALUE(C6)) -> 13706 | F6: 16 | G6: 13818.11 | H6: 1956.61 | I6: 658 | J6: 13.6 | K6: 11190.28 | L6: =G6-K6 -> 2627.83 | M6: =E6-K6 -> 2515.72 | N6: =L6/G6 -> 0.1901729
A7: APR30 | B7: 45828 | C7: 45835 | D7: =COUNTIFS(SwiggyOrders[Order Delivery Time],">="&DATEVALUE(B7),SwiggyOrders[Order Delivery Time],"<="&DATEVALUE(C7)) -> 45 | E7: =SUMIFS(SwiggyOrders[Total Bill Amount],SwiggyOrders[Order Delivery Time],">="&DATEVALUE(B7),SwiggyOrders[Order Delivery Time],"<="&DATEVALUE(C7)) -> 52771 | F7: 53 | G7: 49381.8 | H7: 6992.35 | I7: 2620.5 | J7: 47.03 | K7: 39721.55 | L7: =G7-K7 -> 9660.25 | M7: =E7-K7 -> 13049.45 | N7: =L7/G7 -> 0.19562369
A8: MAY5 | B8: 45774 | C8: 45777 | D8: =COUNTIFS(SwiggyOrders[Order Delivery Time],">="&DATEVALUE(B8),SwiggyOrders[Order Delivery Time],"<="&DATEVALUE(C8)) -> 10 | E8: =SUMIFS(SwiggyOrders[Total Bill Amount],SwiggyOrders[Order Delivery Time],">="&DATEVALUE(B8),SwiggyOrders[Order Delivery Time],"<="&DATEVALUE(C8)) -> 11511 | F8: 18 | G8: 18711.1 | H8: 2649.41 | I8: 891 | J8: 17.82 | K8: 15152.76 | L8: =G8-K8 -> 3558.34 | M8: =E8-K8 -> -3641.76 | N8: =L8/G8 -> 0.19017268
A9: MAY7 | B9: =C8+1 -> 45778 | C9: 45780 | D9: =COUNTIFS(SwiggyOrders[Order Delivery Time],">="&DATEVALUE(B9),SwiggyOrders[Order Delivery Time],"<="&DATEVALUE(C9)) -> 9 | E9: =SUMIFS(SwiggyOrders[Total Bill Amount],SwiggyOrders[Order Delivery Time],">="&DATEVALUE(B9),SwiggyOrders[Order Delivery Time],"<="&DATEVALUE(C9)) -> 10183 | F9: 15 | G9: 13810.73 | H9: 1955.58 | I9: 1355.65 | J9: 13.15 | K9: 10486.25 | L9: =G9-K9 -> 3324.48 | M9: =E9-K9 -> -303.25 | N9: =L9/G9 -> 0.24071718
A10: MAY14 | B10: =C9+1 -> 45781 | C10: =B10+6 -> 45787 | D10: =COUNTIFS(SwiggyOrders[Order Delivery Time],">="&DATEVALUE(B10),SwiggyOrders[Order Delivery Time],"<="&DATEVALUE(C10)) -> 21 | E10: =SUMIFS(SwiggyOrders[Total Bill Amount],SwiggyOrders[Order Delivery Time],">="&DATEVALUE(B10),SwiggyOrders[Order Delivery Time],"<="&DATEVALUE(C10)) -> 19022 | F10: 24 | G10: 17763.48 | H10: 2522.44 | I10: 845.88 | J10: 16.92 | K10: 14375.22 | L10: =G10-K10 -> 3388.26 | M10: =E10-K10 -> 4646.78 | N10: =L10/G10 -> 0.19074303
A11: MAY21 | B11: =C10+1 -> 45788 | C11: =B11+6 -> 45794 | D11: =COUNTIFS(SwiggyOrders[Order Delivery Time],">="&DATEVALUE(B11),SwiggyOrders[Order Delivery Time],"<="&DATEVALUE(C11)) -> 21 | E11: =SUMIFS(SwiggyOrders[Total Bill Amount],SwiggyOrders[Order Delivery Time],">="&DATEVALUE(B11),SwiggyOrders[Order Delivery Time],"<="&DATEVALUE(C11)) -> 17968 | F11: 24 | G11: 19826.22 | H11: 29 | I11: 1646.1 | J11: 17.71 | K11: 15528.99 | L11: =G11-K11 -> 4297.23 | M11: =E11-K11 -> 2439.01 | N11: =L11/G11 -> 0.2167448
A12: MAY28 | B12: =C11+1 -> 45795 | C12: =B12+6 -> 45801 | D12: =COUNTIFS(SwiggyOrders[Order Delivery Time],">="&DATEVALUE(B12),SwiggyOrders[Order Delivery Time],"<="&DATEVALUE(C12)) -> 21 | E12: =SUMIFS(SwiggyOrders[Total Bill Amount],SwiggyOrders[Order Delivery Time],">="&DATEVALUE(B12),SwiggyOrders[Order Delivery Time],"<="&DATEVALUE(C12)) -> 15230 | G12: 20599 | H12: 2916.74 | I12: 1100.9 | J12: 19.62 | K12: 16561.62 | L12: =G12-K12 -> 4037.38 | M12: =E12-K12 -> -1331.62 | N12: =L12/G12 -> 0.19599883
A13: JUN4 | B13: =C12+1 -> 45802 | C13: =B13+6 -> 45808 | D13: =COUNTIFS(SwiggyOrders[Order Delivery Time],">="&DATEVALUE(B13),SwiggyOrders[Order Delivery Time],"<="&DATEVALUE(C13)) -> 26 | E13: =SUMIFS(SwiggyOrders[Total Bill Amount],SwiggyOrders[Order Delivery Time],">="&DATEVALUE(B13),SwiggyOrders[Order Delivery Time],"<="&DATEVALUE(C13)) -> 26045 | F13: 34 | G13: 30568.8 | H13: 4328.51 | I13: 1455.65 | J13: 29.11 | K13: 24755.42 | L13: =G13-K13 -> 5813.38 | M13: =E13-K13 -> 1289.58 | N13: =L13/G13 -> 0.19017364
A14: JUN11 | B14: =C13+1 -> 45809 | C14: =B14+6 -> 45815 | D14: =COUNTIFS(SwiggyOrders[Order Delivery Time],">="&DATEVALUE(B14),SwiggyOrders[Order Delivery Time],"<="&DATEVALUE(C14)) -> 32 | E14: =SUMIFS(SwiggyOrders[Total Bill Amount],SwiggyOrders[Order Delivery Time],">="&DATEVALUE(B14),SwiggyOrders[Order Delivery Time],"<="&DATEVALUE(C14)) -> 27518 | F14: 42 | G14: 35786.6 | H14: 5067.38 | I14: 5244.12 | J14: 34.08 | K14: 25440.8 | L14: =G14-K14 -> 10345.8 | M14: =E14-K14 -> 2077.2 | N14: =L14/G14 -> 0.28909704
A15: JUN18 | B15: =C14+1 -> 45816 | C15: =B15+6 -> 45822 | D15: =COUNTIFS(SwiggyOrders[Order Delivery Time],">="&DATEVALUE(B15),SwiggyOrders[Order Delivery Time],"<="&DATEVALUE(C15)) -> 36 | E15: =SUMIFS(SwiggyOrders[Total Bill Amount],SwiggyOrders[Order Delivery Time],">="&DATEVALUE(B15),SwiggyOrders[Order Delivery Time],"<="&DATEVALUE(C15)) -> 32893 | F15: 42 | G15: 35084.41 | H15: 4967.94 | I15: 5210.68 | J15: 33.41 | K15: 24872.2 | L15: =G15-K15 -> 10212.21 | M15: =E15-K15 -> 8020.8 | N15: =L15/G15 -> 0.29107544
A16: JUN25 | B16: 45830 | C16: 45838 | D16: =COUNTIFS(SwiggyOrders[Order Delivery Time],">="&DATEVALUE(B16),SwiggyOrders[Order Delivery Time],"<="&DATEVALUE(C16)) -> 47 | E16: =SUMIFS(SwiggyOrders[Total Bill Amount],SwiggyOrders[Order Delivery Time],">="&DATEVALUE(B16),SwiggyOrders[Order Delivery Time],"<="&DATEVALUE(C16)) -> 55945 | F16: 34 | G16: 35177.74 | H16: 4981.2 | I16: 5215.12 | J16: 33.5 | K16: 24947.72 | L16: =G16-K16 -> 10230.02 | M16: =E16-K16 -> 30997.28 | N16: =L16/G16 -> 0.29080947
A17: JUL4 | B17: =C16+1 -> 45839 | C17: =B17+6 -> 45845 | D17: =COUNTIFS(SwiggyOrders[Order Delivery Time],">="&DATEVALUE(B17),SwiggyOrders[Order Delivery Time],"<="&DATEVALUE(C17)) -> 75 | E17: =SUMIFS(SwiggyOrders[Total Bill Amount],SwiggyOrders[Order Delivery Time],">="&DATEVALUE(B17),SwiggyOrders[Order Delivery Time],"<="&DATEVALUE(C17)) -> 80771 | F17: 57 | G17: 61543.62 | H17: 8714.56 | I17: 6470.64 | J17: 58.61 | K17: 46299.56 | L17: =G17-K17 -> 15244.06 | M17: =E17-K17 -> 34471.44 | N17: =L17/G17 -> 0.24769521
A18: JUL9 | B18: =C17+1 -> 45846 | C18: =B18+6 -> 45852 | D18: =COUNTIFS(SwiggyOrders[Order Delivery Time],">="&DATEVALUE(B18),SwiggyOrders[Order Delivery Time],"<="&DATEVALUE(C18)) -> 49 | E18: =SUMIFS(SwiggyOrders[Total Bill Amount],SwiggyOrders[Order Delivery Time],">="&DATEVALUE(B18),SwiggyOrders[Order Delivery Time],"<="&DATEVALUE(C18)) -> 56858 | F18: 57 | G18: 61543.62 | H18: 8714.56 | I18: 6470.64 | J18: 58.61 | K18: 46299.56 | L18: =G18-K18 -> 15244.06 | M18: =E18-K18 -> 10558.44 | N18: =L18/G18 -> 0.24769521
A19: JUL17 | B19: =C18+1 -> 45853 | C19: =B19+6 -> 45859 | D19: =COUNTIFS(SwiggyOrders[Order Delivery Time],">="&DATEVALUE(B19),SwiggyOrders[Order Delivery Time],"<="&DATEVALUE(C19)) -> 0 | E19: =SUMIFS(SwiggyOrders[Total Bill Amount],SwiggyOrders[Order Delivery Time],">="&DATEVALUE(B19),SwiggyOrders[Order Delivery Time],"<="&DATEVALUE(C19)) -> 0 | F19: 57 | G19: 61543.62 | H19: 8714.56 | I19: 6470.64 | J19: 58.61 | K19: 46299.56 | L19: =G19-K19 -> 15244.06 | M19: =E19-K19 -> -46299.56 | N19: =L19/G19 -> 0.24769521

Sheet PL
B2: Philos Delicacy, Kakkanad | H2: 45945 | I2: =H2-TODAY() -> -253
B3: P/L Report
B4: Income | C4: =sum(D5:D7) -> 10753785
C5: Petpooja | D5: =sum(Business[Petpooja]) -> 8457809.2
C6: Swiggy | D6: =sum(Business[Swiggy]) -> 2194226
C7: Direct | D7: =sum(Business[Paper Bill]) -> 101750
B8: Expenses | C8: =sum(D9:D12) -> 9829504.2 | F8: =C8/C4 -> 0.91405064 | H8: Sprite | I8: French Fries | J8: Pizza | K8: Combo Price
C9: Paid Bills | D9: =sumif(Purchase_Register[Paid?], True, Purchase_Register[Amount]) -> 9121117.2 | H9: 20 | I9: 130 | J9: 475 | K9: 499 | L9: 8"
C10: Unpaid Bills | D10: =sumif(Purchase_Register[Paid?], False, Purchase_Register[Amount]) -> 15255 | H10: 12 | I10: 50 | J10: 200 | K10: 262
C11: Loan Repay (Sumit) | D11: 350000
C12: Petty Cash | D12: 343132
B13: Balance | C13: =C4-C8 -> 924280.9 | H13: 40 | I13: 130 | J13: 475 | K13: 499 | L13: 8"
H14: 12 | I14: 50 | J14: 200 | K14: 262
C15: Initial Investment | D15: Yrly Interest (8%) | E15: Mnthly Interest
C16: 3583602 | D16: =C16*0.08 -> 286688.16 | E16: =D16/12 -> 23890.68

Sheet Masters
A1: Vendors | B1: Category
A2: T3 SPECIALITY
A3: MATHA MEATS
A4: GREENZ VEGGIES | F4: Sendry Creditors
A5: POLAR ICE CUBES | F5: Sendry Debtors
A6: HOST VYTILA | F6: Raw Materias
A7: ARACKAL BHARATH GAS | F7: Direct Expenses
A8: TRIO MEATS KTM
A9: DIAMOND
A10: GROW GREENS
A11: UNITED TRADERS KTM
A12: LERA COCA COLA
A13: RIGHT SOLUTION PAPER TISSUE
A14: PETPOOJA
A15: ANGADI SUPERMARKET
A16: WATER SUPPLY
A17: ROYAL KTM
A18: AMAZON
A19: ZEPTO
... A80: CM MARGINE FREE

Sheet Monthly Expenditure Report
F44: Profit/Loss
F45: =E45-B39-C39 -> 855604.95
F46: =E46-D39 -> 763843.55
F47: =E47-E39 -> 898091.1
F48: =E48-F39 -> 1515309.6 | H48: YES Bank | I48: 239408 | K48: Ben | L48: 55000
F49: =E49-F40 -> 1685322.9 | H49: FDRL Bank | I49: 21283 | K49: Philo | L49: 20000
F50: =SUM(F46:F49) -> 4862567.1 | K50: School Fee | L50: 37000
K51: Tithe | L51: 50000
K52: Deopsit (Leena) | L52: 10500
F53: =F49-L53 -> 1342190.9 | K53: Petty Cash | L53: =PL!D12 -> 343132

Sheet Savings
A1: Date | B1: Saved amount | C1: Running Total
A2: 45832 | B2: 4000 | C2: =B2 -> 4000
A3: =A2+1 -> 45833 | B3: =B2 -> 4000 | C3: =C2+B3 -> 8000
A4: 45833 | B4: =B3 -> 4000 | C4: =C3+B4 -> 12000
A5: =A4+1 -> 45834 | B5: =B4 -> 4000 | C5: =C4+B5 -> 16000
A6: 45834 | B6: =B5 -> 4000 | C6: =C5+B6 -> 20000
A7: =A6+1 -> 45835 | B7: =B6 -> 4000 | C7: =C6+B7 -> 24000
A8: 45835 | B8: =B7 -> 4000 | C8: =C7+B8 -> 28000
A9: =A8+1 -> 45836 | B9: =B8 -> 4000 | C9: =C8+B9 -> 32000
A10: 45836 | B10: =B9 -> 4000 | C10: =C9+B10 -> 36000
A11: =A10+1 -> 45837 | B11: =B10 -> 4000 | C11: =C10+B11 -> 40000
A12: 45837 | B12: =B11 -> 4000 | C12: =C11+B12 -> 44000
A13: =A12+1 -> 45838 | B13: =B12 -> 4000 | C13: =C12+B13 -> 48000
A14: 45838 | B14: =B13 -> 4000 | C14: =C13+B14 -> 52000
A15: =A14+1 -> 45839 | B15: =B14 -> 4000 | C15: =C14+B15 -> 56000
A16: 45839 | B16: =B15 -> 4000 | C16: =C15+B16 -> 60000
A17: =A16+1 -> 45840 | B17: =B16 -> 4000 | C17: =C16+B17 -> 64000
A18: 45840 | B18: =B17 -> 4000 | C18: =C17+B18 -> 68000
A19: =A18+1 -> 45841 | B19: =B18 -> 4000 | C19: =C18+B19 -> 72000
A20: 45841 | B20: =B19 -> 4000 | C20: =C19+B20 -> 76000
A21: =A20+1 -> 45842 | B21: =B20 -> 4000 | C21: =C20+B21 -> 80000
A22: 45842 | B22: =B21 -> 4000 | C22: =C21+B22 -> 84000
A23: =A22+1 -> 45843 | B23: =B22 -> 4000 | C23: =C22+B23 -> 88000
A24: 45843 | B24: =B23 -> 4000 | C24: =C23+B24 -> 92000
A25: =A24+1 -> 45844 | B25: =B24 -> 4000 | C25: =C24+B25 -> 96000
A26: 45844 | B26: =B25 -> 4000 | C26: =C25+B26 -> 100000
A27: =A26+1 -> 45845 | B27: =B26 -> 4000 | C27: =C26+B27 -> 104000
A28: 45845 | B28: =B27 -> 4000 | C28: =C27+B28 -> 108000
A29: =A28+1 -> 45846 | B29: =B28 -> 4000 | C29: =C28+B29 -> 112000
A30: 45846 | B30: =B29 -> 4000 | C30: =C29+B30 -> 116000
A31: =A30+1 -> 45847 | B31: =B30 -> 4000 | C31: =C30+B31 -> 120000
A32: 45847 | B32: =B31 -> 4000 | C32: =C31+B32 -> 124000
A33: =A32+1 -> 45848 | B33: =B32 -> 4000 | C33: =C32+B33 -> 128000
A34: 45848 | B34: =B33 -> 4000 | C34: =C33+B34 -> 132000
A35: =A34+1 -> 45849 | B35: =B34 -> 4000 | C35: =C34+B35 -> 136000
A36: 45849 | B36: =B35 -> 4000 | C36: =C35+B36 -> 140000
A37: =A36+1 -> 45850 | B37: =B36 -> 4000 | C37: =C36+B37 -> 144000
A38: 45850 | B38: =B37 -> 4000 | C38: =C37+B38 -> 148000
A39: =A38+1 -> 45851 | B39: =B38 -> 4000 | C39: =C38+B39 -> 152000
A40: 45851 | B40: =B39 -> 4000 | C40: =C39+B40 -> 156000
A41: =A40+1 -> 45852 | B41: =B40 -> 4000 | C41: =C40+B41 -> 160000
A42: 45852 | B42: =B41 -> 4000 | C42: =C41+B42 -> 164000
A43: =A42+1 -> 45853 | B43: =B42 -> 4000 | C43: =C42+B43 -> 168000
A44: 45853 | B44: =B43 -> 4000 | C44: =C43+B44 -> 172000
A45: =A44+1 -> 45854 | B45: =B44 -> 4000 | C45: =C44+B45 -> 176000
A46: 45854 | B46: =B45 -> 4000 | C46: =C45+B46 -> 180000
A47: =A46+1 -> 45855 | B47: =B46 -> 4000 | C47: =C46+B47 -> 184000
A48: 45855 | B48: =B47 -> 4000 | C48: =C47+B48 -> 188000
A49: =A48+1 -> 45856 | B49: =B48 -> 4000 | C49: =C48+B49 -> 192000
A50: 45856 | B50: =B49 -> 4000 | C50: =C49+B50 -> 196000
A51: =A50+1 -> 45857 | B51: =B50 -> 4000 | C51: =C50+B51 -> 200000
A52: 45857 | B52: =B51 -> 4000 | C52: =C51+B52 -> 204000
A53: =A52+1 -> 45858 | B53: =B52 -> 4000 | C53: =C52+B53 -> 208000
A54: 45858 | B54: =B53 -> 4000 | C54: =C53+B54 -> 212000
A55: =A54+1 -> 45859 | B55: =B54 -> 4000 | C55: =C54+B55 -> 216000
A56: 45859 | B56: =B55 -> 4000 | C56: =C55+B56 -> 220000
A57: =A56+1 -> 45860 | B57: =B56 -> 4000 | C57: =C56+B57 -> 224000
A58: 45860 | B58: =B57 -> 4000 | C58: =C57+B58 -> 228000
A59: =A58+1 -> 45861 | B59: =B58 -> 4000 | C59: =C58+B59 -> 232000
A60: 45861 | B60: =B59 -> 4000 | C60: =C59+B60 -> 236000
A61: =A60+1 -> 45862 | B61: =B60 -> 4000 | C61: =C60+B61 -> 240000
A62: 45862 | B62: =B61 -> 4000 | C62: =C61+B62 -> 244000
A63: =A62+1 -> 45863 | B63: =B62 -> 4000 | C63: =C62+B63 -> 248000
A64: 45863 | B64: =B63 -> 4000 | C64: =C63+B64 -> 252000
A65: =A64+1 -> 45864 | B65: =B64 -> 4000 | C65: =C64+B65 -> 256000
A66: 45864 | B66: =B65 -> 4000 | C66: =C65+B66 -> 260000
A67: =A66+1 -> 45865 | B67: =B66 -> 4000 | C67: =C66+B67 -> 264000
A68: 45865 | B68: =B67 -> 4000 | C68: =C67+B68 -> 268000
A69: =A68+1 -> 45866 | B69: =B68 -> 4000 | C69: =C68+B69 -> 272000
A70: 45866 | B70: =B69 -> 4000 | C70: =C69+B70 -> 276000
A71: =A70+1 -> 45867 | B71: =B70 -> 4000 | C71: =C70+B71 -> 280000
A72: 45867 | B72: =B71 -> 4000 | C72: =C71+B72 -> 284000
A73: =A72+1 -> 45868 | B73: =B72 -> 4000 | C73: =C72+B73 -> 288000
A74: 45868 | B74: =B73 -> 4000 | C74: =C73+B74 -> 292000
A75: =A74+1 -> 45869 | B75: =B74 -> 4000 | C75: =C74+B75 -> 296000
A76: 45869 | B76: =B75 -> 4000 | C76: =C75+B76 -> 300000
A77: =A76+1 -> 45870 | B77: =B76 -> 4000 | C77: =C76+B77 -> 304000
A78: 45870 | B78: =B77 -> 4000 | C78: =C77+B78 -> 308000
A79: =A78+1 -> 45871 | B79: =B78 -> 4000 | C79: =C78+B79 -> 312000
A80: 45871 | B80: =B79 -> 4000 | C80: =C79+B80 -> 316000
A81: =A80+1 -> 45872 | B81: =B80 -> 4000 | C81: =C80+B81 -> 320000
A82: 45872 | B82: =B81 -> 4000 | C82: =C81+B82 -> 324000
A83: =A82+1 -> 45873 | B83: =B82 -> 4000 | C83: =C82+B83 -> 328000
A84: 45873 | B84: =B83 -> 4000 | C84: =C83+B84 -> 332000
A85: =A84+1 -> 45874 | B85: =B84 -> 4000 | C85: =C84+B85 -> 336000
A86: 45874 | B86: =B85 -> 4000 | C86: =C85+B86 -> 340000
A87: =A86+1 -> 45875 | B87: =B86 -> 4000 | C87: =C86+B87 -> 344000
A88: 45875 | B88: =B87 -> 4000 | C88: =C87+B88 -> 348000
A89: =A88+1 -> 45876 | B89: =B88 -> 4000 | C89: =C88+B89 -> 352000
A90: 45876 | B90: =B89 -> 4000 | C90: =C89+B90 -> 356000
A91: =A90+1 -> 45877 | B91: =B90 -> 4000 | C91: =C90+B91 -> 360000
A92: 45877 | B92: =B91 -> 4000 | C92: =C91+B92 -> 364000
A93: =A92+1 -> 45878 | B93: =B92 -> 4000 | C93: =C92+B93 -> 368000
A94: 45878 | B94: =B93 -> 4000 | C94: =C93+B94 -> 372000
A95: =A94+1 -> 45879 | B95: =B94 -> 4000 | C95: =C94+B95 -> 376000
A96: 45879 | B96: =B95 -> 4000 | C96: =C95+B96 -> 380000
A97: =A96+1 -> 45880 | B97: =B96 -> 4000 | C97: =C96+B97 -> 384000
A98: 45880 | B98: =B97 -> 4000 | C98: =C97+B98 -> 388000
A99: =A98+1 -> 45881 | B99: =B98 -> 4000 | C99: =C98+B99 -> 392000
A100: 45881 | B100: =B99 -> 4000 | C100: =C99+B100 -> 396000
...

Sheet Sheet3
A1: AL SHAH ENTERPRISES | B1: Utensils
A2: Angadi supermarket | B2: lemon | H2: 99 | I2: 45762 | J2: Greenz Veggies | K2: tomato | L2: 1660 | M2: FALSE | P2: 5
A3: Bestocare Traders | B3: Tuna | H3: 154 | I3: 45762 | J3: Greenz Veggies | K3: veggies | L3: 1660 | M3: FALSE | P3: 5
A4: Diamond | B4: Floor cleaner | H4: 04-Apr | I4: 157 | J4: 45764 | K4: Greenz Veggies | L4: veggies | M4: 1538 | N4: FALSE | Q4: 5
A5: Diamond | B5: juice shaker
A6: Diamond | B6: skillet, ice bucket
A7: Diamond | B7: wrap paper
A8: EandE agencies | B8: soda
A9: Glow Green | B9: Sunflower
A10: Greenz Veggies | B10: brocoli
A11: Greenz Veggies | B11: tomato
A12: Greenz Veggies | B12: veggies
A13: Grow greens | B13: micro greens
A14: Grow greens | B14: Sunflower
A15: Hygiene fresh | B15: cap
A16: LERA | B16: soda,sprite
... A60: United traders Kottayam | B60: wheet flour

Sheet Sheet4
A2: Vendors | B2: Category | E2: 10.52 | F2: 1400
A3: T3 Speciality | B3: Meat & Seafood | E3: 3.46 | F3: =F2/E2 -> 133.07985
A4: Matha meats | B4: Meat & Seafood | F4: =F2/E3 -> 404.62428
A5: Greenz Veggies | B5: Vegetables | F5: 0.11
A6: Polar Ice Cubes | B6: Beverages & Ice | F6: =F4*F5 -> 44.508671 | G6: 700 | H6: =sum(F6:F11) -> 253.59958 | I6: =F6 -> 44.508671 | K6: 26320
A7: Green valley water | B7: Beverages & Ice | E7: 490 | F7: =E7/5.5 -> 89.090909 | H7: =H6/G6 -> 0.36228511 | I7: =E7/6 -> 81.666667 | K7: 32
A8: STAFF SALARY | B8: Salaries | F8: 15 | H8: =sum(I6:I11) -> 206.17534 | I8: 15 | K8: =K6/K7 -> 822.5
A9: CAREVELLO (PIZZA BOX) | B9: Other | E9: 437.5 | F9: 15 | H9: =H8/G6 -> 0.2945362 | I9: 15
A10: Trio meats Kottayam | B10: Meat & Seafood | E10: =0.12 -> 0.12 | F10: 70 | I10: 40
A11: Chicken Factory | B11: Meat & Seafood | E11: =E9*E10 -> 52.5 | F11: 20 | I11: 10
A12: Best Fish | B12: Meat & Seafood
A13: Fruits and Vegetables | B13: Vegetables
A14: Elite foods | B14: Other
A15: Bismi water | B15: Beverages & Ice
A16: Royal Bakers | B16: Other
A17: Chungath Poultry Mart | B17: Meat & Seafood
A18: Haritha Vegetables | B18: Vegetables
A19: Thejaswi fish stall | B19: Meat & Seafood
A20: Cochin Frozen Foods | B20: Meat & Seafood
A21: Nandanam Vegetables | B21: Vegetables
A22: Apsara Ice Cream | B22: Beverages & Ice
A23: C.A.Poultry Farm | B23: Meat & Seafood
... A38: Sowparnika | B38: Other

Sheet Pizza Costing
B1: BBQ | C1: Chef Spl | D1: Porchetta | E1: Classic Pork | F1: Chef Spl (8")
A2: Chicken | C2: 45 | D2: 0 | E2: 0 | F2: =55*N3 -> 22.22 | L2: Cheese | M2: 490 | N2: =M2/1000 -> 0.49
A3: Beef | C3: 35 | D3: 0 | E3: 0 | F3: =180*N6 -> 18 | L3: Chicken | M3: 404 | N3: =M3/1000 -> 0.404
A4: Pork | C4: 0 | D4: 127 | E4: 127 | F4: 0 | L4: C. Pepperoni | M4: 633 | N4: =M4/1000 -> 0.633
A5: Pepperoni | C5: 20 | D5: 0 | E5: 0 | F5: =16*N4 -> 10.128 | L5: Imp. Cheese | M5: 565 | N5: =M5/1000 -> 0.565
A6: Bacon | B6: 0 | C6: 0 | D6: 0 | F6: 0 | L6: Beef | M6: 100 | N6: =M6/1000 -> 0.1
A7: Veggies | C7: 0 | D7: 0 | E7: 0 | F7: 0 | I7: Mushroom | J7: 20 | L7: Olives | M7: 762 | N7: =M7/1520 -> 0.50131579
A8: Cheese | C8: =0.49*180 -> 88.2 | D8: 88.2 | E8: 88.2 | F8: =80*N2 -> 39.2 | I8: Olives | J8: 15 | K8: =N7*J8 -> 7.5197368 | L8: Mushroom | M8: 80 | N8: =M8/400 -> 0.2
A9: Imp. Cheese | C9: 2 | D9: 2 | E9: =4*N5 -> 2.26 | F9: =2*N5 -> 1.13 | H9: 565 | I9: Imp. Cheese | J9: 2 | L9: P. Pepperoni
A10: Dough | C10: 15 | D10: 15 | E10: 15 | F10: 10 | L10: Origano | M10: 480 | N10: =M10/500 -> 0.96
A11: Sauce | C11: 15 | D11: 15 | E11: 15 | F11: 10 | L11: Olive Oil
A12: Olives | B12: 9 | C12: 9 | D12: 9 | E12: 9 | F12: =6*N7 -> 3.0078947
A13: Mushroom | C13: 10 | D13: 10 | E13: 10 | F13: =20*N8 -> 4
A14: Toppings | C14: 20 | D14: 20 | E14: 20 | F14: =16*N8 -> 3.2
A15: Olive Oil | B15: 8 | C15: 8 | D15: 8 | E15: 8 | F15: 5
A16: Origano | B16: 5 | C16: 2 | D16: 2 | E16: 2 | F16: 1
A17: Tomato Confit | B17: 10 | C17: 10 | D17: 10 | E17: 10 | F17: 5
B18: =SUM(B2:B17) -> 32 | C18: =SUM(C2:C17) -> 279.2 | D18: =SUM(D2:D17) -> 306.2 | E18: =SUM(E2:E17) -> 306.46 | F18: =SUM(F2:F17) -> 131.88589 | I18: =490/13 -> 37.692308
C19: =C18*4 -> 1116.8 | G19: =F18/F20 -> 0.22936677
C20: 900 | D20: =C20-C18-sum(C23:C27) -> 409.8 | F20: 575 | H20: =F20*75 -> 43125
C21: =C18/C20 -> 0.31022222 | E21: 150 | G21: =400/12 -> 33.333333
E22: 250
C23: 23 | E23: 33 | G23: =1800/12 -> 150
C24: 5 | E24: 800
C25: 1.5 | E25: 500
C26: 0.5 | E26: 700
C27: 181 | E27: 600
E28: 1500
E29: =SUM(E21:E28) -> 4533 | F29: =E29/25 -> 181.32

Sheet Pizza Costing New
A2: PIZZA | B2: Size | C2: Column 25 | D2: Column 24 | E2: Chicken | F2: Column 26 | G2: Column 27 | H2: Beef | I2: Pork | J2: Pepperoni | K2: Bacon | L2: Veggies | M2: Cheese | N2: Imp. Cheese | O2: Dough | P2: Sauce | Q2: Olives | R2: Mushroom | S2: Toppings | T2: Olive Oil | U2: Origano | V2: Tomato Confit | W2: BBQ SAUCE | X2: CHIMICHURRI | Y2: BUTTER | Z2: Column 4 | AA2: Column 5
A3: Wild Mushroom | B3: Small
A4: Wild Mushroom | B4: Medium
A5: Wild Mushroom | B5: Large
A6: Melanzane | B6: Small
A7: Melanzane | B7: Medium
A8: Melanzane | B8: Large
A9: Premavera | B9: Small
A10: Premavera | B10: Medium
A11: Premavera | B11: Large
A12: Grilled Paneer | B12: Small
A13: Grilled Paneer | B13: Medium
A14: Grilled Paneer | B14: Large
A15: Margherita | B15: Small | E15: 0
A16: Margherita | B16: Medium
A17: Margherita | B17: Large
A18: Quattro Formaggi | B18: Small
A19: Quattro Formaggi | B19: Medium
A20: Quattro Formaggi | B20: Large
A21: Italian Salsiccia | B21: Small
A22: Italian Salsiccia | B22: Medium
A23: Italian Salsiccia | B23: Large
A24: Capricciosa | B24: Small
A25: Capricciosa | B25: Medium
A26: Capricciosa | B26: Large
A27: Pepperoni | B27: Small
... A65: Meat Lovers Pizza | B65: Large
R82: =190/8 -> 23.75
A84: Item | C84: S | D84: Sprite | E84: GB | F84: 399 | G84: 449 | H84: 499 | I84: 549 | J84: 599 | K84: 649 | L84: 699 | M84: 749 | N84: 499 | O84: 849 | P84: 699 | Q84: 749 | R84: 499 | S84: 849 | T84: Pizza | U84: Sprite | V84: GB | W84: Pizza | X84: Sprite | Y84: GB | Z84: Pizza | AA84: Sprite | AB84: GB
A85: Wild Mushroom | C85: 450 | F85: FALSE | G85: FALSE | H85: FALSE | I85: FALSE | J85: FALSE | K85: FALSE | L85: FALSE | M85: FALSE | N85: FALSE | O85: FALSE | P85: FALSE | Q85: FALSE | R85: FALSE | S85: FALSE
A86: Melanzane | F86: FALSE | G86: FALSE | H86: FALSE | I86: FALSE | J86: FALSE | K86: FALSE | L86: FALSE | M86: FALSE | N86: FALSE | O86: FALSE | P86: FALSE | Q86: FALSE | R86: FALSE | S86: FALSE
A87: Premavera | B87: =sum(C87:E87) -> 660 | C87: 450 | D87: 20 | E87: 190 | F87: FALSE | G87: FALSE | H87: TRUE | I87: FALSE | J87: FALSE | K87: FALSE | L87: TRUE | M87: FALSE | N87: FALSE | O87: FALSE | P87: TRUE | Q87: FALSE | R87: FALSE | S87: FALSE | T87: 200 | U87: 12 | V87: 15 | W87: 270 | X87: 24 | Y87: 15 | Z87: 350 | AB87: 15
A88: Grilled Paneer | B88: =sum(C88:E88) -> 660 | C88: 450 | D88: 20 | E88: 190 | F88: FALSE | G88: FALSE | H88: TRUE | I88: FALSE | J88: FALSE | K88: FALSE | L88: TRUE | M88: FALSE | N88: FALSE | O88: FALSE | P88: TRUE | Q88: FALSE | R88: FALSE | S88: FALSE | T88: 200 | U88: 12 | V88: 15 | W88: 270 | X88: 24 | Y88: 15 | Z88: 350 | AB88: 15
A89: Margherita | B89: =sum(C89:E89) -> 630 | C89: 420 | D89: 20 | E89: 190 | F89: TRUE | G89: FALSE | H89: FALSE | I89: FALSE | J89: FALSE | K89: FALSE | L89: TRUE | M89: FALSE | N89: FALSE | O89: FALSE | P89: TRUE | Q89: FALSE | R89: FALSE | S89: FALSE | T89: 100 | U89: 12 | V89: 15 | W89: 140 | X89: 24 | Y89: 15 | Z89: 180 | AB89: 15
A90: Quattro Formaggi | B90: =sum(C90:E90) -> 680 | C90: 470 | D90: 20 | E90: 190 | F90: TRUE | G90: FALSE | H90: FALSE | I90: FALSE | J90: FALSE | K90: FALSE | L90: TRUE | M90: FALSE | N90: FALSE | O90: FALSE | P90: TRUE | Q90: FALSE | R90: FALSE | S90: FALSE | T90: 150 | U90: 12 | V90: 15 | W90: 210 | X90: 24 | Y90: 15 | Z90: 260 | AB90: 15
A91: Italian Salsiccia | B91: =sum(C91:E91) -> 685 | C91: 475 | D91: 20 | E91: 190 | F91: FALSE | G91: FALSE | H91: TRUE | I91: FALSE | J91: FALSE | K91: FALSE | L91: TRUE | M91: FALSE | N91: FALSE | O91: FALSE | P91: TRUE | Q91: FALSE | R91: FALSE | S91: FALSE | T91: 160 | U91: 12 | V91: 15 | W91: 225 | X91: 24 | Y91: 15 | Z91: 300 | AB91: 15
A92: Capricciosa | B92: =sum(C92:E92) -> 685 | C92: 475 | D92: 20 | E92: 190 | F92: FALSE | G92: FALSE | H92: TRUE | I92: FALSE | J92: FALSE | K92: FALSE | L92: TRUE | M92: FALSE | N92: FALSE | O92: FALSE | P92: TRUE | Q92: FALSE | R92: FALSE | S92: FALSE | T92: 180 | U92: 12 | V92: 15 | W92: 250 | X92: 24 | Y92: 15 | Z92: 325 | AB92: 15
A93: Pepperoni | B93: =sum(C93:E93) -> 685 | C93: 475 | D93: 20 | E93: 190 | F93: FALSE | G93: TRUE | H93: FALSE | I93: FALSE | J93: FALSE | K93: FALSE | L93: TRUE | M93: FALSE | N93: FALSE | O93: FALSE | P93: TRUE | Q93: FALSE | R93: FALSE | S93: FALSE | T93: 170 | U93: 12 | V93: 15 | W93: 240 | X93: 24 | Y93: 15 | Z93: 325 | AB93: 15
A94: Bbq Chicken Pizza | B94: =sum(C94:E94) -> 735 | C94: 525 | D94: 20 | E94: 190 | F94: FALSE | G94: FALSE | H94: FALSE | I94: TRUE | J94: FALSE | K94: FALSE | L94: FALSE | M94: TRUE | N94: FALSE | O94: FALSE | P94: FALSE | Q94: TRUE | R94: FALSE | S94: FALSE | T94: 275 | U94: 12 | V94: 15 | W94: 300 | X94: 24 | Y94: 15 | Z94: 370 | AB94: 15
A95: Jamaican Jerk Pizza | B95: =sum(C95:E95) -> 735 | C95: 525 | D95: 20 | E95: 190 | F95: FALSE | G95: FALSE | H95: FALSE | I95: TRUE | J95: FALSE | K95: FALSE | L95: FALSE | M95: TRUE | N95: FALSE | O95: FALSE | P95: FALSE | Q95: TRUE | R95: FALSE | S95: FALSE | T95: 285 | U95: 12 | V95: 15 | W95: 315 | X95: 24 | Y95: 15 | Z95: 385 | AB95: 15
A96: Lebanese Chicken Pizza | B96: =sum(C96:E96) -> 770 | C96: 560 | D96: 20 | E96: 190 | F96: FALSE | G96: FALSE | H96: FALSE | I96: TRUE | J96: FALSE | K96: FALSE | L96: FALSE | M96: TRUE | N96: FALSE | O96: FALSE | P96: FALSE | Q96: TRUE | R96: FALSE | S96: FALSE | T96: 285 | U96: 12 | V96: 15 | W96: 315 | X96: 24 | Y96: 15 | Z96: 385 | AB96: 15
A97: Diavola | B97: =sum(C97:E97) -> 770 | C97: 560 | D97: 20 | E97: 190 | F97: FALSE | G97: FALSE | H97: FALSE | I97: TRUE | J97: FALSE | K97: FALSE | L97: FALSE | M97: TRUE | N97: FALSE | O97: FALSE | P97: FALSE | Q97: TRUE | R97: FALSE | S97: FALSE | T97: 305 | U97: 12 | V97: 15 | W97: 345 | X97: 24 | Y97: 15 | Z97: 415 | AB97: 15
A98: Chicken Tikka Pizza | B98: =sum(C98:E98) -> 735 | C98: 525 | D98: 20 | E98: 190 | F98: FALSE | G98: FALSE | H98: FALSE | I98: TRUE | J98: FALSE | K98: FALSE | L98: FALSE | M98: TRUE | N98: FALSE | O98: FALSE | P98: FALSE | Q98: TRUE | R98: FALSE | S98: FALSE | T98: 275 | U98: 12 | V98: 15 | W98: 300 | X98: 24 | Y98: 15 | Z98: 370 | AB98: 15
... A105: Meat Lovers Pizza | B105: =sum(C105:E105) -> 960 | C105: 750 | D105: 20 | E105: 190 | F105: FALSE | G105: FALSE | H105: FALSE | I105: FALSE | J105: FALSE | K105: TRUE | L105: FALSE | M105: FALSE | N105: FALSE | O105: TRUE | P105: FALSE | Q105: FALSE | R105: FALSE | S105: TRUE | T105: 325 | U105: 12 | V105: 15 | W105: 360 | X105: 24 | Y105: 15 | Z105: 450 | AB105: 15

Sheet SwiggyInvoiceAnnexture
J1: 1 | K1: 2 | L1: 3a | M1: 3b | N1: 3 | O1: 4 | P1: 5a | Q1: 5b | R1: A | T1: 6 | U1: 7 | V1: 8 | W1: 9 | X1: 10 | Y1: 11 | Z1: 12 | AA1: 13 | AB1: 14 | AC1: 15 | AD1: 16 | AE1: B | AF1: 17 | AG1: 18 | AH1: C | AI1: 19 | AJ1: 20 | AK1: 21 | AL1: D
A2: PaymentID | B2: Order ID | C2: Parent Order ID | D2: Order Date | E2: Order Status | F2: Order Category | G2: Order Payment Type | H2: Cancelled By? | I2: Coupon type applied by customer | J2: Item Total | K2: Packaging Charges | L2: Restaurant Discounts (Promo, Freebies, Flat Off, etc.) | M2: Swiggy One Exclusive Offer Discount | N2: Restaurant Discount Share [3a+3b] | O2: Net Bill Value (before taxes) [1+2-3] | P2: GST Collected | Q2: Total Customer Paid [4+5] | R2: Commission charged on | S2: Service Fees % | T2: Commission | U2: Long Distance Charges | V2: Discount on Long Distance Fee | W2: Pocket Hero Fees | X2: Swiggy One Fees | Y2: Payment Collection Charges | Z2: Restaurant Cancellation Charges | AA2: Call Center Charges | AB2: Delivery Fee sponsored by Restaurant (w/o tax) | AC2: Bolt Fees | AD2: GST on Service Fee @18% | AE2: Total Swiggy Fees [6+7+8-9+10+11+12+13+14+15+16] | AF2: Customer Cancellations | AG2: Customer Complaints | AH2: Complaint & Cancellation Charges [17+18] | AI2: GST Deduction | AJ2: TCS | AK2: TDS | AL2: Total Taxes [19+20+21] | AM2: Net Payout for Order (after taxes) [A-B-C-D] | AN2: Long Distance Order | AO2: Last Mile (in km) | AP2: MFR Accurate? | AQ2: MFR Pressed? | AR2: Coupon Code Sourced | AS2: Discount Campaign ID | AT2: Replicated Order | AU2: Base order ID | AV2: Cancellation time | AW2: Pick Up Status | AX2: Swiggy One Customer? | AY2: Pocket Hero Order?
A3: 45763 | B3: 203323727833985 | D3: 45758.513 | E3: delivered | F3: regular | J3: 400 | K3: 0 | L3: 0 | M3: 0 | N3: 0 | O3: 400 | P3: 20 | Q3: 420 | R3: 420 | S3: 0.1 | T3: 42 | U3: 0 | V3: 0 | W3: 0 | X3: 0 | Y3: 8.4 | Z3: 0 | AA3: 0 | AB3: 0 | AC3: 0 | AD3: 9.08 | AE3: 59.48 | AF3: 0 | AG3: 0 | AH3: 0 | AI3: 20 | AJ3: 0 | AK3: 0.4 | AL3: 20.4 | AM3: 340.14 | AN3: No | AO3: 1.447 | AP3: No | AQ3: No | AS3: 02fe73c8-087b-4f40-b26e-536d6bfecc24 | AT3: No | AX3: Yes | AY3: No
A4: 45763 | B4: 203349440127363 | D4: 45758.811 | E4: delivered | F4: regular | I4: SWIGGYUPI25 | J4: 750 | K4: 10 | L4: 0 | M4: 0 | N4: 0 | O4: 760 | P4: 38 | Q4: 798 | R4: 798 | S4: 0.1 | T4: 79.8 | U4: 0 | V4: 0 | W4: 0 | X4: 0 | Y4: 15.96 | Z4: 0 | AA4: 0 | AB4: 0 | AC4: 0 | AD4: 17.24 | AE4: 113 | AF4: 0 | AG4: 0 | AH4: 0 | AI4: 38 | AJ4: 0 | AK4: 0.76 | AL4: 38.76 | AM4: 646.24 | AN4: No | AO4: 0.694 | AP4: No | AQ4: No | AS4: db2ebb10-8c7f-40f4-a0e3-4179ee1fb8e7 | AT4: No | AX4: Yes | AY4: No
A5: 45763 | B5: 203359178077774 | D5: 45758.923 | E5: delivered | F5: regular | J5: 1250 | K5: 0 | L5: 0 | M5: 0 | N5: 0 | O5: 1250 | P5: 62.5 | Q5: 1312.5 | R5: 1312.5 | S5: 0.1 | T5: 131.25 | U5: 0 | V5: 0 | W5: 0 | X5: 0 | Y5: 26.25 | Z5: 0 | AA5: 0 | AB5: 0 | AC5: 0 | AD5: 28.34 | AE5: 185.84 | AF5: 0 | AG5: 0 | AH5: 0 | AI5: 62.5 | AJ5: 0 | AK5: 1.25 | AL5: 63.75 | AM5: 1062.89 | AN5: No | AO5: 5.372 | AP5: No | AQ5: No | AS5: 10632ce9-1bdc-421b-a9b9-65a5a0edf08f | AT5: No | AX5: Yes | AY5: No
A6: 45763 | B6: 203433657056770 | D6: 45759.785 | E6: delivered | F6: regular | J6: 525 | K6: 10 | L6: 0 | M6: 0 | N6: 0 | O6: 535 | P6: 26.76 | Q6: 561.76 | R6: 561.76 | S6: 0.1 | T6: 56.18 | U6: 0 | V6: 0 | W6: 0 | X6: 0 | Y6: 11.24 | Z6: 0 | AA6: 0 | AB6: 0 | AC6: 0 | AD6: 12.14 | AE6: 79.56 | AF6: 0 | AG6: 0 | AH6: 0 | AI6: 26.75 | AJ6: 0 | AK6: 0.54 | AL6: 27.29 | AM6: 454.91 | AN6: No | AO6: 5.081 | AP6: No | AQ6: No | AS6: e83de7e4-6e68-4026-aad6-78b7ee68900d | AT6: No | AX6: Yes | AY6: No
A7: 45763 | B7: 203435912866093 | D7: 45759.811 | E7: delivered | F7: regular | J7: 1105 | K7: 10 | L7: 0 | M7: 0 | N7: 0 | O7: 1115 | P7: 55.76 | Q7: 1170.76 | R7: 1170.76 | S7: 0.1 | T7: 117.08 | U7: 0 | V7: 0 | W7: 0 | X7: 0 | Y7: 23.42 | Z7: 0 | AA7: 0 | AB7: 0 | AC7: 0 | AD7: 25.3 | AE7: 165.8 | AF7: 0 | AG7: 0 | AH7: 0 | AI7: 55.75 | AJ7: 0 | AK7: 1.11 | AL7: 56.86 | AM7: 948.11 | AN7: No | AO7: 0.785 | AP7: No | AQ7: No | AS7: 99e14625-b48f-4bd8-866a-17aa4cb76d44 | AT7: No | AX7: Yes | AY7: No
A8: 45763 | B8: 203438608676679 | D8: 45759.843 | E8: delivered | F8: regular | J8: 1185 | K8: 10 | L8: 0 | M8: 0 | N8: 0 | O8: 1195 | P8: 59.76 | Q8: 1254.76 | R8: 1254.76 | S8: 0.1 | T8: 125.48 | U8: 0 | V8: 0 | W8: 0 | X8: 0 | Y8: 25.1 | Z8: 0 | AA8: 0 | AB8: 0 | AC8: 0 | AD8: 27.1 | AE8: 177.68 | AF8: 0 | AG8: 0 | AH8: 0 | AI8: 59.75 | AJ8: 0 | AK8: 1.2 | AL8: 60.95 | AM8: 1016.12 | AN8: No | AO8: 1.277 | AP8: No | AQ8: No | AS8: ad5bc6b6-9d4c-4c85-8d0d-6c378b2cbe44 | AT8: No | AX8: Yes | AY8: No
A9: 45763 | B9: 203438922167612 | D9: 45759.846 | E9: delivered | F9: regular | J9: 1290 | K9: 0 | L9: 0 | M9: 0 | N9: 0 | O9: 1290 | P9: 64.5 | Q9: 1354.5 | R9: 1354.5 | S9: 0.1 | T9: 135.45 | U9: 0 | V9: 0 | W9: 0 | X9: 0 | Y9: 27.09 | Z9: 0 | AA9: 0 | AB9: 0 | AC9: 0 | AD9: 29.26 | AE9: 191.8 | AF9: 0 | AG9: 0 | AH9: 0 | AI9: 64.5 | AJ9: 0 | AK9: 1.29 | AL9: 65.79 | AM9: 1096.91 | AN9: No | AO9: 5.743 | AP9: No | AQ9: No | AS9: e96dbff1-0260-46a2-b2ce-f7352dbfd416 | AT9: No | AX9: Yes | AY9: No
A10: 45770 | B10: 203508162484177 | D10: 45760.648 | E10: delivered | F10: regular | J10: 575 | K10: 10 | L10: 0 | M10: 0 | N10: 0 | O10: 585 | P10: 29.26 | Q10: 614.26 | R10: 614.24 | S10: 0.1 | T10: 61.42 | U10: 0 | V10: 0 | W10: 0 | X10: 0 | Y10: 12.28 | Z10: 0 | AA10: 0 | AB10: 0 | AC10: 0 | AD10: 13.26 | AE10: 86.96 | AF10: 0 | AG10: 0 | AH10: 0 | AI10: 29.25 | AJ10: 0 | AK10: 0.58 | AL10: 29.83 | AM10: 497.44 | AN10: No | AO10: 7.235 | AP10: No | AQ10: No | AS10: 8a15f9cc-a3fa-4192-8f37-bcb6cb209e45 | AT10: No | AX10: Yes | AY10: No
A11: 45770 | B11: 203521051067944 | D11: 45760.797 | E11: delivered | F11: regular | J11: 1910 | K11: 0 | L11: 0 | M11: 0 | N11: 0 | O11: 1910 | P11: 95.5 | Q11: 2005.5 | R11: 2005.5 | S11: 0.1 | T11: 200.55 | U11: 0 | V11: 0 | W11: 0 | X11: 0 | Y11: 40.11 | Z11: 0 | AA11: 0 | AB11: 0 | AC11: 0 | AD11: 43.32 | AE11: 283.98 | AF11: 0 | AG11: 0 | AH11: 0 | AI11: 95.5 | AJ11: 0 | AK11: 1.91 | AL11: 97.41 | AM11: 1624.11 | AN11: No | AO11: 2.691 | AP11: No | AQ11: No | AS11: e87ec607-e87f-4200-b3c6-f8498907a2fc | AT11: No | AX11: Yes | AY11: No
A12: 45770 | B12: 203536479647997 | D12: 45760.975 | E12: delivered | F12: regular | J12: 1340 | K12: 10 | L12: 0 | M12: 0 | N12: 0 | O12: 1350 | P12: 67.5 | Q12: 1417.5 | R12: 1417.5 | S12: 0.1 | T12: 141.75 | U12: 0 | V12: 0 | W12: 0 | X12: 0 | Y12: 28.35 | Z12: 0 | AA12: 0 | AB12: 0 | AC12: 0 | AD12: 30.62 | AE12: 200.72 | AF12: 0 | AG12: 0 | AH12: 0 | AI12: 67.5 | AJ12: 0 | AK12: 1.35 | AL12: 68.85 | AM12: 1147.93 | AN12: No | AO12: 6.205 | AP12: No | AQ12: No | AS12: 89ea4797-9174-4a12-9f83-446aba7d390e | AT12: No | AX12: Yes | AY12: No
A13: 45770 | B13: 203595884273246 | D13: 45761.663 | E13: delivered | F13: regular | I13: TRYNEW | J13: 525 | K13: 10 | L13: 50 | M13: 0 | N13: 50 | O13: 485 | P13: 24.26 | Q13: 509.26 | R13: 509.24 | S13: 0.1 | T13: 50.92 | U13: 0 | V13: 0 | W13: 0 | X13: 0 | Y13: 10.18 | Z13: 0 | AA13: 0 | AB13: 0 | AC13: 0 | AD13: 11 | AE13: 72.1 | AF13: 0 | AG13: 0 | AH13: 0 | AI13: 24.25 | AJ13: 0 | AK13: 0.48 | AL13: 24.73 | AM13: 412.42 | AN13: No | AO13: 8.762 | AP13: Yes | AQ13: No | AS13: 90729877 | AT13: No | AX13: Yes | AY13: No
A14: 45770 | B14: 203690078159199 | D14: 45762.753 | E14: delivered | F14: regular | I14: TRYNEW | J14: 735 | K14: 10 | L14: 49.99 | M14: 0 | N14: 49.99 | O14: 695.01 | P14: 34.76 | Q14: 729.77 | R14: 729.77 | S14: 0.1 | T14: 72.98 | U14: 0 | V14: 0 | W14: 0 | X14: 0 | Y14: 14.6 | Z14: 0 | AA14: 0 | AB14: 0 | AC14: 0 | AD14: 15.76 | AE14: 103.34 | AF14: 0 | AG14: 0 | AH14: 0 | AI14: 34.75 | AJ14: 0 | AK14: 0.7 | AL14: 35.45 | AM14: 590.97 | AN14: No | AO14: 4.92 | AP14: Yes | AQ14: No | AS14: 6f4d7725-dab3-4496-8081-432387f8de29,5862cbfe-0ccd-4058-9b01-929069317251,6f4d7725-dab3-4496-8081-432387f8de29,5862cbfe-0ccd-4058-9b01-929069317251 | AT14: No | AX14: Yes | AY14: No
A15: 45770 | B15: 203697189606601 | D15: 45762.836 | E15: delivered | F15: regular | I15: TRYNEW | J15: 475 | K15: 10 | L15: 50 | M15: 0 | N15: 50 | O15: 435 | P15: 21.76 | Q15: 456.76 | R15: 456.76 | S15: 0.1 | T15: 45.68 | U15: 0 | V15: 0 | W15: 0 | X15: 0 | Y15: 9.14 | Z15: 0 | AA15: 0 | AB15: 0 | AC15: 0 | AD15: 9.86 | AE15: 64.68 | AF15: 0 | AG15: 0 | AH15: 0 | AI15: 21.75 | AJ15: 0 | AK15: 0.43 | AL15: 22.18 | AM15: 369.87 | AN15: No | AO15: 0.494 | AP15: Yes | AQ15: No | AS15: 90729877 | AT15: No | AX15: No | AY15: No
A16: 45770 | B16: 203755054264094 | D16: 45763.505 | E16: delivered | F16: regular | I16: TRYNEW | J16: 400 | K16: 0 | L16: 50 | M16: 0 | N16: 50 | O16: 350 | P16: 17.5 | Q16: 367.5 | R16: 367.5 | S16: 0.1 | T16: 36.75 | U16: 0 | V16: 0 | W16: 0 | X16: 0 | Y16: 7.35 | Z16: 0 | AA16: 0 | AB16: 0 | AC16: 0 | AD16: 7.94 | AE16: 52.04 | AF16: 0 | AG16: 0 | AH16: 0 | AI16: 17.5 | AJ16: 0 | AK16: 0.35 | AL16: 17.85 | AM16: 297.61 | AN16: No | AO16: 7.172 | AP16: Yes | AQ16: No | AS16: 2742d5bf-d25b-4ce0-a5c8-0b965a455541,2742d5bf-d25b-4ce0-a5c8-0b965a455541 | AT16: No | AX16: Yes | AY16: No
A17: 45770 | B17: 203761162091130 | D17: 45763.576 | E17: delivered | F17: regular | I17: TRYNEW | J17: 880 | K17: 10 | L17: 50 | M17: 0 | N17: 50 | O17: 840 | P17: 42 | Q17: 882 | R17: 882 | S17: 0.1 | T17: 88.2 | U17: 0 | V17: 0 | W17: 0 | X17: 0 | Y17: 17.64 | Z17: 0 | AA17: 0 | AB17: 0 | AC17: 0 | AD17: 19.06 | AE17: 124.9 | AF17: 0 | AG17: 0 | AH17: 0 | AI17: 42 | AJ17: 0 | AK17: 0.84 | AL17: 42.84 | AM17: 714.28 | AN17: No | AO17: 3.355 | AP17: Yes | AQ17: No | AS17: fa46f67b-3f5e-42e6-8cf9-5a5f53bb4f32,e08f0c64-50e7-4bb2-bd4f-4fd6697f5908,fa46f67b-3f5e-42e6-8cf9-5a5f53bb4f32,e08f0c64-50e7-4bb2-bd4f-4fd6697f5908 | AT17: No | AX17: Yes | AY17: No
A18: 45770 | B18: 203785580997113 | D18: 45763.859 | E18: delivered | F18: regular | J18: 1365 | K18: 20 | L18: 0 | M18: 0 | N18: 0 | O18: 1385 | P18: 69.26 | Q18: 1454.26 | R18: 1454.24 | S18: 0.1 | T18: 145.42 | U18: 0 | V18: 0 | W18: 0 | X18: 0 | Y18: 29.08 | Z18: 0 | AA18: 0 | AB18: 0 | AC18: 0 | AD18: 31.42 | AE18: 205.92 | AF18: 0 | AG18: 0 | AH18: 0 | AI18: 69.25 | AJ18: 0 | AK18: 1.39 | AL18: 70.64 | AM18: 1177.72 | AN18: No | AO18: 5.142 | AP18: Yes | AQ18: No | AS18: 35e81f58-2cb3-4f23-8f84-37e8baa01223 | AT18: No | AX18: Yes | AY18: No
A19: 45770 | B19: 203788164490719 | D19: 45763.888 | E19: delivered | F19: regular | I19: TOPUPOFFER | J19: 725 | K19: 0 | L19: 50 | M19: 0 | N19: 50 | O19: 675 | P19: 33.76 | Q19: 708.76 | R19: 708.76 | S19: 0.1 | T19: 70.88 | U19: 0 | V19: 0 | W19: 0 | X19: 0 | Y19: 14.18 | Z19: 0 | AA19: 0 | AB19: 0 | AC19: 0 | AD19: 15.32 | AE19: 100.38 | AF19: 0 | AG19: 0 | AH19: 0 | AI19: 33.75 | AJ19: 0 | AK19: 0.68 | AL19: 34.43 | AM19: 573.96 | AN19: No | AO19: 1.119 | AP19: Yes | AQ19: No | AR19: TRYNEW | AS19: 63a17ebb-dc25-49b0-80fe-70f5d9dc24cc,dd81fa81-54ee-4d25-a10a-f177fb52d3c5,63a17ebb-dc25-49b0-80fe-70f5d9dc24cc,dd81fa81-54ee-4d25-a10a-f177fb52d3c5 | AT19: No | AX19: Yes | AY19: No
A20: 45770 | B20: 203862521805423 | D20: 45764.749 | E20: delivered | F20: regular | I20: TRYNEW | J20: 575 | K20: 10 | L20: 50 | M20: 0 | N20: 50 | O20: 535 | P20: 26.76 | Q20: 561.76 | R20: 561.76 | S20: 0.1 | T20: 56.18 | U20: 0 | V20: 0 | W20: 0 | X20: 0 | Y20: 11.24 | Z20: 0 | AA20: 0 | AB20: 0 | AC20: 0 | AD20: 12.14 | AE20: 79.56 | AF20: 0 | AG20: 0 | AH20: 0 | AI20: 26.75 | AJ20: 0 | AK20: 0.54 | AL20: 27.29 | AM20: 454.91 | AN20: No | AO20: 0.767 | AP20: Yes | AQ20: No | AS20: d6e050f4-eca0-4818-8d37-5f77515a7742,534bdf7e-0aca-4236-8889-d0ab7f3859ce,d6e050f4-eca0-4818-8d37-5f77515a7742,534bdf7e-0aca-4236-8889-d0ab7f3859ce | AT20: No | AX20: Yes | AY20: No
A21: 45770 | B21: 203867191085444 | D21: 45764.803 | E21: delivered | F21: regular | I21: SWIGGYIT | J21: 750 | K21: 10 | L21: 50 | M21: 0 | N21: 50 | O21: 710 | P21: 35.5 | Q21: 745.5 | R21: 745.5 | S21: 0.1 | T21: 74.55 | U21: 0 | V21: 0 | W21: 0 | X21: 0 | Y21: 14.91 | Z21: 0 | AA21: 0 | AB21: 0 | AC21: 0 | AD21: 16.1 | AE21: 105.56 | AF21: 0 | AG21: 0 | AH21: 0 | AI21: 35.5 | AJ21: 0 | AK21: 0.71 | AL21: 36.21 | AM21: 603.73 | AN21: No | AO21: 0.802 | AP21: Yes | AQ21: No | AS21: db2ebb10-8c7f-40f4-a0e3-4179ee1fb8e7,db2ebb10-8c7f-40f4-a0e3-4179ee1fb8e7 | AT21: No | AX21: Yes | AY21: No
A22: 45770 | B22: 204035770284769 | D22: 45766.754 | E22: delivered | F22: regular | J22: 1185 | K22: 0 | L22: 0 | M22: 0 | N22: 0 | O22: 1185 | P22: 59.26 | Q22: 1244.26 | R22: 1244.24 | S22: 0.1 | T22: 124.42 | U22: 0 | V22: 0 | W22: 0 | X22: 0 | Y22: 24.88 | Z22: 0 | AA22: 0 | AB22: 0 | AC22: 0 | AD22: 26.88 | AE22: 176.18 | AF22: 0 | AG22: 0 | AH22: 0 | AI22: 59.25 | AJ22: 0 | AK22: 1.19 | AL22: 60.44 | AM22: 1007.65 | AN22: No | AO22: 2.691 | AP22: Yes | AQ22: No | AS22: 5245b39a-cfa2-43cb-9a94-31ab9d88140a,785d7880-dd52-4886-84fa-96561a025dfd | AT22: No | AX22: Yes | AY22: No
A23: 45770 | B23: 204042752030857 | D23: 45766.835 | E23: delivered | F23: regular | I23: AXIS200 | J23: 1050 | K23: 0 | L23: 0 | M23: 0 | N23: 0 | O23: 1050 | P23: 52.5 | Q23: 1102.5 | R23: 1102.5 | S23: 0.1 | T23: 110.25 | U23: 0 | V23: 0 | W23: 0 | X23: 0 | Y23: 22.05 | Z23: 0 | AA23: 0 | AB23: 0 | AC23: 0 | AD23: 23.82 | AE23: 156.12 | AF23: 0 | AG23: 0 | AH23: 0 | AI23: 52.5 | AJ23: 0 | AK23: 1.05 | AL23: 53.55 | AM23: 892.85 | AN23: No | AO23: 4.255 | AP23: Yes | AQ23: No | AS23: 35e81f58-2cb3-4f23-8f84-37e8baa01223 | AT23: No | AX23: Yes | AY23: No
A24: 45770 | B24: 204051867574558 | D24: 45766.941 | E24: cancelled | F24: regular | G24: cash | H24: CUSTOMER | J24: 475 | K24: 10 | L24: 0 | M24: 0 | N24: 0 | O24: 485 | P24: 24.26 | Q24: 509.26 | R24: 509.24 | S24: 0.1 | T24: 50.92 | U24: 0 | V24: 0 | W24: 0 | X24: 0 | Y24: 10.18 | Z24: 0 | AA24: 0 | AB24: 0 | AC24: 0 | AD24: 11 | AE24: 72.1 | AF24: 0 | AG24: 0 | AH24: 0 | AI24: 24.25 | AJ24: 0 | AK24: 0.48 | AL24: 24.73 | AM24: 412.42 | AN24: No | AO24: 6.518 | AP24: Yes | AQ24: Yes | AS24: 16f4c31c-55dd-4039-b271-c0e3333c4b2f,b3e9bb18-0a53-40a1-a9ed-29020681a1c2 | AT24: No | AV24: 81.85 | AW24: picked up | AX24: Yes | AY24: No
A25: 45770 | B25: 204052645766134 | D25: 45766.95 | E25: delivered | F25: regular | J25: 475 | K25: 10 | L25: 0 | M25: 0 | N25: 0 | O25: 485 | P25: 24.26 | Q25: 509.26 | R25: 509.24 | S25: 0.1 | T25: 50.92 | U25: 0 | V25: 0 | W25: 0 | X25: 0 | Y25: 10.18 | Z25: 0 | AA25: 0 | AB25: 0 | AC25: 0 | AD25: 11 | AE25: 72.1 | AF25: 0 | AG25: 0 | AH25: 0 | AI25: 24.25 | AJ25: 0 | AK25: 0.48 | AL25: 24.73 | AM25: 412.42 | AN25: No | AO25: 9.562 | AP25: Yes | AQ25: No | AS25: 16f4c31c-55dd-4039-b271-c0e3333c4b2f | AT25: No | AX25: Yes | AY25: No
A26: 45777 | B26: 204102083771100 | D26: 45767.522 | E26: delivered | F26: regular | I26: ON-TIME-PROMISE | J26: 875 | K26: 0 | L26: 0 | M26: 0 | N26: 0 | O26: 875 | P26: 43.76 | Q26: 918.76 | R26: 918.76 | S26: 0.1 | T26: 91.88 | U26: 0 | V26: 0 | W26: 0 | X26: 0 | Y26: 18.38 | Z26: 0 | AA26: 0 | AB26: 0 | AC26: 0 | AD26: 19.84 | AE26: 130.1 | AF26: 0 | AG26: 269 | AH26: 269 | AI26: 43.75 | AJ26: 0 | AK26: 0.88 | AL26: 44.63 | AM26: 475.01 | AN26: No | AO26: 16.192 | AP26: Yes | AQ26: No | AT26: No | AX26: Yes | AY26: No
A27: 45777 | B27: 204124492278368 | D27: 45767.781 | E27: delivered | F27: regular | J27: 400 | K27: 0 | L27: 0 | M27: 0 | N27: 0 | O27: 400 | P27: 20 | Q27: 420 | R27: 420 | S27: 0.1 | T27: 42 | U27: 0 | V27: 0 | W27: 0 | X27: 0 | Y27: 8.4 | Z27: 0 | AA27: 0 | AB27: 0 | AC27: 0 | AD27: 9.08 | AE27: 59.48 | AF27: 0 | AG27: 0 | AH27: 0 | AI27: 20 | AJ27: 0 | AK27: 0.4 | AL27: 20.4 | AM27: 340.14 | AN27: No | AO27: 5.013 | AP27: Yes | AQ27: No | AS27: 711fc754-4304-4178-a84a-19e7d53c8509 | AT27: No | AX27: Yes | AY27: No
A28: 45777 | B28: 204124647404444 | D28: 45767.783 | E28: delivered | F28: regular | J28: 1065 | K28: 10 | L28: 0 | M28: 0 | N28: 0 | O28: 1075 | P28: 53.76 | Q28: 1128.76 | R28: 1128.76 | S28: 0.1 | T28: 112.88 | U28: 0 | V28: 0 | W28: 0 | X28: 0 | Y28: 22.58 | Z28: 0 | AA28: 0 | AB28: 0 | AC28: 0 | AD28: 24.38 | AE28: 159.84 | AF28: 0 | AG28: 0 | AH28: 0 | AI28: 53.75 | AJ28: 0 | AK28: 1.07 | AL28: 54.82 | AM28: 914.08 | AN28: No | AO28: 1.649 | AP28: Yes | AQ28: No | AS28: fbb9e879-f026-4f66-a87a-6c22f7cd320b | AT28: No | AX28: No | AY28: No
A29: 45777 | B29: 204212905215057 | D29: 45768.804 | E29: delivered | F29: regular | J29: 975 | K29: 10 | L29: 0 | M29: 0 | N29: 0 | O29: 985 | P29: 49.26 | Q29: 1034.26 | R29: 1034.24 | S29: 0.1 | T29: 103.42 | U29: 0 | V29: 0 | W29: 0 | X29: 0 | Y29: 20.68 | Z29: 0 | AA29: 0 | AB29: 0 | AC29: 0 | AD29: 22.34 | AE29: 146.44 | AF29: 0 | AG29: 0 | AH29: 0 | AI29: 49.25 | AJ29: 0 | AK29: 0.98 | AL29: 50.23 | AM29: 837.58 | AN29: No | AO29: 8.021 | AP29: Yes | AQ29: No | AT29: No | AX29: Yes | AY29: No
A30: 45777 | B30: 204215490761230 | D30: 45768.834 | E30: delivered | F30: regular | J30: 1990 | K30: 30 | L30: 0 | M30: 0 | N30: 0 | O30: 2020 | P30: 101 | Q30: 2121 | R30: 2121 | S30: 0.1 | T30: 212.1 | U30: 0 | V30: 0 | W30: 0 | X30: 0 | Y30: 42.42 | Z30: 0 | AA30: 0 | AB30: 0 | AC30: 0 | AD30: 45.82 | AE30: 300.34 | AF30: 0 | AG30: 0 | AH30: 0 | AI30: 101 | AJ30: 0 | AK30: 2.02 | AL30: 103.02 | AM30: 1717.66 | AN30: No | AO30: 1.555 | AP30: Yes | AQ30: No | AS30: cca1fb70-4e2f-4a28-ab2b-0216e01e6571 | AT30: No | AX30: Yes | AY30: No
A31: 45777 | B31: 204218347708026 | D31: 45768.867 | E31: delivered | F31: regular | J31: 1035 | K31: 10 | L31: 0 | M31: 0 | N31: 0 | O31: 1045 | P31: 52.26 | Q31: 1097.26 | R31: 1097.24 | S31: 0.1 | T31: 109.72 | U31: 0 | V31: 0 | W31: 0 | X31: 0 | Y31: 21.94 | Z31: 0 | AA31: 0 | AB31: 0 | AC31: 0 | AD31: 23.7 | AE31: 155.36 | AF31: 0 | AG31: 0 | AH31: 0 | AI31: 52.25 | AJ31: 0 | AK31: 1.04 | AL31: 53.29 | AM31: 888.6 | AN31: No | AO31: 10.826 | AP31: Yes | AQ31: No | AT31: No | AX31: No | AY31: No
A32: 45777 | B32: 204222343884996 | D32: 45768.914 | E32: delivered | F32: regular | I32: FEDERALCC150 | J32: 745 | K32: 10 | L32: 0 | M32: 0 | N32: 0 | O32: 755 | P32: 37.76 | Q32: 792.76 | R32: 792.76 | S32: 0.1 | T32: 79.28 | U32: 0 | V32: 0 | W32: 0 | X32: 0 | Y32: 15.86 | Z32: 0 | AA32: 0 | AB32: 0 | AC32: 0 | AD32: 17.12 | AE32: 112.26 | AF32: 0 | AG32: 0 | AH32: 0 | AI32: 37.75 | AJ32: 0 | AK32: 0.76 | AL32: 38.51 | AM32: 641.97 | AN32: No | AO32: 13.615 | AP32: Yes | AQ32: No | AT32: No | AX32: Yes | AY32: No
A33: 45777 | B33: 204287737282944 | D33: 45769.671 | E33: delivered | F33: regular | J33: 495 | K33: 10 | L33: 0 | M33: 0 | N33: 0 | O33: 505 | P33: 25.26 | Q33: 530.26 | R33: 530.24 | S33: 0.1 | T33: 53.02 | U33: 0 | V33: 0 | W33: 0 | X33: 0 | Y33: 10.6 | Z33: 0 | AA33: 0 | AB33: 0 | AC33: 0 | AD33: 11.46 | AE33: 75.08 | AF33: 0 | AG33: 0 | AH33: 0 | AI33: 25.25 | AJ33: 0 | AK33: 0.51 | AL33: 25.76 | AM33: 429.43 | AN33: No | AO33: 2.881 | AP33: Yes | AQ33: No | AS33: ed87e74c-eeb9-4f96-a60f-38c1c94e0a64 | AT33: No | AX33: Yes | AY33: No
A34: 45777 | B34: 204288821088966 | D34: 45769.683 | E34: delivered | F34: regular | J34: 1565 | K34: 20 | L34: 0 | M34: 0 | N34: 0 | O34: 1585 | P34: 79.26 | Q34: 1664.26 | R34: 1664.24 | S34: 0.1 | T34: 166.42 | U34: 0 | V34: 0 | W34: 0 | X34: 0 | Y34: 33.28 | Z34: 0 | AA34: 0 | AB34: 0 | AC34: 0 | AD34: 35.94 | AE34: 235.64 | AF34: 0 | AG34: 0 | AH34: 0 | AI34: 79.25 | AJ34: 0 | AK34: 1.58 | AL34: 80.83 | AM34: 1347.76 | AN34: No | AO34: 2.795 | AP34: Yes | AQ34: No | AS34: 96f74bff-5e8e-4571-9afb-f1fc59d437ff | AT34: No | AX34: Yes | AY34: No
A35: 45777 | B35: 204292365396131 | D35: 45769.724 | E35: delivered | F35: regular | J35: 575 | K35: 10 | L35: 0 | M35: 0 | N35: 0 | O35: 585 | P35: 29.26 | Q35: 614.26 | R35: 614.24 | S35: 0.1 | T35: 61.42 | U35: 0 | V35: 0 | W35: 0 | X35: 0 | Y35: 12.28 | Z35: 0 | AA35: 0 | AB35: 0 | AC35: 0 | AD35: 13.26 | AE35: 86.96 | AF35: 0 | AG35: 0 | AH35: 0 | AI35: 29.25 | AJ35: 0 | AK35: 0.58 | AL35: 29.83 | AM35: 497.44 | AN35: No | AO35: 6.702 | AP35: Yes | AQ35: No | AS35: 2487d21e-a744-4219-b261-ca894617d49f | AT35: No | AX35: Yes | AY35: No
A36: 45777 | B36: 204294771366388 | D36: 45769.752 | E36: delivered | F36: regular | J36: 160 | K36: 0 | L36: 0 | M36: 0 | N36: 0 | O36: 160 | P36: 8 | Q36: 168 | R36: 168 | S36: 0.1 | T36: 16.8 | U36: 0 | V36: 0 | W36: 0 | X36: 0 | Y36: 3.36 | Z36: 0 | AA36: 0 | AB36: 0 | AC36: 0 | AD36: 3.62 | AE36: 23.78 | AF36: 0 | AG36: 0 | AH36: 0 | AI36: 8 | AJ36: 0 | AK36: 0.16 | AL36: 8.16 | AM36: 136.04 | AN36: No | AO36: 0.745 | AP36: Yes | AQ36: No | AT36: No | AX36: Yes | AY36: No
A37: 45777 | B37: 204299841075979 | D37: 45769.811 | E37: delivered | F37: regular | J37: 575 | K37: 10 | L37: 0 | M37: 0 | N37: 0 | O37: 585 | P37: 29.26 | Q37: 614.26 | R37: 614.24 | S37: 0.1 | T37: 61.42 | U37: 0 | V37: 0 | W37: 0 | X37: 0 | Y37: 12.28 | Z37: 0 | AA37: 0 | AB37: 0 | AC37: 0 | AD37: 13.26 | AE37: 86.96 | AF37: 0 | AG37: 0 | AH37: 0 | AI37: 29.25 | AJ37: 0 | AK37: 0.58 | AL37: 29.83 | AM37: 497.44 | AN37: No | AO37: 0.746 | AP37: Yes | AQ37: No | AS37: 4499333e-583b-4762-9901-688a3746fa7e | AT37: No | AX37: Yes | AY37: No
A38: 45777 | B38: 204300656245087 | D38: 45769.82 | E38: delivered | F38: regular | J38: 965 | K38: 10 | L38: 0 | M38: 0 | N38: 0 | O38: 975 | P38: 48.76 | Q38: 1023.76 | R38: 1023.76 | S38: 0.1 | T38: 102.38 | U38: 0 | V38: 0 | W38: 0 | X38: 0 | Y38: 20.48 | Z38: 0 | AA38: 0 | AB38: 0 | AC38: 0 | AD38: 22.12 | AE38: 144.98 | AF38: 0 | AG38: 0 | AH38: 0 | AI38: 48.75 | AJ38: 0 | AK38: 0.97 | AL38: 49.72 | AM38: 829.06 | AN38: No | AO38: 0.841 | AP38: Yes | AQ38: No | AS38: 541de567-a020-484d-b77c-bad51ae0cfa9 | AT38: No | AX38: Yes | AY38: No
A39: 45777 | B39: 204303850607557 | D39: 45769.857 | E39: delivered | F39: regular | J39: 1490 | K39: 10 | L39: 0 | M39: 0 | N39: 0 | O39: 1500 | P39: 75 | Q39: 1575 | R39: 1575 | S39: 0.1 | T39: 157.5 | U39: 0 | V39: 0 | W39: 0 | X39: 0 | Y39: 31.5 | Z39: 0 | AA39: 0 | AB39: 0 | AC39: 0 | AD39: 34.02 | AE39: 223.02 | AF39: 0 | AG39: 0 | AH39: 0 | AI39: 75 | AJ39: 0 | AK39: 1.5 | AL39: 76.5 | AM39: 1275.48 | AN39: No | AO39: 1.451 | AP39: Yes | AQ39: No | AS39: fc926566-88f0-4dd4-b383-00ae35801ddb | AT39: No | AX39: Yes | AY39: No
A40: 45777 | B40: 204305353193813 | D40: 45769.874 | E40: delivered | F40: regular | I40: AXIS120 | J40: 575 | K40: 10 | L40: 0 | M40: 0 | N40: 0 | O40: 585 | P40: 29.26 | Q40: 614.26 | R40: 614.24 | S40: 0.1 | T40: 61.42 | U40: 0 | V40: 0 | W40: 0 | X40: 0 | Y40: 12.28 | Z40: 0 | AA40: 0 | AB40: 0 | AC40: 0 | AD40: 13.26 | AE40: 86.96 | AF40: 0 | AG40: 0 | AH40: 0 | AI40: 29.25 | AJ40: 0 | AK40: 0.58 | AL40: 29.83 | AM40: 497.44 | AN40: No | AO40: 0.651 | AP40: Yes | AQ40: No | AS40: 63a17ebb-dc25-49b0-80fe-70f5d9dc24cc,dd81fa81-54ee-4d25-a10a-f177fb52d3c5 | AT40: No | AX40: Yes | AY40: No
A41: 45777 | B41: 204359894567486 | D41: 45770.506 | E41: delivered | F41: regular | J41: 495 | K41: 10 | L41: 0 | M41: 0 | N41: 0 | O41: 505 | P41: 25.26 | Q41: 530.26 | R41: 530.24 | S41: 0.1 | T41: 53.02 | U41: 0 | V41: 0 | W41: 0 | X41: 0 | Y41: 10.6 | Z41: 0 | AA41: 0 | AB41: 0 | AC41: 0 | AD41: 11.46 | AE41: 75.08 | AF41: 0 | AG41: 0 | AH41: 0 | AI41: 25.25 | AJ41: 0 | AK41: 0.51 | AL41: 25.76 | AM41: 429.43 | AN41: No | AO41: 3.831 | AP41: Yes | AQ41: No | AT41: No | AX41: No | AY41: No
A42: 45777 | B42: 204361637504711 | D42: 45770.526 | E42: delivered | F42: regular | J42: 1050 | K42: 20 | L42: 0 | M42: 0 | N42: 0 | O42: 1070 | P42: 53.5 | Q42: 1123.5 | R42: 1123.5 | S42: 0.1 | T42: 112.35 | U42: 0 | V42: 0 | W42: 0 | X42: 0 | Y42: 22.47 | Z42: 0 | AA42: 0 | AB42: 0 | AC42: 0 | AD42: 24.26 | AE42: 159.08 | AF42: 0 | AG42: 0 | AH42: 0 | AI42: 53.5 | AJ42: 0 | AK42: 1.07 | AL42: 54.57 | AM42: 909.83 | AN42: No | AO42: 8.435 | AP42: Yes | AQ42: No | AS42: 118ef14f-05aa-4010-a2f6-a008746384db | AT42: No | AX42: No | AY42: No
A43: 45777 | B43: 204366702358606 | D43: 45770.585 | E43: delivered | F43: regular | J43: 815 | K43: 10 | L43: 0 | M43: 0 | N43: 0 | O43: 825 | P43: 41.26 | Q43: 866.26 | R43: 866.24 | S43: 0.1 | T43: 86.62 | U43: 0 | V43: 0 | W43: 0 | X43: 0 | Y43: 17.32 | Z43: 0 | AA43: 0 | AB43: 0 | AC43: 0 | AD43: 18.7 | AE43: 122.64 | AF43: 0 | AG43: 0 | AH43: 0 | AI43: 41.25 | AJ43: 0 | AK43: 0.83 | AL43: 42.08 | AM43: 701.52 | AN43: No | AO43: 0.815 | AP43: Yes | AQ43: No | AS43: f8fe01e5-662e-4644-baf6-92c03a6f52f2 | AT43: No | AX43: Yes | AY43: No
A44: 45777 | B44: 204367058136210 | D44: 45770.589 | E44: delivered | F44: regular | I44: APAYFEST | J44: 845 | K44: 10 | L44: 0 | M44: 0 | N44: 0 | O44: 855 | P44: 42.76 | Q44: 897.76 | R44: 897.76 | S44: 0.1 | T44: 89.78 | U44: 0 | V44: 0 | W44: 0 | X44: 0 | Y44: 17.96 | Z44: 0 | AA44: 0 | AB44: 0 | AC44: 0 | AD44: 19.4 | AE44: 127.14 | AF44: 0 | AG44: 0 | AH44: 0 | AI44: 42.75 | AJ44: 0 | AK44: 0.85 | AL44: 43.6 | AM44: 727.02 | AN44: No | AO44: 1.555 | AP44: Yes | AQ44: No | AT44: No | AX44: No | AY44: No
A45: 45777 | B45: 204381833273804 | D45: 45770.76 | E45: delivered | F45: regular | J45: 635 | K45: 10 | L45: 0 | M45: 0 | N45: 0 | O45: 645 | P45: 32.26 | Q45: 677.26 | R45: 677.24 | S45: 0.1 | T45: 67.72 | U45: 0 | V45: 0 | W45: 0 | X45: 0 | Y45: 13.54 | Z45: 0 | AA45: 0 | AB45: 0 | AC45: 0 | AD45: 14.62 | AE45: 95.88 | AF45: 0 | AG45: 0 | AH45: 0 | AI45: 32.25 | AJ45: 0 | AK45: 0.65 | AL45: 32.9 | AM45: 548.46 | AN45: No | AO45: 6.528 | AP45: Yes | AQ45: No | AS45: 6f4d7725-dab3-4496-8081-432387f8de29,5862cbfe-0ccd-4058-9b01-929069317251 | AT45: No | AX45: Yes | AY45: No
A46: 45777 | B46: 204383537632730 | D46: 45770.779 | E46: delivered | F46: regular | J46: 595 | K46: 10 | L46: 0 | M46: 0 | N46: 0 | O46: 605 | P46: 30.26 | Q46: 635.26 | R46: 635.24 | S46: 0.1 | T46: 63.52 | U46: 0 | V46: 0 | W46: 0 | X46: 0 | Y46: 12.7 | Z46: 0 | AA46: 0 | AB46: 0 | AC46: 0 | AD46: 13.72 | AE46: 89.94 | AF46: 0 | AG46: 0 | AH46: 0 | AI46: 30.25 | AJ46: 0 | AK46: 0.6 | AL46: 30.85 | AM46: 514.46 | AN46: No | AO46: 4.306 | AP46: Yes | AQ46: No | AS46: 3fc2d95a-588c-42b6-8b4f-20d1b3a8b343 | AT46: No | AX46: Yes | AY46: No
A47: 45777 | B47: 204383544317804 | D47: 45770.779 | E47: delivered | F47: regular | J47: 675 | K47: 10 | L47: 0 | M47: 0 | N47: 0 | O47: 685 | P47: 34.26 | Q47: 719.26 | R47: 719.24 | S47: 0.1 | T47: 71.92 | U47: 0 | V47: 0 | W47: 0 | X47: 0 | Y47: 14.38 | Z47: 0 | AA47: 0 | AB47: 0 | AC47: 0 | AD47: 15.54 | AE47: 101.84 | AF47: 0 | AG47: 0 | AH47: 0 | AI47: 34.25 | AJ47: 0 | AK47: 0.69 | AL47: 34.94 | AM47: 582.49 | AN47: No | AO47: 0.925 | AP47: Yes | AQ47: No | AS47: c0ed4dc5-d96a-452a-a03d-3f63c70ec49b | AT47: No | AX47: Yes | AY47: No
A48: 45777 | B48: 204383765079852 | D48: 45770.782 | E48: delivered | F48: regular | J48: 490 | K48: 10 | L48: 0 | M48: 0 | N48: 0 | O48: 500 | P48: 25 | Q48: 525 | R48: 525 | S48: 0.1 | T48: 52.5 | U48: 0 | V48: 0 | W48: 0 | X48: 0 | Y48: 10.5 | Z48: 0 | AA48: 0 | AB48: 0 | AC48: 0 | AD48: 11.34 | AE48: 74.34 | AF48: 0 | AG48: 0 | AH48: 0 | AI48: 25 | AJ48: 0 | AK48: 0.5 | AL48: 25.5 | AM48: 425.16 | AN48: No | AO48: 1.787 | AP48: Yes | AQ48: No | AS48: d8755106-c594-42af-83b3-d3aaa1f30811,78104d7c-7d71-4546-bda1-11b8faca7eb4 | AT48: No | AX48: Yes | AY48: No
A49: 45777 | B49: 204383873319990 | D49: 45770.783 | E49: delivered | F49: regular | J49: 625 | K49: 10 | L49: 0 | M49: 0 | N49: 0 | O49: 635 | P49: 31.76 | Q49: 666.76 | R49: 666.76 | S49: 0.1 | T49: 66.68 | U49: 0 | V49: 0 | W49: 0 | X49: 0 | Y49: 13.34 | Z49: 0 | AA49: 0 | AB49: 0 | AC49: 0 | AD49: 14.4 | AE49: 94.42 | AF49: 0 | AG49: 0 | AH49: 0 | AI49: 31.75 | AJ49: 0 | AK49: 0.64 | AL49: 32.39 | AM49: 539.94 | AN49: No | AO49: 3.164 | AP49: Yes | AQ49: No | AS49: 5e6c7a57-1da9-4c4a-aa6e-68f670d2fb8f | AT49: No | AX49: Yes | AY49: No
A50: 45777 | B50: 204384185156754 | D50: 45770.787 | E50: delivered | F50: regular | J50: 775 | K50: 10 | L50: 0 | M50: 0 | N50: 0 | O50: 785 | P50: 39.26 | Q50: 824.26 | R50: 824.24 | S50: 0.1 | T50: 82.42 | U50: 0 | V50: 0 | W50: 0 | X50: 0 | Y50: 16.48 | Z50: 0 | AA50: 0 | AB50: 0 | AC50: 0 | AD50: 17.8 | AE50: 116.7 | AF50: 0 | AG50: 0 | AH50: 0 | AI50: 39.25 | AJ50: 0 | AK50: 0.79 | AL50: 40.04 | AM50: 667.51 | AN50: No | AO50: 5.363 | AP50: Yes | AQ50: No | AS50: 78ea451d-4d30-4600-bfa9-eca1021eec94 | AT50: No | AX50: Yes | AY50: No
A51: 45777 | B51: 204385855697434 | D51: 45770.806 | E51: delivered | F51: regular | J51: 575 | K51: 10 | L51: 0 | M51: 0 | N51: 0 | O51: 585 | P51: 29.26 | Q51: 614.26 | R51: 614.24 | S51: 0.1 | T51: 61.42 | U51: 0 | V51: 0 | W51: 0 | X51: 0 | Y51: 12.28 | Z51: 0 | AA51: 0 | AB51: 0 | AC51: 0 | AD51: 13.26 | AE51: 86.96 | AF51: 0 | AG51: 0 | AH51: 0 | AI51: 29.25 | AJ51: 0 | AK51: 0.58 | AL51: 29.83 | AM51: 497.44 | AN51: No | AO51: 3.918 | AP51: Yes | AQ51: No | AS51: 98f8927b-40ae-4309-8dab-302fe487c277 | AT51: No | AX51: Yes | AY51: No
A52: 45777 | B52: 204386739344028 | D52: 45770.816 | E52: delivered | F52: regular | J52: 625 | K52: 10 | L52: 0 | M52: 0 | N52: 0 | O52: 635 | P52: 31.76 | Q52: 666.76 | R52: 666.76 | S52: 0.1 | T52: 66.68 | U52: 0 | V52: 0 | W52: 0 | X52: 0 | Y52: 13.34 | Z52: 0 | AA52: 0 | AB52: 0 | AC52: 0 | AD52: 14.4 | AE52: 94.42 | AF52: 0 | AG52: 0 | AH52: 0 | AI52: 31.75 | AJ52: 0 | AK52: 0.64 | AL52: 32.39 | AM52: 539.94 | AN52: No | AO52: 11.254 | AP52: Yes | AQ52: No | AT52: No | AX52: Yes | AY52: No
A53: 45777 | B53: 204388648675384 | D53: 45770.839 | E53: delivered | F53: regular | J53: 350 | K53: 0 | L53: 0 | M53: 0 | N53: 0 | O53: 350 | P53: 17.5 | Q53: 367.5 | R53: 367.5 | S53: 0.1 | T53: 36.75 | U53: 0 | V53: 0 | W53: 0 | X53: 0 | Y53: 7.35 | Z53: 0 | AA53: 0 | AB53: 0 | AC53: 0 | AD53: 7.94 | AE53: 52.04 | AF53: 0 | AG53: 0 | AH53: 0 | AI53: 17.5 | AJ53: 0 | AK53: 0.35 | AL53: 17.85 | AM53: 297.61 | AN53: No | AO53: 5.446 | AP53: Yes | AQ53: No | AS53: 5a28bb56-e22c-4d5f-912f-7e9be887a8fb | AT53: No | AX53: Yes | AY53: No
A54: 45777 | B54: 204390039914798 | D54: 45770.855 | E54: delivered | F54: regular | J54: 695 | K54: 10 | L54: 0 | M54: 0 | N54: 0 | O54: 705 | P54: 35.26 | Q54: 740.26 | R54: 740.24 | S54: 0.1 | T54: 74.02 | U54: 0 | V54: 0 | W54: 0 | X54: 0 | Y54: 14.8 | Z54: 0 | AA54: 0 | AB54: 0 | AC54: 0 | AD54: 15.98 | AE54: 104.8 | AF54: 0 | AG54: 0 | AH54: 0 | AI54: 35.25 | AJ54: 0 | AK54: 0.7 | AL54: 35.95 | AM54: 599.48 | AN54: No | AO54: 2.004 | AP54: Yes | AQ54: No | AS54: bcf8ddf2-0dd7-45f6-bb00-e654c5beba7d | AT54: No | AX54: Yes | AY54: No
A55: 45777 | B55: 204397084928030 | D55: 45770.936 | E55: delivered | F55: regular | I55: PNBCC125 | J55: 625 | K55: 10 | L55: 0 | M55: 0 | N55: 0 | O55: 635 | P55: 31.76 | Q55: 666.76 | R55: 666.76 | S55: 0.1 | T55: 66.68 | U55: 0 | V55: 0 | W55: 0 | X55: 0 | Y55: 13.34 | Z55: 0 | AA55: 0 | AB55: 0 | AC55: 0 | AD55: 14.4 | AE55: 94.42 | AF55: 0 | AG55: 0 | AH55: 0 | AI55: 31.75 | AJ55: 0 | AK55: 0.64 | AL55: 32.39 | AM55: 539.94 | AN55: No | AO55: 0.651 | AP55: Yes | AQ55: No | AS55: 63a17ebb-dc25-49b0-80fe-70f5d9dc24cc,dd81fa81-54ee-4d25-a10a-f177fb52d3c5 | AT55: No | AX55: Yes | AY55: No
A56: 45777 | B56: 204446834613113 | D56: 45771.512 | E56: delivered | F56: regular | J56: 850 | K56: 10 | L56: 0 | M56: 0 | N56: 0 | O56: 860 | P56: 43 | Q56: 903 | R56: 903 | S56: 0.1 | T56: 90.3 | U56: 0 | V56: 0 | W56: 0 | X56: 0 | Y56: 18.06 | Z56: 0 | AA56: 0 | AB56: 0 | AC56: 0 | AD56: 19.5 | AE56: 127.86 | AF56: 0 | AG56: 0 | AH56: 0 | AI56: 43 | AJ56: 0 | AK56: 0.86 | AL56: 43.86 | AM56: 731.28 | AN56: No | AO56: 6.411 | AP56: Yes | AQ56: No | AT56: No | AX56: No | AY56: No
A57: 45777 | B57: 204463308717339 | D57: 45771.703 | E57: delivered | F57: regular | J57: 850 | K57: 10 | L57: 0 | M57: 0 | N57: 0 | O57: 860 | P57: 43 | Q57: 903 | R57: 903 | S57: 0.1 | T57: 90.3 | U57: 0 | V57: 0 | W57: 0 | X57: 0 | Y57: 18.06 | Z57: 0 | AA57: 0 | AB57: 0 | AC57: 0 | AD57: 19.5 | AE57: 127.86 | AF57: 0 | AG57: 0 | AH57: 0 | AI57: 43 | AJ57: 0 | AK57: 0.86 | AL57: 43.86 | AM57: 731.28 | AN57: No | AO57: 11.067 | AP57: Yes | AQ57: No | AS57: e8644b64-cddb-402d-9a4c-ed66b27edbe0 | AT57: No | AX57: No | AY57: No
A58: 45777 | B58: 204468550764975 | D58: 45771.763 | E58: delivered | F58: regular | I58: AXIS120 | J58: 750 | K58: 10 | L58: 0 | M58: 0 | N58: 0 | O58: 760 | P58: 38 | Q58: 798 | R58: 798 | S58: 0.1 | T58: 79.8 | U58: 0 | V58: 0 | W58: 0 | X58: 0 | Y58: 15.96 | Z58: 0 | AA58: 0 | AB58: 0 | AC58: 0 | AD58: 17.24 | AE58: 113 | AF58: 0 | AG58: 0 | AH58: 0 | AI58: 38 | AJ58: 0 | AK58: 0.76 | AL58: 38.76 | AM58: 646.24 | AN58: No | AO58: 0.694 | AP58: Yes | AQ58: No | AS58: db2ebb10-8c7f-40f4-a0e3-4179ee1fb8e7 | AT58: No | AX58: Yes | AY58: No
A59: 45777 | B59: 204472510573544 | D59: 45771.809 | E59: delivered | F59: regular | J59: 575 | K59: 10 | L59: 0 | M59: 0 | N59: 0 | O59: 585 | P59: 29.26 | Q59: 614.26 | R59: 614.24 | S59: 0.1 | T59: 61.42 | U59: 0 | V59: 0 | W59: 0 | X59: 0 | Y59: 12.28 | Z59: 0 | AA59: 0 | AB59: 0 | AC59: 0 | AD59: 13.26 | AE59: 86.96 | AF59: 0 | AG59: 0 | AH59: 0 | AI59: 29.25 | AJ59: 0 | AK59: 0.58 | AL59: 29.83 | AM59: 497.44 | AN59: No | AO59: 5.962 | AP59: Yes | AQ59: No | AS59: aa41814f-78bf-4174-b095-60cecb61c908 | AT59: No | AX59: Yes | AY59: No
A60: 45777 | B60: 204474748775180 | D60: 45771.835 | E60: delivered | F60: regular | J60: 750 | K60: 10 | L60: 0 | M60: 0 | N60: 0 | O60: 760 | P60: 38 | Q60: 798 | R60: 798 | S60: 0.1 | T60: 79.8 | U60: 0 | V60: 0 | W60: 0 | X60: 0 | Y60: 15.96 | Z60: 0 | AA60: 0 | AB60: 0 | AC60: 0 | AD60: 17.24 | AE60: 113 | AF60: 0 | AG60: 0 | AH60: 0 | AI60: 38 | AJ60: 0 | AK60: 0.76 | AL60: 38.76 | AM60: 646.24 | AN60: No | AO60: 6.628 | AP60: Yes | AQ60: No | AS60: 58da1cb1-f081-4a98-867b-11cf1f3ced04 | AT60: No | AX60: Yes | AY60: No
A61: 45777 | B61: 204476158750656 | D61: 45771.851 | E61: delivered | F61: regular | J61: 750 | K61: 10 | L61: 0 | M61: 0 | N61: 0 | O61: 760 | P61: 38 | Q61: 798 | R61: 798 | S61: 0.1 | T61: 79.8 | U61: 0 | V61: 0 | W61: 0 | X61: 0 | Y61: 15.96 | Z61: 0 | AA61: 0 | AB61: 0 | AC61: 0 | AD61: 17.24 | AE61: 113 | AF61: 0 | AG61: 0 | AH61: 0 | AI61: 38 | AJ61: 0 | AK61: 0.76 | AL61: 38.76 | AM61: 646.24 | AN61: No | AO61: 0.777 | AP61: Yes | AQ61: No | AS61: 2852fd70-a715-4a3a-b53e-78b01b071e82 | AT61: No | AX61: Yes | AY61: No
A62: 45777 | B62: 204479499552477 | D62: 45771.89 | E62: delivered | F62: regular | J62: 2015 | K62: 20 | L62: 0 | M62: 0 | N62: 0 | O62: 2035 | P62: 101.76 | Q62: 2136.76 | R62: 2136.76 | S62: 0.1 | T62: 213.68 | U62: 0 | V62: 0 | W62: 0 | X62: 0 | Y62: 42.74 | Z62: 0 | AA62: 0 | AB62: 0 | AC62: 0 | AD62: 46.16 | AE62: 302.58 | AF62: 0 | AG62: 0 | AH62: 0 | AI62: 101.75 | AJ62: 0 | AK62: 2.04 | AL62: 103.79 | AM62: 1730.39 | AN62: No | AO62: 1.555 | AP62: Yes | AQ62: No | AS62: afbd0f65-b503-4eb2-b645-6708b0ebf4b3,a0eadc79-7a6b-4925-b5dc-70f264a12a52 | AT62: No | AX62: Yes | AY62: No
A63: 45777 | B63: 204482779724792 | D63: 45771.928 | E63: delivered | F63: regular | J63: 1350 | K63: 20 | L63: 0 | M63: 0 | N63: 0 | O63: 1370 | P63: 68.5 | Q63: 1438.5 | R63: 1438.5 | S63: 0.1 | T63: 143.85 | U63: 0 | V63: 0 | W63: 0 | X63: 0 | Y63: 28.77 | Z63: 0 | AA63: 0 | AB63: 0 | AC63: 0 | AD63: 31.08 | AE63: 203.7 | AF63: 0 | AG63: 0 | AH63: 0 | AI63: 68.5 | AJ63: 0 | AK63: 1.37 | AL63: 69.87 | AM63: 1164.95 | AN63: No | AO63: 3.721 | AP63: Yes | AQ63: No | AS63: 844fcc6d-a59f-4ce5-846b-d635b49ffdb4,d2677200-233f-4bf2-bed2-6b0b174cd8bc | AT63: No | AX63: Yes | AY63: No
A64: 45777 | B64: 204558048502256 | D64: 45772.799 | E64: delivered | F64: regular | J64: 1100 | K64: 20 | L64: 0 | M64: 0 | N64: 0 | O64: 1120 | P64: 56 | Q64: 1176 | R64: 1176 | S64: 0.1 | T64: 117.6 | U64: 0 | V64: 0 | W64: 0 | X64: 0 | Y64: 23.52 | Z64: 0 | AA64: 0 | AB64: 0 | AC64: 0 | AD64: 25.4 | AE64: 166.52 | AF64: 0 | AG64: 0 | AH64: 0 | AI64: 56 | AJ64: 0 | AK64: 1.12 | AL64: 57.12 | AM64: 952.36 | AN64: No | AO64: 3.022 | AP64: Yes | AQ64: No | AS64: ed87e74c-eeb9-4f96-a60f-38c1c94e0a64 | AT64: No | AX64: Yes | AY64: No
A65: 45777 | B65: 204558947155827 | D65: 45772.81 | E65: delivered | F65: regular | J65: 380 | K65: 0 | L65: 0 | M65: 0 | N65: 0 | O65: 380 | P65: 19 | Q65: 399 | R65: 399 | S65: 0.1 | T65: 39.9 | U65: 0 | V65: 0 | W65: 0 | X65: 0 | Y65: 7.98 | Z65: 0 | AA65: 0 | AB65: 0 | AC65: 0 | AD65: 8.62 | AE65: 56.5 | AF65: 0 | AG65: 0 | AH65: 0 | AI65: 19 | AJ65: 0 | AK65: 0.38 | AL65: 19.38 | AM65: 323.12 | AN65: No | AO65: 2.964 | AP65: Yes | AQ65: No | AS65: 60be9fdd-ee4b-4899-8769-18142ddc7f6e | AT65: No | AX65: Yes | AY65: No
A66: 45777 | B66: 204559154889387 | D66: 45772.812 | E66: delivered | F66: regular | I66: FEDERALCC150 | J66: 1705 | K66: 30 | L66: 0 | M66: 0 | N66: 0 | O66: 1735 | P66: 86.76 | Q66: 1821.76 | R66: 1821.76 | S66: 0.1 | T66: 182.18 | U66: 0 | V66: 0 | W66: 0 | X66: 0 | Y66: 36.44 | Z66: 0 | AA66: 0 | AB66: 0 | AC66: 0 | AD66: 39.36 | AE66: 257.98 | AF66: 0 | AG66: 0 | AH66: 0 | AI66: 86.75 | AJ66: 0 | AK66: 1.74 | AL66: 88.49 | AM66: 1475.3 | AN66: No | AO66: 6.589 | AP66: Yes | AQ66: No | AS66: 8dfdd3ba-1ab7-4cee-b82b-bf896ce35bad | AT66: No | AX66: No | AY66: No
A67: 45777 | B67: 204561278937219 | D67: 45772.837 | E67: delivered | F67: regular | J67: 570 | K67: 0 | L67: 0 | M67: 0 | N67: 0 | O67: 570 | P67: 28.5 | Q67: 598.5 | R67: 598.5 | S67: 0.1 | T67: 59.85 | U67: 0 | V67: 0 | W67: 0 | X67: 0 | Y67: 11.97 | Z67: 0 | AA67: 0 | AB67: 0 | AC67: 0 | AD67: 12.92 | AE67: 84.74 | AF67: 0 | AG67: 0 | AH67: 0 | AI67: 28.5 | AJ67: 0 | AK67: 0.57 | AL67: 29.07 | AM67: 484.67 | AN67: No | AO67: 6.844 | AP67: Yes | AQ67: No | AS67: 528a5933-8df9-40c0-99a7-e331c5929152 | AT67: No | AX67: Yes | AY67: No
A68: 45777 | B68: 204565890938565 | D68: 45772.89 | E68: delivered | F68: regular | J68: 625 | K68: 10 | L68: 0 | M68: 0 | N68: 0 | O68: 635 | P68: 31.76 | Q68: 666.76 | R68: 666.76 | S68: 0.1 | T68: 66.68 | U68: 0 | V68: 0 | W68: 0 | X68: 0 | Y68: 13.34 | Z68: 0 | AA68: 0 | AB68: 0 | AC68: 0 | AD68: 14.4 | AE68: 94.42 | AF68: 0 | AG68: 0 | AH68: 0 | AI68: 31.75 | AJ68: 0 | AK68: 0.64 | AL68: 32.39 | AM68: 539.94 | AN68: No | AO68: 1.621 | AP68: Yes | AQ68: No | AS68: 5e74bcf6-36df-43e9-9a0d-a4d22ea7b7cb | AT68: No | AX68: Yes | AY68: No
A69: 45777 | B69: 204622634805390 | D69: 45773.547 | E69: delivered | F69: regular | J69: 1010 | K69: 10 | L69: 0 | M69: 0 | N69: 0 | O69: 1020 | P69: 51 | Q69: 1071 | R69: 1071 | S69: 0.1 | T69: 107.1 | U69: 0 | V69: 0 | W69: 0 | X69: 0 | Y69: 21.42 | Z69: 0 | AA69: 0 | AB69: 0 | AC69: 0 | AD69: 23.14 | AE69: 151.66 | AF69: 0 | AG69: 0 | AH69: 0 | AI69: 51 | AJ69: 0 | AK69: 1.02 | AL69: 52.02 | AM69: 867.34 | AN69: No | AO69: 1.555 | AP69: Yes | AQ69: No | AS69: a288f834-77d9-4c40-8115-54c6559224b0 | AT69: No | AX69: Yes | AY69: No
A70: 45777 | B70: 204631797271980 | D70: 45773.653 | E70: delivered | F70: regular | I70: AMEX150 | J70: 850 | K70: 10 | L70: 0 | M70: 0 | N70: 0 | O70: 860 | P70: 43 | Q70: 903 | R70: 903 | S70: 0.1 | T70: 90.3 | U70: 0 | V70: 0 | W70: 0 | X70: 0 | Y70: 18.06 | Z70: 0 | AA70: 0 | AB70: 0 | AC70: 0 | AD70: 19.5 | AE70: 127.86 | AF70: 0 | AG70: 0 | AH70: 0 | AI70: 43 | AJ70: 0 | AK70: 0.86 | AL70: 43.86 | AM70: 731.28 | AN70: No | AO70: 4.361 | AP70: Yes | AQ70: No | AS70: e923bca6-dac7-4489-99cd-1b60ca87157d | AT70: No | AX70: Yes | AY70: No
A71: 45777 | B71: 204636040412270 | D71: 45773.702 | E71: delivered | F71: regular | J71: 1300 | K71: 20 | L71: 0 | M71: 0 | N71: 0 | O71: 1320 | P71: 66 | Q71: 1386 | R71: 1386 | S71: 0.1 | T71: 138.6 | U71: 0 | V71: 0 | W71: 0 | X71: 0 | Y71: 27.72 | Z71: 0 | AA71: 0 | AB71: 0 | AC71: 0 | AD71: 29.94 | AE71: 196.26 | AF71: 0 | AG71: 0 | AH71: 0 | AI71: 66 | AJ71: 0 | AK71: 1.32 | AL71: 67.32 | AM71: 1122.42 | AN71: No | AO71: 11.287 | AP71: Yes | AQ71: No | AT71: No | AX71: Yes | AY71: No
A72: 45777 | B72: 204639269706561 | D72: 45773.739 | E72: delivered | F72: regular | J72: 725 | K72: 10 | L72: 0 | M72: 0 | N72: 0 | O72: 735 | P72: 36.76 | Q72: 771.76 | R72: 771.76 | S72: 0.1 | T72: 77.18 | U72: 0 | V72: 0 | W72: 0 | X72: 0 | Y72: 15.44 | Z72: 0 | AA72: 0 | AB72: 0 | AC72: 0 | AD72: 16.68 | AE72: 109.3 | AF72: 0 | AG72: 0 | AH72: 0 | AI72: 36.75 | AJ72: 0 | AK72: 0.73 | AL72: 37.48 | AM72: 624.98 | AN72: No | AO72: 1.726 | AP72: Yes | AQ72: No | AS72: 16ba7efa-5742-43de-b8b5-fb89beb98004 | AT72: No | AX72: Yes | AY72: No
A73: 45777 | B73: 204642526185227 | D73: 45773.777 | E73: delivered | F73: regular | J73: 475 | K73: 10 | L73: 0 | M73: 0 | N73: 0 | O73: 485 | P73: 24.26 | Q73: 509.26 | R73: 509.24 | S73: 0.1 | T73: 50.92 | U73: 0 | V73: 0 | W73: 0 | X73: 0 | Y73: 10.18 | Z73: 0 | AA73: 0 | AB73: 0 | AC73: 0 | AD73: 11 | AE73: 72.1 | AF73: 0 | AG73: 0 | AH73: 0 | AI73: 24.25 | AJ73: 0 | AK73: 0.48 | AL73: 24.73 | AM73: 412.42 | AN73: No | AO73: 12.655 | AP73: Yes | AQ73: No | AT73: No | AX73: Yes | AY73: No
A74: 45777 | B74: 204648498429964 | D74: 45773.846 | E74: delivered | F74: regular | J74: 1370 | K74: 20 | L74: 0 | M74: 0 | N74: 0 | O74: 1390 | P74: 69.5 | Q74: 1459.5 | R74: 1459.5 | S74: 0.1 | T74: 145.95 | U74: 0 | V74: 0 | W74: 0 | X74: 0 | Y74: 29.19 | Z74: 0 | AA74: 0 | AB74: 0 | AC74: 0 | AD74: 31.52 | AE74: 206.66 | AF74: 0 | AG74: 0 | AH74: 0 | AI74: 69.5 | AJ74: 0 | AK74: 1.39 | AL74: 70.89 | AM74: 1181.93 | AN74: No | AO74: 13.116 | AP74: Yes | AQ74: No | AT74: No | AX74: Yes | AY74: No
A75: 45777 | B75: 204649345151698 | D75: 45773.856 | E75: delivered | F75: regular | J75: 1450 | K75: 20 | L75: 0 | M75: 0 | N75: 0 | O75: 1470 | P75: 73.5 | Q75: 1543.5 | R75: 1543.5 | S75: 0.1 | T75: 154.35 | U75: 0 | V75: 0 | W75: 0 | X75: 0 | Y75: 30.87 | Z75: 0 | AA75: 0 | AB75: 0 | AC75: 0 | AD75: 33.34 | AE75: 218.56 | AF75: 0 | AG75: 0 | AH75: 0 | AI75: 73.5 | AJ75: 0 | AK75: 1.47 | AL75: 74.97 | AM75: 1249.97 | AN75: No | AO75: 6.733 | AP75: Yes | AQ75: No | AS75: 6c73bb8f-72f8-48ff-bda9-5808e793919a | AT75: No | AX75: Yes | AY75: No
A76: 45777 | B76: 204649360253678 | D76: 45773.856 | E76: delivered | F76: regular | J76: 1040 | K76: 0 | L76: 0 | M76: 0 | N76: 0 | O76: 1040 | P76: 52 | Q76: 1092 | R76: 1092 | S76: 0.1 | T76: 109.2 | U76: 0 | V76: 0 | W76: 0 | X76: 0 | Y76: 21.84 | Z76: 0 | AA76: 0 | AB76: 0 | AC76: 0 | AD76: 23.58 | AE76: 154.62 | AF76: 0 | AG76: 0 | AH76: 0 | AI76: 52 | AJ76: 0 | AK76: 1.04 | AL76: 53.04 | AM76: 884.32 | AN76: No | AO76: 5.765 | AP76: Yes | AQ76: No | AS76: 200b14f4-5d71-4315-804e-05d4590e00d2 | AT76: No | AX76: Yes | AY76: No
A77: 45777 | B77: 204650646695434 | D77: 45773.871 | E77: delivered | F77: regular | J77: 2030 | K77: 10 | L77: 0 | M77: 0 | N77: 0 | O77: 2040 | P77: 102 | Q77: 2142 | R77: 2142 | S77: 0.1 | T77: 214.2 | U77: 0 | V77: 0 | W77: 0 | X77: 0 | Y77: 42.84 | Z77: 0 | AA77: 0 | AB77: 0 | AC77: 0 | AD77: 46.26 | AE77: 303.3 | AF77: 0 | AG77: 0 | AH77: 0 | AI77: 102 | AJ77: 0 | AK77: 2.04 | AL77: 104.04 | AM77: 1734.64 | AN77: No | AO77: 10.996 | AP77: Yes | AQ77: No | AT77: No | AX77: Yes | AY77: No
A78: 45777 | B78: 204650871018646 | D78: 45773.874 | E78: delivered | F78: regular | J78: 575 | K78: 10 | L78: 0 | M78: 0 | N78: 0 | O78: 585 | P78: 29.26 | Q78: 614.26 | R78: 614.24 | S78: 0.1 | T78: 61.42 | U78: 0 | V78: 0 | W78: 0 | X78: 0 | Y78: 12.28 | Z78: 0 | AA78: 0 | AB78: 0 | AC78: 0 | AD78: 13.26 | AE78: 86.96 | AF78: 0 | AG78: 0 | AH78: 0 | AI78: 29.25 | AJ78: 0 | AK78: 0.58 | AL78: 29.83 | AM78: 497.44 | AN78: No | AO78: 3.03 | AP78: Yes | AQ78: No | AS78: 7793b017-3e64-42ec-ac40-b296f751eb1b | AT78: No | AX78: Yes | AY78: No
A79: 45782 | B79: 204709933377978 | D79: 45774.557 | E79: delivered | F79: regular | J79: 1475 | K79: 10 | L79: 0 | M79: 0 | N79: 0 | O79: 1485 | P79: 74.26 | Q79: 1559.26 | R79: 1559.24 | S79: 0.1 | T79: 155.92 | U79: 0 | V79: 0 | W79: 0 | X79: 0 | Y79: 31.18 | Z79: 0 | AA79: 0 | AB79: 0 | AC79: 0 | AD79: 33.68 | AE79: 220.78 | AF79: 0 | AG79: 0 | AH79: 0 | AI79: 74.25 | AJ79: 0 | AK79: 1.49 | AL79: 75.74 | AM79: 1262.74 | AN79: No | AO79: 6.101 | AP79: Yes | AQ79: No | AS79: 4e51ece0-d129-4df3-8e9f-9e73cd241e3f,19aed996-6048-4b10-90d9-3abd207c014f | AT79: No | AX79: Yes | AY79: No
A80: 45782 | B80: 204722108011096 | D80: 45774.698 | E80: delivered | F80: regular | J80: 575 | K80: 10 | L80: 0 | M80: 0 | N80: 0 | O80: 585 | P80: 29.26 | Q80: 614.26 | R80: 614.24 | S80: 0.1 | T80: 61.42 | U80: 0 | V80: 0 | W80: 0 | X80: 0 | Y80: 12.28 | Z80: 0 | AA80: 0 | AB80: 0 | AC80: 0 | AD80: 13.26 | AE80: 86.96 | AF80: 0 | AG80: 0 | AH80: 0 | AI80: 29.25 | AJ80: 0 | AK80: 0.58 | AL80: 29.83 | AM80: 497.44 | AN80: No | AO80: 0.785 | AP80: Yes | AQ80: No | AS80: 99e14625-b48f-4bd8-866a-17aa4cb76d44 | AT80: No | AX80: Yes | AY80: No
A81: 45782 | B81: 204724969773033 | D81: 45774.731 | E81: delivered | F81: regular | J81: 1280 | K81: 10 | L81: 0 | M81: 0 | N81: 0 | O81: 1290 | P81: 64.5 | Q81: 1354.5 | R81: 1354.5 | S81: 0.1 | T81: 135.45 | U81: 0 | V81: 0 | W81: 0 | X81: 0 | Y81: 27.09 | Z81: 0 | AA81: 0 | AB81: 0 | AC81: 0 | AD81: 29.26 | AE81: 191.8 | AF81: 0 | AG81: 0 | AH81: 0 | AI81: 64.5 | AJ81: 0 | AK81: 1.29 | AL81: 65.79 | AM81: 1096.91 | AN81: No | AO81: 5.959 | AP81: Yes | AQ81: No | AS81: 48fee9d4-386f-4a34-be78-d1a2b29b2651 | AT81: No | AX81: Yes | AY81: No
A82: 45782 | B82: 204730231518825 | D82: 45774.792 | E82: delivered | F82: regular | J82: 475 | K82: 10 | L82: 0 | M82: 0 | N82: 0 | O82: 485 | P82: 24.26 | Q82: 509.26 | R82: 509.24 | S82: 0.1 | T82: 50.92 | U82: 0 | V82: 0 | W82: 0 | X82: 0 | Y82: 10.18 | Z82: 0 | AA82: 0 | AB82: 0 | AC82: 0 | AD82: 11 | AE82: 72.1 | AF82: 0 | AG82: 0 | AH82: 0 | AI82: 24.25 | AJ82: 0 | AK82: 0.48 | AL82: 24.73 | AM82: 412.42 | AN82: No | AO82: 0.638 | AP82: Yes | AQ82: No | AT82: No | AX82: No | AY82: No
A83: 45782 | B83: 204791947854122 | D83: 45775.506 | E83: delivered | F83: regular | J83: 2875 | K83: 50 | L83: 0 | M83: 0 | N83: 0 | O83: 2925 | P83: 146.26 | Q83: 3071.26 | R83: 3071.24 | S83: 0.1 | T83: 307.12 | U83: 0 | V83: 0 | W83: 0 | X83: 0 | Y83: 61.42 | Z83: 0 | AA83: 0 | AB83: 0 | AC83: 0 | AD83: 66.34 | AE83: 434.88 | AF83: 0 | AG83: 0 | AH83: 0 | AI83: 146.25 | AJ83: 0 | AK83: 2.93 | AL83: 149.18 | AM83: 2487.2 | AN83: No | AO83: 3.739 | AP83: No | AQ83: No | AS83: 41862eed-5bf7-42fb-a358-3ca68ffb0761 | AT83: No | AX83: Yes | AY83: No
A84: 45782 | B84: 204827953081349 | D84: 45775.923 | E84: delivered | F84: regular | J84: 675 | K84: 10 | L84: 0 | M84: 0 | N84: 0 | O84: 685 | P84: 34.26 | Q84: 719.26 | R84: 719.24 | S84: 0.1 | T84: 71.92 | U84: 0 | V84: 0 | W84: 0 | X84: 0 | Y84: 14.38 | Z84: 0 | AA84: 0 | AB84: 0 | AC84: 0 | AD84: 15.54 | AE84: 101.84 | AF84: 0 | AG84: 0 | AH84: 0 | AI84: 34.25 | AJ84: 0 | AK84: 0.69 | AL84: 34.94 | AM84: 582.49 | AN84: No | AO84: 1.802 | AP84: No | AQ84: No | AS84: 16ba7efa-5742-43de-b8b5-fb89beb98004 | AT84: No | AX84: Yes | AY84: No
A85: 45782 | B85: 204903634665309 | D85: 45776.799 | E85: delivered | F85: regular | J85: 490 | K85: 10 | L85: 0 | M85: 0 | N85: 0 | O85: 500 | P85: 25 | Q85: 525 | R85: 525 | S85: 0.1 | T85: 52.5 | U85: 0 | V85: 0 | W85: 0 | X85: 0 | Y85: 10.5 | Z85: 0 | AA85: 0 | AB85: 0 | AC85: 0 | AD85: 11.34 | AE85: 74.34 | AF85: 0 | AG85: 0 | AH85: 0 | AI85: 25 | AJ85: 0 | AK85: 0.5 | AL85: 25.5 | AM85: 425.16 | AN85: No | AO85: 1.951 | AP85: No | AQ85: No | AS85: ff9fbdab-3f9d-414d-82e8-b0551e8d2061 | AT85: No | AX85: Yes | AY85: No
A86: 45782 | B86: 204904327438482 | D86: 45776.807 | E86: delivered | F86: regular | J86: 380 | K86: 0 | L86: 0 | M86: 0 | N86: 0 | O86: 380 | P86: 19 | Q86: 399 | R86: 399 | S86: 0.1 | T86: 39.9 | U86: 0 | V86: 0 | W86: 0 | X86: 0 | Y86: 7.98 | Z86: 0 | AA86: 0 | AB86: 0 | AC86: 0 | AD86: 8.62 | AE86: 56.5 | AF86: 0 | AG86: 0 | AH86: 0 | AI86: 19 | AJ86: 0 | AK86: 0.38 | AL86: 19.38 | AM86: 323.12 | AN86: No | AO86: 2.803 | AP86: No | AQ86: No | AS86: 96f74bff-5e8e-4571-9afb-f1fc59d437ff | AT86: No | AX86: Yes | AY86: No
A87: 45782 | B87: 204911523747820 | D87: 45776.89 | E87: delivered | F87: regular | J87: 1210 | K87: 0 | L87: 0 | M87: 0 | N87: 0 | O87: 1210 | P87: 60.5 | Q87: 1270.5 | R87: 1270.5 | S87: 0.1 | T87: 127.05 | U87: 0 | V87: 0 | W87: 0 | X87: 0 | Y87: 25.41 | Z87: 0 | AA87: 0 | AB87: 0 | AC87: 0 | AD87: 27.44 | AE87: 179.9 | AF87: 0 | AG87: 0 | AH87: 0 | AI87: 60.5 | AJ87: 0 | AK87: 1.21 | AL87: 61.71 | AM87: 1028.89 | AN87: No | AO87: 1.802 | AP87: No | AQ87: No | AS87: 16ba7efa-5742-43de-b8b5-fb89beb98004 | AT87: No | AX87: Yes | AY87: No
A88: 45782 | B88: 204914721836186 | D88: 45776.927 | E88: delivered | F88: regular | J88: 1420 | K88: 0 | L88: 0 | M88: 0 | N88: 0 | O88: 1420 | P88: 71 | Q88: 1491 | R88: 1491 | S88: 0.1 | T88: 149.1 | U88: 0 | V88: 0 | W88: 0 | X88: 0 | Y88: 29.82 | Z88: 0 | AA88: 0 | AB88: 0 | AC88: 0 | AD88: 32.2 | AE88: 211.12 | AF88: 0 | AG88: 0 | AH88: 0 | AI88: 71 | AJ88: 0 | AK88: 1.42 | AL88: 72.42 | AM88: 1207.44 | AN88: No | AO88: 1.451 | AP88: No | AQ88: No | AS88: cb847266-a56f-4c4c-83a6-cf74f33d8a1c | AT88: No | AX88: Yes | AY88: No
A89: 45782 | B89: 204980957551815 | D89: 45777.694 | E89: delivered | F89: regular | J89: 725 | K89: 10 | L89: 0 | M89: 0 | N89: 0 | O89: 735 | P89: 36.76 | Q89: 771.76 | R89: 771.76 | S89: 0.1 | T89: 77.18 | U89: 0 | V89: 0 | W89: 0 | X89: 0 | Y89: 15.44 | Z89: 0 | AA89: 0 | AB89: 0 | AC89: 0 | AD89: 16.68 | AE89: 109.3 | AF89: 0 | AG89: 0 | AH89: 0 | AI89: 36.75 | AJ89: 0 | AK89: 0.73 | AL89: 37.48 | AM89: 624.98 | AN89: No | AO89: 6.328 | AP89: No | AQ89: No | AT89: No | AX89: No | AY89: No
A90: 45782 | B90: 204984443691974 | D90: 45777.734 | E90: delivered | F90: regular | J90: 750 | K90: 10 | L90: 0 | M90: 0 | N90: 0 | O90: 760 | P90: 38 | Q90: 798 | R90: 798 | S90: 0.1 | T90: 79.8 | U90: 0 | V90: 0 | W90: 0 | X90: 0 | Y90: 15.96 | Z90: 0 | AA90: 0 | AB90: 0 | AC90: 0 | AD90: 17.24 | AE90: 113 | AF90: 0 | AG90: 0 | AH90: 0 | AI90: 38 | AJ90: 0 | AK90: 0.76 | AL90: 38.76 | AM90: 646.24 | AN90: No | AO90: 3.421 | AP90: No | AQ90: No | AS90: 5e6c7a57-1da9-4c4a-aa6e-68f670d2fb8f | AT90: No | AX90: Yes | AY90: No
A91: 45782 | B91: 204986998231753 | D91: 45777.764 | E91: delivered | F91: regular | J91: 1185 | K91: 10 | L91: 0 | M91: 0 | N91: 0 | O91: 1195 | P91: 59.76 | Q91: 1254.76 | R91: 1254.76 | S91: 0.1 | T91: 125.48 | U91: 0 | V91: 0 | W91: 0 | X91: 0 | Y91: 25.1 | Z91: 0 | AA91: 0 | AB91: 0 | AC91: 0 | AD91: 27.1 | AE91: 177.68 | AF91: 0 | AG91: 0 | AH91: 0 | AI91: 59.75 | AJ91: 0 | AK91: 1.2 | AL91: 60.95 | AM91: 1016.12 | AN91: No | AO91: 1.311 | AP91: No | AQ91: No | AS91: 639465c1-9b88-42a2-8860-12f1f56fa2c3 | AT91: No | AX91: Yes | AY91: No
A92: 45782 | B92: 204988498603609 | D92: 45777.781 | E92: delivered | F92: regular | J92: 525 | K92: 0 | L92: 0 | M92: 0 | N92: 0 | O92: 525 | P92: 26.26 | Q92: 551.26 | R92: 551.24 | S92: 0.1 | T92: 55.12 | U92: 0 | V92: 0 | W92: 0 | X92: 0 | Y92: 11.02 | Z92: 0 | AA92: 0 | AB92: 0 | AC92: 0 | AD92: 11.9 | AE92: 78.04 | AF92: 0 | AG92: 0 | AH92: 0 | AI92: 26.25 | AJ92: 0 | AK92: 0.53 | AL92: 26.78 | AM92: 446.42 | AN92: No | AO92: 6.283 | AP92: No | AQ92: No | AS92: 320d299d-cd09-4ee6-8c85-547d617ebd5f,b0917622-678d-4294-b191-93716506a457 | AT92: No | AX92: Yes | AY92: No
A93: 45782 | B93: 204988734305065 | D93: 45777.784 | E93: delivered | F93: regular | J93: 475 | K93: 10 | L93: 0 | M93: 0 | N93: 0 | O93: 485 | P93: 24.26 | Q93: 509.26 | R93: 509.24 | S93: 0.1 | T93: 50.92 | U93: 0 | V93: 0 | W93: 0 | X93: 0 | Y93: 10.18 | Z93: 0 | AA93: 0 | AB93: 0 | AC93: 0 | AD93: 11 | AE93: 72.1 | AF93: 0 | AG93: 0 | AH93: 0 | AI93: 24.25 | AJ93: 0 | AK93: 0.48 | AL93: 24.73 | AM93: 412.42 | AN93: No | AO93: 1.903 | AP93: No | AQ93: No | AS93: d8755106-c594-42af-83b3-d3aaa1f30811,78104d7c-7d71-4546-bda1-11b8faca7eb4 | AT93: No | AX93: Yes | AY93: No
A94: 45782 | B94: 204994912053171 | D94: 45777.855 | E94: delivered | F94: regular | I94: AXIS200 | J94: 1350 | K94: 20 | L94: 0 | M94: 0 | N94: 0 | O94: 1370 | P94: 68.5 | Q94: 1438.5 | R94: 1438.5 | S94: 0.1 | T94: 143.85 | U94: 0 | V94: 0 | W94: 0 | X94: 0 | Y94: 28.77 | Z94: 0 | AA94: 0 | AB94: 0 | AC94: 0 | AD94: 31.08 | AE94: 203.7 | AF94: 0 | AG94: 0 | AH94: 0 | AI94: 68.5 | AJ94: 0 | AK94: 1.37 | AL94: 69.87 | AM94: 1164.95 | AN94: No | AO94: 4.255 | AP94: No | AQ94: No | AS94: 35e81f58-2cb3-4f23-8f84-37e8baa01223 | AT94: No | AX94: Yes | AY94: No
A95: 45782 | B95: 205002325907918 | D95: 45777.941 | E95: delivered | F95: regular | J95: 1200 | K95: 0 | L95: 0 | M95: 0 | N95: 0 | O95: 1200 | P95: 60 | Q95: 1260 | R95: 1260 | S95: 0.1 | T95: 126 | U95: 0 | V95: 0 | W95: 0 | X95: 0 | Y95: 25.2 | Z95: 0 | AA95: 0 | AB95: 0 | AC95: 0 | AD95: 27.22 | AE95: 178.42 | AF95: 0 | AG95: 0 | AH95: 0 | AI95: 60 | AJ95: 0 | AK95: 1.2 | AL95: 61.2 | AM95: 1020.38 | AN95: No | AO95: 1.802 | AP95: No | AQ95: No | AS95: 16ba7efa-5742-43de-b8b5-fb89beb98004,d1457f99-aa9a-4015-b838-2a8abb25f5b9 | AT95: No | AX95: Yes | AY95: No
A96: 45782 | B96: 205005693962860 | D96: 45777.98 | E96: delivered | F96: regular | J96: 575 | K96: 10 | L96: 0 | M96: 0 | N96: 0 | O96: 585 | P96: 29.26 | Q96: 614.26 | R96: 614.24 | S96: 0.1 | T96: 61.42 | U96: 0 | V96: 0 | W96: 0 | X96: 0 | Y96: 12.28 | Z96: 0 | AA96: 0 | AB96: 0 | AC96: 0 | AD96: 13.26 | AE96: 86.96 | AF96: 0 | AG96: 0 | AH96: 0 | AI96: 29.25 | AJ96: 0 | AK96: 0.58 | AL96: 29.83 | AM96: 497.44 | AN96: No | AO96: 5.212 | AP96: No | AQ96: No | AS96: 60be9fdd-ee4b-4899-8769-18142ddc7f6e | AT96: No | AX96: Yes | AY96: No
A97: 45784 | B97: 205064961587010 | D97: 45778.666 | E97: delivered | F97: regular | J97: 1170 | K97: 10 | L97: 0 | M97: 0 | N97: 0 | O97: 1180 | P97: 59 | Q97: 1239 | R97: 1239 | S97: 0.1 | T97: 123.9 | U97: 0 | V97: 0 | W97: 0 | X97: 0 | Y97: 24.78 | Z97: 0 | AA97: 0 | AB97: 0 | AC97: 0 | AD97: 26.76 | AE97: 175.44 | AF97: 0 | AG97: 0 | AH97: 0 | AI97: 59 | AJ97: 0 | AK97: 1.18 | AL97: 60.18 | AM97: 1003.38 | AN97: No | AO97: 1.451 | AP97: No | AQ97: No | AS97: cb847266-a56f-4c4c-83a6-cf74f33d8a1c | AT97: No | AX97: Yes | AY97: No
A98: 45784 | B98: 205077102596204 | D98: 45778.807 | E98: delivered | F98: regular | J98: 1350 | K98: 10 | L98: 0 | M98: 0 | N98: 0 | O98: 1360 | P98: 68 | Q98: 1428 | R98: 1428 | S98: 0.1 | T98: 142.8 | U98: 0 | V98: 0 | W98: 0 | X98: 0 | Y98: 28.56 | Z98: 0 | AA98: 0 | AB98: 0 | AC98: 0 | AD98: 30.84 | AE98: 202.2 | AF98: 0 | AG98: 0 | AH98: 0 | AI98: 68 | AJ98: 0 | AK98: 1.36 | AL98: 69.36 | AM98: 1156.44 | AN98: No | AO98: 11.08 | AP98: No | AQ98: No | AT98: No | AX98: Yes | AY98: No
A99: 45784 | B99: 205080470481036 | D99: 45778.846 | E99: delivered | F99: regular | J99: 575 | K99: 10 | L99: 0 | M99: 0 | N99: 0 | O99: 585 | P99: 29.26 | Q99: 614.26 | R99: 614.24 | S99: 0.1 | T99: 61.42 | U99: 0 | V99: 0 | W99: 0 | X99: 0 | Y99: 12.28 | Z99: 0 | AA99: 0 | AB99: 0 | AC99: 0 | AD99: 13.26 | AE99: 86.96 | AF99: 0 | AG99: 698 | AH99: 698 | AI99: 29.25 | AJ99: 0 | AK99: 0.58 | AL99: 29.83 | AM99: -200.56 | AN99: No | AO99: 10.538 | AP99: No | AQ99: No | AT99: No | AX99: No | AY99: No
A100: 45784 | B100: 205083244866572 | D100: 45778.878 | E100: delivered | F100: regular | J100: 1240 | K100: 10 | L100: 0 | M100: 123.49 | N100: 123.49 | O100: 1126.51 | P100: 56.32 | Q100: 1182.83 | R100: 1182.83 | S100: 0.1 | T100: 118.28 | U100: 0 | V100: 0 | W100: 0 | X100: 0 | Y100: 23.66 | Z100: 0 | AA100: 0 | AB100: 0 | AC100: 0 | AD100: 25.54 | AE100: 167.48 | AF100: 0 | AG100: 0 | AH100: 0 | AI100: 56.33 | AJ100: 0 | AK100: 1.13 | AL100: 57.46 | AM100: 957.89 | AN100: No | AO100: 1.802 | AP100: No | AQ100: No | AS100: 16ba7efa-5742-43de-b8b5-fb89beb98004,9e917396-79ab-45be-b9ee-13aac831ea1d,66cbf698-a359-4d45-96f7-bc8d574e7259 | AT100: No | AX100: Yes | AY100: No
...

Sheet Swiggy Orders
A1: Sl. | B1: PaymentID | C1: Order ID | D1: Order-status | E1: Order Place Time | F1: Order Acceptance Time | G1: Order Delivery Time | H1: Total Bill Amount | I1: Tax Restaurant | J1: Item-SGST | K1: Item-CGST | L1: Item-IGST | M1: PackagingCharge-SGST | N1: PackagingCharge-CGST | O1: PackagingCharge-IGST | P1: ServiceCharge-SGST | Q1: ServiceCharge-CGST | R1: ServiceCharge-IGST | S1: Item-GST-Inclusive | T1: Packaging_GST_Inclusive | U1: ServiceCharge-GST-inclusive | V1: Restaurant Trade Discount | W1: Restaurant Coupon Discount Share | X1: Packing-charge | Y1: Cancelled reason | Z1: Food-prepared <Yes/No> | AA1: Order-Cancellation-time | AB1: Edited-status | AC1: Item-count | AD1: MOU type | AE1: Cancellation-responsible-entity | AF1: Restaurant-bear | AG1: Item1 | AH1: Item2 | AI1: Item3 | AJ1: Item4 | AK1: Item5
A2: 1 | B2: {=XLOOKUP(C2,SwiggyInvoiceAnnexture!$B$3:$B992,SwiggyInvoiceAnnexture!$A$3:$A992,"Order Not Found",0,1)} -> 45763 | C2: 203323727833985 | D2: delivered | G2: 45758.547 | H2: 420 | I2: 20 | J2: 10 | K2: 10 | L2: 0 | M2: 0 | N2: 0 | O2: 0 | P2: 0 | Q2: 0 | R2: 0 | S2: FALSE | T2: FALSE | U2: FALSE | V2: 0 | W2: 0 | X2: 0 | AB2: unedited | AC2: 1 | AD2: NEW_MOU | AG2: Grilled Paneer, Spicy Grilled Paneer, Olives, Caramalized Onion_NA_1_400+8 inches
A3: 2 | B3: {=XLOOKUP(C3,SwiggyInvoiceAnnexture!$B$3:$B992,SwiggyInvoiceAnnexture!$A$3:$A992,"Order Not Found",0,1)} -> 45763 | C3: 203349440127363 | D3: delivered | E3: 45758.811 | F3: 45758.814 | G3: 45758.838 | H3: 798 | I3: 38 | J3: 18.75 | K3: 18.75 | L3: 0 | M3: 0.25 | N3: 0.25 | O3: 0 | P3: 0 | Q3: 0 | R3: 0 | S3: FALSE | T3: FALSE | U3: FALSE | V3: 0 | W3: 0 | X3: 10 | AB3: unedited | AC3: 1 | AD3: NEW_MOU | AG3: Chicken Tikka Pizza_NA_1_760+12 inches
A4: 3 | B4: {=XLOOKUP(C4,SwiggyInvoiceAnnexture!$B$3:$B992,SwiggyInvoiceAnnexture!$A$3:$A992,"Order Not Found",0,1)} -> 45763 | C4: 203359178077774 | D4: delivered | E4: 45758.924 | F4: 45758.925 | G4: 45758.959 | H4: 1312 | I4: 62.5 | J4: 31.25 | K4: 31.25 | L4: 0 | M4: 0 | N4: 0 | O4: 0 | P4: 0 | Q4: 0 | R4: 0 | S4: FALSE | T4: FALSE | U4: FALSE | V4: 0 | W4: 0 | X4: 0 | AB4: unedited | AC4: 1 | AD4: NEW_MOU | AG4: Meat Lovers Pizza_NA_1_1250+12 inches
A5: 4 | B5: {=XLOOKUP(C5,SwiggyInvoiceAnnexture!$B$3:$B992,SwiggyInvoiceAnnexture!$A$3:$A992,"Order Not Found",0,1)} -> 45763 | C5: 203433657056770 | D5: delivered | E5: 45759.785 | F5: 45759.787 | G5: 45759.813 | H5: 562 | I5: 26.76 | J5: 13.13 | K5: 13.13 | L5: 0 | M5: 0.25 | N5: 0.25 | O5: 0 | P5: 0 | Q5: 0 | R5: 0 | S5: FALSE | T5: FALSE | U5: FALSE | V5: 0 | W5: 0 | X5: 10 | AB5: unedited | AC5: 1 | AD5: NEW_MOU | AG5: Signature Truffled Bolognese Pizza, _NA_1_535+8 inches
A6: 5 | B6: {=XLOOKUP(C6,SwiggyInvoiceAnnexture!$B$3:$B992,SwiggyInvoiceAnnexture!$A$3:$A992,"Order Not Found",0,1)} -> 45763 | C6: 203435912866093 | D6: delivered | E6: 45759.812 | F6: 45759.812 | G6: 45759.835 | H6: 1171 | I6: 55.76 | J6: 27.63 | K6: 27.63 | L6: 0 | M6: 0.25 | N6: 0.25 | O6: 0 | P6: 0 | Q6: 0 | R6: 0 | S6: FALSE | T6: FALSE | U6: FALSE | V6: 0 | W6: 0 | X6: 10 | AB6: unedited | AC6: 2 | AD6: NEW_MOU | AG6: Oriental Bbq Pork With Chilly Honey_NA_1_380 | AH6: Chef Special Pizza_NA_1_735+10 inches
A7: 6 | B7: {=XLOOKUP(C7,SwiggyInvoiceAnnexture!$B$3:$B992,SwiggyInvoiceAnnexture!$A$3:$A992,"Order Not Found",0,1)} -> 45763 | C7: 203438608676679 | D7: delivered | E7: 45759.843 | F7: 45759.843 | G7: 45759.872 | H7: 1255 | I7: 59.76 | J7: 29.63 | K7: 29.63 | L7: 0 | M7: 0.25 | N7: 0.25 | O7: 0 | P7: 0 | Q7: 0 | R7: 0 | S7: FALSE | T7: FALSE | U7: FALSE | V7: 0 | W7: 0 | X7: 10 | AB7: unedited | AC7: 3 | AD7: NEW_MOU | AG7: Chef Special Pizza_NA_1_585+8 inches | AH7: Garlic Bread_NA_1_110 | AI7: Quattro Formaggi, 4varieties Of Double Cheese With Fresh Basil_NA_1_500+8 inches+Olives
A8: 7 | B8: {=XLOOKUP(C8,SwiggyInvoiceAnnexture!$B$3:$B992,SwiggyInvoiceAnnexture!$A$3:$A992,"Order Not Found",0,1)} -> 45763 | C8: 203438922167612 | D8: delivered | E8: 45759.847 | F8: 45759.847 | G8: 45759.879 | H8: 1354 | I8: 64.5 | J8: 32.25 | K8: 32.25 | L8: 0 | M8: 0 | N8: 0 | O8: 0 | P8: 0 | Q8: 0 | R8: 0 | S8: FALSE | T8: FALSE | U8: FALSE | V8: 0 | W8: 0 | X8: 0 | AB8: unedited | AC8: 2 | AD8: NEW_MOU | AG8: Meat Lovers Pizza_NA_1_1050+10 inches+Double Cheese | AH8: Loaded Fries_NA_1_240
A9: 8 | B9: {=XLOOKUP(C9,SwiggyInvoiceAnnexture!$B$3:$B992,SwiggyInvoiceAnnexture!$A$3:$A992,"Order Not Found",0,1)} -> 45770 | C9: 203508162484177 | D9: delivered | E9: 45760.648 | F9: 45760.648 | G9: 45760.672 | H9: 614 | I9: 29.26 | J9: 14.38 | K9: 14.38 | L9: 0 | M9: 0.25 | N9: 0.25 | O9: 0 | P9: 0 | Q9: 0 | R9: 0 | S9: FALSE | T9: FALSE | U9: FALSE | V9: 0 | W9: 0 | X9: 10 | AB9: unedited | AC9: 1 | AD9: NEW_MOU | AG9: Chef Special Pizza_NA_1_585+8 inches
A10: 9 | B10: {=XLOOKUP(C10,SwiggyInvoiceAnnexture!$B$3:$B992,SwiggyInvoiceAnnexture!$A$3:$A992,"Order Not Found",0,1)} -> 45770 | C10: 203521051067944 | D10: delivered | E10: 45760.797 | F10: 45760.798 | G10: 45760.829 | H10: 2005 | I10: 95.5 | J10: 47.75 | K10: 47.75 | L10: 0 | M10: 0 | N10: 0 | O10: 0 | P10: 0 | Q10: 0 | R10: 0 | S10: FALSE | T10: FALSE | U10: FALSE | V10: 0 | W10: 0 | X10: 0 | AB10: unedited | AC10: 3 | AD10: NEW_MOU | AG10: Cajun Fried Prawns Thyme Infuced Panko Dusted Fried Prawns Chilli Tomato Aioli_NA_2_780 | AH10: Moroccan Meat Balls Harissa Sauce_NA_1_380 | AI10: Crispy Salmon Tempura Roll, Acocado, Philadelphia Cream Chese, Truffle Mayo_NA_1_750
A11: 10 | B11: {=XLOOKUP(C11,SwiggyInvoiceAnnexture!$B$3:$B992,SwiggyInvoiceAnnexture!$A$3:$A992,"Order Not Found",0,1)} -> 45770 | C11: 203536479647997 | D11: delivered | E11: 45760.976 | F11: 45760.977 | G11: 45761.01 | H11: 1417 | I11: 67.5 | J11: 33.5 | K11: 33.5 | L11: 0 | M11: 0.25 | N11: 0.25 | O11: 0 | P11: 0 | Q11: 0 | R11: 0 | S11: FALSE | T11: FALSE | U11: FALSE | V11: 0 | W11: 0 | X11: 10 | AB11: unedited | AC11: 3 | AD11: NEW_MOU | AG11: Chilly Cheese Toast_NA_1_190 | AH11: Pepperoni (Chicken Or Pork)_NA_1_760+12 inches | AI11: Grilled Paneer, Spicy Grilled Paneer, Olives, Caramalized Onion_NA_1_400+8 inches
A12: 11 | B12: {=XLOOKUP(C12,SwiggyInvoiceAnnexture!$B$3:$B992,SwiggyInvoiceAnnexture!$A$3:$A992,"Order Not Found",0,1)} -> 45770 | C12: 203595884273246 | D12: delivered | E12: 45761.663 | F12: 45761.663 | G12: 45761.705 | H12: 559 | I12: 24.26 | J12: 11.88 | K12: 11.88 | L12: 0 | M12: 0.25 | N12: 0.25 | O12: 0 | P12: 0 | Q12: 0 | R12: 0 | S12: FALSE | T12: FALSE | U12: FALSE | V12: 0 | W12: 50 | X12: 10 | AB12: unedited | AC12: 1 | AD12: NEW_MOU | AG12: Turkish Meal Pizza_NA_1_535+8 inches
A13: 12 | B13: {=XLOOKUP(C13,SwiggyInvoiceAnnexture!$B$3:$B992,SwiggyInvoiceAnnexture!$A$3:$A992,"Order Not Found",0,1)} -> 45770 | C13: 203690078159199 | D13: delivered | E13: 45762.753 | F13: 45762.755 | G13: 45762.782 | H13: 780 | I13: 34.76 | J13: 17.13 | K13: 17.13 | L13: 0 | M13: 0.25 | N13: 0.25 | O13: 0 | P13: 0 | Q13: 0 | R13: 0 | S13: FALSE | T13: FALSE | U13: FALSE | V13: 0 | W13: 49.99 | X13: 10 | AB13: unedited | AC13: 2 | AD13: NEW_MOU | AG13: Potato Wedges_NA_1_160 | AH13: Chef Special Pizza_NA_1_585+8 inches
A14: 13 | B14: {=XLOOKUP(C14,SwiggyInvoiceAnnexture!$B$3:$B992,SwiggyInvoiceAnnexture!$A$3:$A992,"Order Not Found",0,1)} -> 45770 | C14: 203697189606601 | D14: delivered | E14: 45762.836 | F14: 45762.836 | G14: 45762.858 | H14: 507 | I14: 21.76 | J14: 10.63 | K14: 10.63 | L14: 0 | M14: 0.25 | N14: 0.25 | O14: 0 | P14: 0 | Q14: 0 | R14: 0 | S14: FALSE | T14: FALSE | U14: FALSE | V14: 0 | W14: 50 | X14: 10 | AB14: unedited | AC14: 1 | AD14: NEW_MOU | AG14: Jamaican Jerk Pizza_NA_1_485+8 inches
A15: 14 | B15: {=XLOOKUP(C15,SwiggyInvoiceAnnexture!$B$3:$B992,SwiggyInvoiceAnnexture!$A$3:$A992,"Order Not Found",0,1)} -> 45770 | C15: 203755054264094 | D15: delivered | E15: 45763.505 | F15: 45763.506 | G15: 45763.546 | H15: 417 | I15: 17.5 | J15: 8.75 | K15: 8.75 | L15: 0 | M15: 0 | N15: 0 | O15: 0 | P15: 0 | Q15: 0 | R15: 0 | S15: FALSE | T15: FALSE | U15: FALSE | V15: 0 | W15: 50 | X15: 0 | AB15: unedited | AC15: 1 | AD15: NEW_MOU | AG15: Grilled Paneer, Spicy Grilled Paneer, Olives, Caramalized Onion_NA_1_400+8 inches
A16: 15 | B16: {=XLOOKUP(C16,SwiggyInvoiceAnnexture!$B$3:$B992,SwiggyInvoiceAnnexture!$A$3:$A992,"Order Not Found",0,1)} -> 45770 | C16: 203761162091130 | D16: delivered | E16: 45763.576 | F16: 45763.576 | G16: 45763.605 | H16: 932 | I16: 42 | J16: 20.75 | K16: 20.75 | L16: 0 | M16: 0.25 | N16: 0.25 | O16: 0 | P16: 0 | Q16: 0 | R16: 0 | S16: FALSE | T16: FALSE | U16: FALSE | V16: 0 | W16: 50 | X16: 10 | AB16: unedited | AC16: 2 | AD16: NEW_MOU | AG16: Garlic Bread_NA_1_110 | AH16: Lebanese Chicken Pizza_NA_1_780+12 inches
A17: 16 | B17: {=XLOOKUP(C17,SwiggyInvoiceAnnexture!$B$3:$B992,SwiggyInvoiceAnnexture!$A$3:$A992,"Order Not Found",0,1)} -> 45770 | C17: 203785580997113 | D17: delivered | E17: 45763.859 | F17: 45763.859 | G17: 45763.886 | H17: 1454 | I17: 69.26 | J17: 34.13 | K17: 34.13 | L17: 0 | M17: 0.5 | N17: 0.5 | O17: 0 | P17: 0 | Q17: 0 | R17: 0 | S17: FALSE | T17: FALSE | U17: FALSE | V17: 0 | W17: 0 | X17: 20 | AB17: unedited | AC17: 2 | AD17: NEW_MOU | AG17: Chef Special Pizza_NA_1_735+10 inches | AH17: Diavola_NA_1_650+10 inches
A18: 17 | B18: {=XLOOKUP(C18,SwiggyInvoiceAnnexture!$B$3:$B992,SwiggyInvoiceAnnexture!$A$3:$A992,"Order Not Found",0,1)} -> 45770 | C18: 203788164490719 | D18: delivered | E18: 45763.889 | F18: 45763.89 | G18: 45763.914 | H18: 759 | I18: 33.76 | J18: 16.88 | K18: 16.88 | L18: 0 | M18: 0 | N18: 0 | O18: 0 | P18: 0 | Q18: 0 | R18: 0 | S18: FALSE | T18: FALSE | U18: FALSE | V18: 0 | W18: 50 | X18: 0 | AB18: unedited | AC18: 1 | AD18: NEW_MOU | AG18: Meat Lovers Pizza_NA_1_725+8 inches+Double Cheese
A19: 18 | B19: {=XLOOKUP(C19,SwiggyInvoiceAnnexture!$B$3:$B992,SwiggyInvoiceAnnexture!$A$3:$A992,"Order Not Found",0,1)} -> 45770 | C19: 203862521805423 | D19: delivered | E19: 45764.749 | F19: 45764.752 | G19: 45764.772 | H19: 612 | I19: 26.76 | J19: 13.13 | K19: 13.13 | L19: 0 | M19: 0.25 | N19: 0.25 | O19: 0 | P19: 0 | Q19: 0 | R19: 0 | S19: FALSE | T19: FALSE | U19: FALSE | V19: 0 | W19: 50 | X19: 10 | AB19: unedited | AC19: 1 | AD19: NEW_MOU | AG19: Chef Special Pizza_NA_1_585+8 inches
A20: 19 | B20: {=XLOOKUP(C20,SwiggyInvoiceAnnexture!$B$3:$B992,SwiggyInvoiceAnnexture!$A$3:$A992,"Order Not Found",0,1)} -> 45770 | C20: 203867191085444 | D20: delivered | E20: 45764.804 | F20: 45764.805 | G20: 45764.824 | H20: 795 | I20: 35.5 | J20: 17.5 | K20: 17.5 | L20: 0 | M20: 0.25 | N20: 0.25 | O20: 0 | P20: 0 | Q20: 0 | R20: 0 | S20: FALSE | T20: FALSE | U20: FALSE | V20: 0 | W20: 50 | X20: 10 | AB20: unedited | AC20: 1 | AD20: NEW_MOU | AG20: Chicken Tikka Pizza_NA_1_760+12 inches
A21: 20 | B21: {=XLOOKUP(C21,SwiggyInvoiceAnnexture!$B$3:$B992,SwiggyInvoiceAnnexture!$A$3:$A992,"Order Not Found",0,1)} -> 45770 | C21: 204035770284769 | D21: delivered | E21: 45766.754 | F21: 45766.756 | G21: 45766.784 | H21: 1244 | I21: 59.26 | J21: 29.63 | K21: 29.63 | L21: 0 | M21: 0 | N21: 0 | O21: 0 | P21: 0 | Q21: 0 | R21: 0 | S21: FALSE | T21: FALSE | U21: FALSE | V21: 0 | W21: 0 | X21: 0 | AB21: edited | AC21: 2 | AD21: NEW_MOU | AG21: Chefs Signature Spaghetti Bolognese, Slow Cooked Minced Beef, Tomato and Basil_NA_1_460 | AH21: Meat Lovers Pizza_NA_1_725+8 inches
A22: 21 | B22: {=XLOOKUP(C22,SwiggyInvoiceAnnexture!$B$3:$B992,SwiggyInvoiceAnnexture!$A$3:$A992,"Order Not Found",0,1)} -> 45770 | C22: 204042752030857 | D22: delivered | E22: 45766.835 | F22: 45766.836 | G22: 45766.868 | H22: 1102 | I22: 52.5 | J22: 26.25 | K22: 26.25 | L22: 0 | M22: 0 | N22: 0 | O22: 0 | P22: 0 | Q22: 0 | R22: 0 | S22: FALSE | T22: FALSE | U22: FALSE | V22: 0 | W22: 0 | X22: 0 | AB22: unedited | AC22: 1 | AD22: NEW_MOU | AG22: Meat Lovers Pizza_NA_1_1050+10 inches
A23: 22 | B23: {=XLOOKUP(C23,SwiggyInvoiceAnnexture!$B$3:$B992,SwiggyInvoiceAnnexture!$A$3:$A992,"Order Not Found",0,1)} -> 45770 | C23: 204051867574558 | D23: cancelled | E23: 45766.941 | F23: 45766.942 | H23: 509 | I23: 24.26 | J23: 11.88 | K23: 11.88 | L23: 0 | M23: 0.25 | N23: 0.25 | O23: 0 | P23: 0 | Q23: 0 | R23: 0 | S23: FALSE | T23: FALSE | U23: FALSE | V23: 0 | W23: 0 | X23: 10 | Y23: 14 | AA23: 45766.997 | AB23: unedited | AC23: 1 | AD23: NEW_MOU | AE23: CUSTOMER | AG23: Chicken Tikka Pizza_NA_1_485+8 inches
A24: 23 | B24: {=XLOOKUP(C24,SwiggyInvoiceAnnexture!$B$3:$B992,SwiggyInvoiceAnnexture!$A$3:$A992,"Order Not Found",0,1)} -> 45770 | C24: 204052645766134 | D24: delivered | E24: 45766.95 | F24: 45766.95 | G24: 45766.981 | H24: 509 | I24: 24.26 | J24: 11.88 | K24: 11.88 | L24: 0 | M24: 0.25 | N24: 0.25 | O24: 0 | P24: 0 | Q24: 0 | R24: 0 | S24: FALSE | T24: FALSE | U24: FALSE | V24: 0 | W24: 0 | X24: 10 | AB24: unedited | AC24: 1 | AD24: NEW_MOU | AG24: Chicken Tikka Pizza_NA_1_485+8 inches
A25: 24 | B25: {=XLOOKUP(C25,SwiggyInvoiceAnnexture!$B$3:$B992,SwiggyInvoiceAnnexture!$A$3:$A992,"Order Not Found",0,1)} -> 45777 | C25: 204102083771100 | D25: delivered | E25: 45767.522 | F25: 45767.523 | G25: 45767.572 | H25: 919 | I25: 43.76 | J25: 21.88 | K25: 21.88 | L25: 0 | M25: 0 | N25: 0 | O25: 0 | P25: 0 | Q25: 0 | R25: 0 | S25: FALSE | T25: FALSE | U25: FALSE | V25: 0 | W25: 0 | X25: 0 | AB25: unedited | AC25: 3 | AD25: NEW_MOU | AG25: Grilled Paneer, Spicy Grilled Paneer, Olives, Caramalized Onion_NA_1_525+10 inches+Double Cheese | AH25: Garlic Bread_NA_1_110 | AI25: Loaded Fries_NA_1_240
A26: 25 | B26: {=XLOOKUP(C26,SwiggyInvoiceAnnexture!$B$3:$B992,SwiggyInvoiceAnnexture!$A$3:$A992,"Order Not Found",0,1)} -> 45777 | C26: 204124492278368 | D26: delivered | E26: 45767.781 | F26: 45767.782 | G26: 45767.802 | H26: 420 | I26: 20 | J26: 10 | K26: 10 | L26: 0 | M26: 0 | N26: 0 | O26: 0 | P26: 0 | Q26: 0 | R26: 0 | S26: FALSE | T26: FALSE | U26: FALSE | V26: 0 | W26: 0 | X26: 0 | AB26: unedited | AC26: 1 | AD26: NEW_MOU | AG26: Grilled Paneer, Spicy Grilled Paneer, Olives, Caramalized Onion_NA_1_400+8 inches
A27: 26 | B27: {=XLOOKUP(C27,SwiggyInvoiceAnnexture!$B$3:$B992,SwiggyInvoiceAnnexture!$A$3:$A992,"Order Not Found",0,1)} -> 45777 | C27: 204124647404444 | D27: delivered | E27: 45767.783 | F27: 45767.783 | G27: 45767.803 | H27: 1129 | I27: 53.76 | J27: 26.63 | K27: 26.63 | L27: 0 | M27: 0.25 | N27: 0.25 | O27: 0 | P27: 0 | Q27: 0 | R27: 0 | S27: FALSE | T27: FALSE | U27: FALSE | V27: 0 | W27: 0 | X27: 10 | AB27: unedited | AC27: 2 | AD27: NEW_MOU | AG27: Cajun Fried Prawns Thyme Infuced Panko Dusted Fried Prawns Chilli Tomato Aioli_NA_1_390 | AH27: Signature Truffled Bolognese Pizza, _NA_1_685+10 inches
A28: 27 | B28: {=XLOOKUP(C28,SwiggyInvoiceAnnexture!$B$3:$B992,SwiggyInvoiceAnnexture!$A$3:$A992,"Order Not Found",0,1)} -> 45777 | C28: 204212905215057 | D28: delivered | E28: 45768.804 | F28: 45768.807 | G28: 45768.846 | H28: 1034 | I28: 49.26 | J28: 24.38 | K28: 24.38 | L28: 0 | M28: 0.25 | N28: 0.25 | O28: 0 | P28: 0 | Q28: 0 | R28: 0 | S28: FALSE | T28: FALSE | U28: FALSE | V28: 0 | W28: 0 | X28: 10 | AB28: unedited | AC28: 3 | AD28: NEW_MOU | AG28: Garlic Bread_NA_1_110 | AH28: Loaded Fries_NA_1_240 | AI28: Chicken Tikka Pizza_NA_1_635+10 inches
A29: 28 | B29: {=XLOOKUP(C29,SwiggyInvoiceAnnexture!$B$3:$B992,SwiggyInvoiceAnnexture!$A$3:$A992,"Order Not Found",0,1)} -> 45777 | C29: 204215490761230 | D29: delivered | E29: 45768.835 | F29: 45768.835 | G29: 45768.858 | H29: 2121 | I29: 101 | J29: 49.75 | K29: 49.75 | L29: 0 | M29: 0.75 | N29: 0.75 | O29: 0 | P29: 0 | Q29: 0 | R29: 0 | S29: FALSE | T29: FALSE | U29: FALSE | V29: 0 | W29: 0 | X29: 30 | AB29: unedited | AC29: 4 | AD29: NEW_MOU | AG29: Diavola_NA_1_650+10 inches | AH29: Pepperoni (Chicken Or Pork)_NA_1_485+8 inches | AI29: Premavera, Assorted Selection Of Veggies, Paneer and Mushrooms_NA_1_400+8 inches | AJ29: Bbq Chicken Pizza_NA_1_485+8 inches
A30: 29 | B30: {=XLOOKUP(C30,SwiggyInvoiceAnnexture!$B$3:$B992,SwiggyInvoiceAnnexture!$A$3:$A992,"Order Not Found",0,1)} -> 45777 | C30: 204218347708026 | D30: delivered | E30: 45768.868 | F30: 45768.871 | G30: 45768.912 | H30: 1097 | I30: 52.26 | J30: 25.88 | K30: 25.88 | L30: 0 | M30: 0.25 | N30: 0.25 | O30: 0 | P30: 0 | Q30: 0 | R30: 0 | S30: FALSE | T30: FALSE | U30: FALSE | V30: 0 | W30: 0 | X30: 10 | AB30: unedited | AC30: 2 | AD30: NEW_MOU | AG30: Chilly Cheese Toast_NA_1_190 | AH30: Chef Special Pizza_NA_1_855+10 inches+Double Cheese Pepperoni (Chicken Or Pork)
A31: 30 | B31: {=XLOOKUP(C31,SwiggyInvoiceAnnexture!$B$3:$B992,SwiggyInvoiceAnnexture!$A$3:$A992,"Order Not Found",0,1)} -> 45777 | C31: 204222343884996 | D31: delivered | E31: 45768.914 | F31: 45768.916 | G31: 45768.956 | H31: 793 | I31: 37.76 | J31: 18.63 | K31: 18.63 | L31: 0 | M31: 0.25 | N31: 0.25 | O31: 0 | P31: 0 | Q31: 0 | R31: 0 | S31: FALSE | T31: FALSE | U31: FALSE | V31: 0 | W31: 0 | X31: 10 | AB31: unedited | AC31: 1 | AD31: NEW_MOU | AG31: Jamaican Jerk Pizza_NA_1_755+10 inches+Pepperoni (Chicken Or Pork)
A32: 31 | B32: {=XLOOKUP(C32,SwiggyInvoiceAnnexture!$B$3:$B992,SwiggyInvoiceAnnexture!$A$3:$A992,"Order Not Found",0,1)} -> 45777 | C32: 204287737282944 | D32: delivered | E32: 45769.671 | F32: 45769.673 | G32: 45769.705 | H32: 530 | I32: 25.26 | J32: 12.38 | K32: 12.38 | L32: 0 | M32: 0.25 | N32: 0.25 | O32: 0 | P32: 0 | Q32: 0 | R32: 0 | S32: FALSE | T32: FALSE | U32: FALSE | V32: 0 | W32: 0 | X32: 10 | AB32: unedited | AC32: 1 | AD32: NEW_MOU | AG32: Lebanese Chicken Pizza_NA_1_505+8 inches
A33: 32 | B33: {=XLOOKUP(C33,SwiggyInvoiceAnnexture!$B$3:$B992,SwiggyInvoiceAnnexture!$A$3:$A992,"Order Not Found",0,1)} -> 45777 | C33: 204288821088966 | D33: delivered | E33: 45769.683 | F33: 45769.685 | G33: 45769.724 | H33: 1664 | I33: 79.26 | J33: 39.13 | K33: 39.13 | L33: 0 | M33: 0.5 | N33: 0.5 | O33: 0 | P33: 0 | Q33: 0 | R33: 0 | S33: FALSE | T33: FALSE | U33: FALSE | V33: 0 | W33: 0 | X33: 20 | AB33: unedited | AC33: 2 | AD33: NEW_MOU | AG33: Signature Truffled Bolognese Pizza, _NA_1_810+12 inches+Double Cheese | AH33: Diavola_NA_1_775+12 inches+Double Cheese
A34: 33 | B34: {=XLOOKUP(C34,SwiggyInvoiceAnnexture!$B$3:$B992,SwiggyInvoiceAnnexture!$A$3:$A992,"Order Not Found",0,1)} -> 45777 | C34: 204292365396131 | D34: delivered | E34: 45769.724 | F34: 45769.725 | G34: 45769.754 | H34: 614 | I34: 29.26 | J34: 14.38 | K34: 14.38 | L34: 0 | M34: 0.25 | N34: 0.25 | O34: 0 | P34: 0 | Q34: 0 | R34: 0 | S34: FALSE | T34: FALSE | U34: FALSE | V34: 0 | W34: 0 | X34: 10 | AB34: unedited | AC34: 1 | AD34: NEW_MOU | AG34: Chef Special Pizza_NA_1_585+8 inches+Double Cheese
A35: 34 | B35: {=XLOOKUP(C35,SwiggyInvoiceAnnexture!$B$3:$B992,SwiggyInvoiceAnnexture!$A$3:$A992,"Order Not Found",0,1)} -> 45777 | C35: 204294771366388 | D35: delivered | E35: 45769.752 | F35: 45769.752 | G35: 45769.765 | H35: 168 | I35: 8 | J35: 4 | K35: 4 | L35: 0 | M35: 0 | N35: 0 | O35: 0 | P35: 0 | Q35: 0 | R35: 0 | S35: FALSE | T35: FALSE | U35: FALSE | V35: 0 | W35: 0 | X35: 0 | AB35: unedited | AC35: 1 | AD35: NEW_MOU | AG35: Potato Wedges_NA_1_160
A36: 35 | B36: {=XLOOKUP(C36,SwiggyInvoiceAnnexture!$B$3:$B992,SwiggyInvoiceAnnexture!$A$3:$A992,"Order Not Found",0,1)} -> 45777 | C36: 204299841075979 | D36: delivered | E36: 45769.811 | F36: 45769.813 | G36: 45769.827 | H36: 614 | I36: 29.26 | J36: 14.38 | K36: 14.38 | L36: 0 | M36: 0.25 | N36: 0.25 | O36: 0 | P36: 0 | Q36: 0 | R36: 0 | S36: FALSE | T36: FALSE | U36: FALSE | V36: 0 | W36: 0 | X36: 10 | AB36: unedited | AC36: 1 | AD36: NEW_MOU | AG36: Chef Special Pizza_NA_1_585+8 inches
A37: 36 | B37: {=XLOOKUP(C37,SwiggyInvoiceAnnexture!$B$3:$B992,SwiggyInvoiceAnnexture!$A$3:$A992,"Order Not Found",0,1)} -> 45777 | C37: 204300656245087 | D37: delivered | E37: 45769.82 | F37: 45769.82 | G37: 45769.845 | H37: 1024 | I37: 48.76 | J37: 24.13 | K37: 24.13 | L37: 0 | M37: 0.25 | N37: 0.25 | O37: 0 | P37: 0 | Q37: 0 | R37: 0 | S37: FALSE | T37: FALSE | U37: FALSE | V37: 0 | W37: 0 | X37: 10 | AB37: unedited | AC37: 2 | AD37: NEW_MOU | AG37: Chicken Quesadilla, Cajun Marinated Chicken, Crispy Tortilla Sour Cream_NA_1_390 | AH37: Chef Special Pizza_NA_1_585+8 inches
A38: 37 | B38: {=XLOOKUP(C38,SwiggyInvoiceAnnexture!$B$3:$B992,SwiggyInvoiceAnnexture!$A$3:$A992,"Order Not Found",0,1)} -> 45777 | C38: 204303850607557 | D38: delivered | E38: 45769.857 | F38: 45769.858 | G38: 45769.887 | H38: 1575 | I38: 75 | J38: 37.25 | K38: 37.25 | L38: 0 | M38: 0.25 | N38: 0.25 | O38: 0 | P38: 0 | Q38: 0 | R38: 0 | S38: FALSE | T38: FALSE | U38: FALSE | V38: 0 | W38: 0 | X38: 10 | AB38: unedited | AC38: 3 | AD38: NEW_MOU | AG38: Loaded Fries_NA_1_240 | AH38: Signature Truffled Bolognese Pizza, _NA_1_535+8 inches | AI38: Meat Lovers Pizza_NA_1_725+8 inches
A39: 38 | B39: {=XLOOKUP(C39,SwiggyInvoiceAnnexture!$B$3:$B992,SwiggyInvoiceAnnexture!$A$3:$A992,"Order Not Found",0,1)} -> 45777 | C39: 204305353193813 | D39: delivered | E39: 45769.875 | F39: 45769.875 | G39: 45769.893 | H39: 614 | I39: 29.26 | J39: 14.38 | K39: 14.38 | L39: 0 | M39: 0.25 | N39: 0.25 | O39: 0 | P39: 0 | Q39: 0 | R39: 0 | S39: FALSE | T39: FALSE | U39: FALSE | V39: 0 | W39: 0 | X39: 10 | AB39: unedited | AC39: 1 | AD39: NEW_MOU | AG39: Chef Special Pizza_NA_1_585+8 inches+Double Cheese
A40: 39 | B40: {=XLOOKUP(C40,SwiggyInvoiceAnnexture!$B$3:$B992,SwiggyInvoiceAnnexture!$A$3:$A992,"Order Not Found",0,1)} -> 45777 | C40: 204359894567486 | D40: delivered | E40: 45770.506 | F40: 45770.508 | G40: 45770.536 | H40: 530 | I40: 25.26 | J40: 12.38 | K40: 12.38 | L40: 0 | M40: 0.25 | N40: 0.25 | O40: 0 | P40: 0 | Q40: 0 | R40: 0 | S40: FALSE | T40: FALSE | U40: FALSE | V40: 0 | W40: 0 | X40: 10 | AB40: unedited | AC40: 1 | AD40: NEW_MOU | AG40: Lebanese Chicken Pizza_NA_1_505+8 inches
